Workbook

Sheet Master Dashboard
B1: MASTER DASHBOARD — DISTRICT PRIORITY AGENDA REVIEW, LUDHIANA
B2: Auto roll-up | Data as on 05-06-2026 | Cadence: every 3–4 days / before each weekly review
B3: ⚙ Auto-Flag Threshold (× Flag-Bar for achievement rules):
B4: 1 | C4: 1.00 = flag anyone below the Flag-Bar; lower (e.g. 0.90) for stricter.
A6: # | B6: Officer / Tab | C6: Total KPIs | D6: Completed | E6: On Track | F6: In Progress | G6: Pending/Blocked | H6: Not Started | I6: % Done | J6: 🔴 Flags
A7: 1 | B7: ADC (G) | C7: =COUNTIF('ADC (G)'!K3:K1997,"?*") -> 111 | D7: =COUNTIF('ADC (G)'!K3:K1997,"Completed") -> 1 | E7: =COUNTIF('ADC (G)'!K3:K1997,"On Track") -> 10 | F7: =COUNTIF('ADC (G)'!K3:K1997,"In Progress") -> 82 | G7: =COUNTIF('ADC (G)'!K3:K1997,"Pending/Blocked") -> 18 | H7: =COUNTIF('ADC (G)'!K3:K1997,"Not Started") -> 0 | I7: =IF(C7=0,0,(D7+E7)/C7) -> 0.099099099 | J7: =COUNTIF('ADC (G)'!L3:L1997,"*🔴*") -> 54
A8: 2 | B8: ADC (RD) | C8: =COUNTIF('ADC (RD)'!K3:K2000,"?*") -> 71 | D8: =COUNTIF('ADC (RD)'!K3:K2000,"Completed") -> 4 | E8: =COUNTIF('ADC (RD)'!K3:K2000,"On Track") -> 2 | F8: =COUNTIF('ADC (RD)'!K3:K2000,"In Progress") -> 44 | G8: =COUNTIF('ADC (RD)'!K3:K2000,"Pending/Blocked") -> 19 | H8: =COUNTIF('ADC (RD)'!K3:K2000,"Not Started") -> 2 | I8: =IF(C8=0,0,(D8+E8)/C8) -> 0.084507042 | J8: =COUNTIF('ADC (RD)'!L3:L2000,"*🔴*") -> 36
A9: 3 | B9: ADC (UD) | C9: =COUNTIF('ADC (UD)'!K3:K2000,"?*") -> 9 | D9: =COUNTIF('ADC (UD)'!K3:K2000,"Completed") -> 0 | E9: =COUNTIF('ADC (UD)'!K3:K2000,"On Track") -> 0 | F9: =COUNTIF('ADC (UD)'!K3:K2000,"In Progress") -> 6 | G9: =COUNTIF('ADC (UD)'!K3:K2000,"Pending/Blocked") -> 3 | H9: =COUNTIF('ADC (UD)'!K3:K2000,"Not Started") -> 0 | I9: =IF(C9=0,0,(D9+E9)/C9) -> 0 | J9: =COUNTIF('ADC (UD)'!L3:L2000,"*🔴*") -> 2
A10: 4 | B10: ADC (J) | C10: =COUNTIF('ADC (J)'!K3:K2000,"?*") -> 12 | D10: =COUNTIF('ADC (J)'!K3:K2000,"Completed") -> 1 | E10: =COUNTIF('ADC (J)'!K3:K2000,"On Track") -> 0 | F10: =COUNTIF('ADC (J)'!K3:K2000,"In Progress") -> 5 | G10: =COUNTIF('ADC (J)'!K3:K2000,"Pending/Blocked") -> 6 | H10: =COUNTIF('ADC (J)'!K3:K2000,"Not Started") -> 0 | I10: =IF(C10=0,0,(D10+E10)/C10) -> 0.083333333 | J10: =COUNTIF('ADC (J)'!L3:L2000,"*🔴*") -> 3
A11: 5 | B11: ADC (K) | C11: =COUNTIF('ADC (K)'!K3:K2000,"?*") -> 10 | D11: =COUNTIF('ADC (K)'!K3:K2000,"Completed") -> 0 | E11: =COUNTIF('ADC (K)'!K3:K2000,"On Track") -> 0 | F11: =COUNTIF('ADC (K)'!K3:K2000,"In Progress") -> 6 | G11: =COUNTIF('ADC (K)'!K3:K2000,"Pending/Blocked") -> 4 | H11: =COUNTIF('ADC (K)'!K3:K2000,"Not Started") -> 0 | I11: =IF(C11=0,0,(D11+E11)/C11) -> 0 | J11: =COUNTIF('ADC (K)'!L3:L2000,"*🔴*") -> 5
A12: 6 | B12: CMFO | C12: =COUNTIF(CMFO!K3:K2000,"?*") -> 39 | D12: =COUNTIF(CMFO!K3:K2000,"Completed") -> 0 | E12: =COUNTIF(CMFO!K3:K2000,"On Track") -> 0 | F12: =COUNTIF(CMFO!K3:K2000,"In Progress") -> 13 | G12: =COUNTIF(CMFO!K3:K2000,"Pending/Blocked") -> 26 | H12: =COUNTIF(CMFO!K3:K2000,"Not Started") -> 0 | I12: =IF(C12=0,0,(D12+E12)/C12) -> 0 | J12: =COUNTIF(CMFO!L3:L2000,"*🔴*") -> 20
A13: 7 | B13: AC (G) | C13: =COUNTIF('AC (G)'!K3:K2000,"?*") -> 30 | D13: =COUNTIF('AC (G)'!K3:K2000,"Completed") -> 3 | E13: =COUNTIF('AC (G)'!K3:K2000,"On Track") -> 1 | F13: =COUNTIF('AC (G)'!K3:K2000,"In Progress") -> 18 | G13: =COUNTIF('AC (G)'!K3:K2000,"Pending/Blocked") -> 8 | H13: =COUNTIF('AC (G)'!K3:K2000,"Not Started") -> 0 | I13: =IF(C13=0,0,(D13+E13)/C13) -> 0.13333333 | J13: =COUNTIF('AC (G)'!L3:L2000,"*🔴*") -> 11
A14: 8 | B14: DRO | C14: =COUNTIF(DRO!K3:K2000,"?*") -> 18 | D14: =COUNTIF(DRO!K3:K2000,"Completed") -> 0 | E14: =COUNTIF(DRO!K3:K2000,"On Track") -> 0 | F14: =COUNTIF(DRO!K3:K2000,"In Progress") -> 13 | G14: =COUNTIF(DRO!K3:K2000,"Pending/Blocked") -> 5 | H14: =COUNTIF(DRO!K3:K2000,"Not Started") -> 0 | I14: =IF(C14=0,0,(D14+E14)/C14) -> 0 | J14: =COUNTIF(DRO!L3:L2000,"*🔴*") -> 5
A15: 9 | B15: SDM Samrala | C15: =COUNTIF('SDM Samrala'!K3:K2000,"?*") -> 6 | D15: =COUNTIF('SDM Samrala'!K3:K2000,"Completed") -> 0 | E15: =COUNTIF('SDM Samrala'!K3:K2000,"On Track") -> 0 | F15: =COUNTIF('SDM Samrala'!K3:K2000,"In Progress") -> 1 | G15: =COUNTIF('SDM Samrala'!K3:K2000,"Pending/Blocked") -> 5 | H15: =COUNTIF('SDM Samrala'!K3:K2000,"Not Started") -> 0 | I15: =IF(C15=0,0,(D15+E15)/C15) -> 0 | J15: =COUNTIF('SDM Samrala'!L3:L2000,"*🔴*") -> 2
A16: 10 | B16: SDM Jagraon | C16: =COUNTIF('SDM Jagraon'!K3:K2000,"?*") -> 6 | D16: =COUNTIF('SDM Jagraon'!K3:K2000,"Completed") -> 0 | E16: =COUNTIF('SDM Jagraon'!K3:K2000,"On Track") -> 0 | F16: =COUNTIF('SDM Jagraon'!K3:K2000,"In Progress") -> 2 | G16: =COUNTIF('SDM Jagraon'!K3:K2000,"Pending/Blocked") -> 4 | H16: =COUNTIF('SDM Jagraon'!K3:K2000,"Not Started") -> 0 | I16: =IF(C16=0,0,(D16+E16)/C16) -> 0 | J16: =COUNTIF('SDM Jagraon'!L3:L2000,"*🔴*") -> 1
A17: 11 | B17: SDM Payal | C17: =COUNTIF('SDM Payal'!K3:K2000,"?*") -> 6 | D17: =COUNTIF('SDM Payal'!K3:K2000,"Completed") -> 0 | E17: =COUNTIF('SDM Payal'!K3:K2000,"On Track") -> 0 | F17: =COUNTIF('SDM Payal'!K3:K2000,"In Progress") -> 5 | G17: =COUNTIF('SDM Payal'!K3:K2000,"Pending/Blocked") -> 1 | H17: =COUNTIF('SDM Payal'!K3:K2000,"Not Started") -> 0 | I17: =IF(C17=0,0,(D17+E17)/C17) -> 0 | J17: =COUNTIF('SDM Payal'!L3:L2000,"*🔴*") -> 1
A18: 12 | B18: SDM East | C18: =COUNTIF('SDM East'!K3:K2000,"?*") -> 9 | D18: =COUNTIF('SDM East'!K3:K2000,"Completed") -> 0 | E18: =COUNTIF('SDM East'!K3:K2000,"On Track") -> 0 | F18: =COUNTIF('SDM East'!K3:K2000,"In Progress") -> 3 | G18: =COUNTIF('SDM East'!K3:K2000,"Pending/Blocked") -> 6 | H18: =COUNTIF('SDM East'!K3:K2000,"Not Started") -> 0 | I18: =IF(C18=0,0,(D18+E18)/C18) -> 0 | J18: =COUNTIF('SDM East'!L3:L2000,"*🔴*") -> 0
A19: 13 | B19: SDM West | C19: =COUNTIF('SDM West'!K3:K2000,"?*") -> 10 | D19: =COUNTIF('SDM West'!K3:K2000,"Completed") -> 0 | E19: =COUNTIF('SDM West'!K3:K2000,"On Track") -> 0 | F19: =COUNTIF('SDM West'!K3:K2000,"In Progress") -> 5 | G19: =COUNTIF('SDM West'!K3:K2000,"Pending/Blocked") -> 5 | H19: =COUNTIF('SDM West'!K3:K2000,"Not Started") -> 0 | I19: =IF(C19=0,0,(D19+E19)/C19) -> 0 | J19: =COUNTIF('SDM West'!L3:L2000,"*🔴*") -> 3
A20: 14 | B20: SDM Raikot | C20: =COUNTIF('SDM Raikot'!K3:K2000,"?*") -> 7 | D20: =COUNTIF('SDM Raikot'!K3:K2000,"Completed") -> 1 | E20: =COUNTIF('SDM Raikot'!K3:K2000,"On Track") -> 0 | F20: =COUNTIF('SDM Raikot'!K3:K2000,"In Progress") -> 4 | G20: =COUNTIF('SDM Raikot'!K3:K2000,"Pending/Blocked") -> 2 | H20: =COUNTIF('SDM Raikot'!K3:K2000,"Not Started") -> 0 | I20: =IF(C20=0,0,(D20+E20)/C20) -> 0.14285714 | J20: =COUNTIF('SDM Raikot'!L3:L2000,"*🔴*") -> 1
A21: 15 | B21: RTA | C21: =COUNTIF(RTA!K3:K2000,"?*") -> 5 | D21: =COUNTIF(RTA!K3:K2000,"Completed") -> 0 | E21: =COUNTIF(RTA!K3:K2000,"On Track") -> 0 | F21: =COUNTIF(RTA!K3:K2000,"In Progress") -> 5 | G21: =COUNTIF(RTA!K3:K2000,"Pending/Blocked") -> 0 | H21: =COUNTIF(RTA!K3:K2000,"Not Started") -> 0 | I21: =IF(C21=0,0,(D21+E21)/C21) -> 0 | J21: =COUNTIF(RTA!L3:L2000,"*🔴*") -> 0
B22: DISTRICT TOTAL | C22: =SUM(C7:C21) -> 349 | D22: =SUM(D7:D21) -> 10 | E22: =SUM(E7:E21) -> 13 | F22: =SUM(F7:F21) -> 212 | G22: =SUM(G7:G21) -> 112 | H22: =SUM(H7:H21) -> 2 | I22: =IF(C22=0,0,(D22+E22)/C22) -> 0.065902579 | J22: =SUM(J7:J21) -> 144
B24: WEEKLY MEETING FOCUS
B25: • Each officer tab shows SCHEMES (metrics) first, then PRIORITY TASKS — take highest 🔴 Flags + Pending first.
B26: • Each scheme opens with a 📊 SNAPSHOT band of headline totals.
B27: • Filter any tab's 'Auto-Flag' for 🔴 to list that officer's at-risk items.
B28: • Connect officer workbooks via the 'Data Connections' tab to make figures auto-refresh.

Sheet Instructions
B1: OFFICE OF THE DEPUTY COMMISSIONER-CUM-DISTRICT MAGISTRATE, LUDHIANA
B2: MASTER PRIORITY AGENDA — REVIEW & TRACKING (DC consolidated)
B4: Purpose | C4: DC's consolidated view of all priority agendas. Data is fed up from each officer's own workbook (see 'Data Connections' tab). The DC runs the weekly review from here + the Master Dashboard.
B5: Two-tier design | C5: Each officer maintains their OWN workbook (one tab per scheme + a Priority Tasks tab). Those cells link into this master via IMPORTRANGE. Update once in the officer workbook → flows up here.
B7: Each officer tab is split | C7: ▣ SCHEMES (metric-based) — quantitative agendas with targets, shown FIRST under a blue banner. ▣ PRIORITY TASKS (qualitative) — assigned tasks, shown BELOW under a gold banner.
B9: 📊 SNAPSHOT band | C9: Each scheme opens with light-blue bold headline totals (e.g. Rangla P-I: Total/Started/In Progress/Completed/Not Started).
B10: Auto bottom-performer flag | C10: 🔴 LOW (below Flag-Bar) / 🔴 HIGH (above pendency ceiling). Threshold on Master Dashboard B4. Manual override via 'Bottom Performer' column (Auto/Yes/No).
B11: Linking | C11: Until officer workbook URLs are pasted (Data Connections tab), the figures here are the 04–05 Jun headline values. After linking, Current/Status/Flag auto-refresh from each officer workbook.
B12: MLA Works | C12: MLA constituency works remain in the separate linked MLA Works List sheet (unchanged).

Sheet ADC (G)
A1: ADC (G) — Priority Agenda Review | DC Ludhiana (MASTER)
A2: Sr | B2: Priority Agenda | C2: KPI / Metric | D2: Concerned Officer / Unit | E2: Target / Total | F2: Flag Bar | G2: Last Value | H2: Current Value | I2: Change | J2: Achieved % | K2: Status | L2: Auto-Flag | M2: Bottom Performer | N2: Updated By | O2: Update Date | P2: Remarks / Context / Pending Action | Q2: Rule | R2: Key
A3: ▣ SCHEMES — metric-based (fed from officer workbook)
A4: 1 | B4: MMSBY — Sehat Bima Yojna | C4: 📊 Total cards made — cumulative 26 May–04 Jun | H4: 7669 | P4: District total across all ACs incl. not-mapped (5,917 dept-channel + 1,752 Sewa-Kendra).
C5: 📊 Cards made today — 04 Jun | H5: 921 | P5: All channels combined on 04 Jun (674 dept + 247 Sewa-Kendra).
C6: 📊 Cards NOT mapped to any AC | H6: 186 | P6: Generated but not yet linked to an Assembly Constituency — to be reassigned.
C7: 📊 Nodals yet to fill Phase-18 sheet | H7: 6 | P7: Sahnewal, Payal, Khanna, Dakha, Samrala, Atam Nagar.
C8: Total cards — 04 Jun (single day) | D8: cards | H8: 921 | I8: =IF(AND(ISNUMBER(G8),ISNUMBER(H8)),H8-G8,"") | J8: =IF(AND(ISNUMBER(E8),E8>0,ISNUMBER(H8)),H8/E8,"") | K8: In Progress | L8: =IF(M8="Yes","🔴 BOTTOM",IF(M8="No","✓ Cleared",IF(Q8="MIN",IF(AND(ISNUMBER(F8),ISNUMBER(H8)),IF(H8<F8*'Master Dashboard'!$B$4,"🔴 LOW",""),""),IF(Q8="MAX",IF(AND(ISNUMBER(F8),ISNUMBER(H8)),IF(H8>F8,"🔴 HIGH",""),""),"")))) | M8: Auto | N8: Gov Cell (report) | O8: 05-06-2026 | P8: 674 dept + 247 SK | R8: ADCG-001
C9: Total cards — cumulative 26 May–04 Jun | D9: cards | H9: 7669 | I9: =IF(AND(ISNUMBER(G9),ISNUMBER(H9)),H9-G9,"") | J9: =IF(AND(ISNUMBER(E9),E9>0,ISNUMBER(H9)),H9/E9,"") | K9: In Progress | L9: =IF(M9="Yes","🔴 BOTTOM",IF(M9="No","✓ Cleared",IF(Q9="MIN",IF(AND(ISNUMBER(F9),ISNUMBER(H9)),IF(H9<F9*'Master Dashboard'!$B$4,"🔴 LOW",""),""),IF(Q9="MAX",IF(AND(ISNUMBER(F9),ISNUMBER(H9)),IF(H9>F9,"🔴 HIGH",""),""),"")))) | M9: Auto | N9: Gov Cell (report) | O9: 05-06-2026 | P9: 5917 dept + 1752 SK | R9: ADCG-002
C10: Channel — DM CSC (04 Jun) | D10: cards | G10: 832 | H10: 795 | I10: =IF(AND(ISNUMBER(G10),ISNUMBER(H10)),H10-G10,"") -> -37 | J10: =IF(AND(ISNUMBER(E10),E10>0,ISNUMBER(H10)),H10/E10,"") | K10: In Progress | L10: =IF(M10="Yes","🔴 BOTTOM",IF(M10="No","✓ Cleared",IF(Q10="MIN",IF(AND(ISNUMBER(F10),ISNUMBER(H10)),IF(H10<F10*'Master Dashboard'!$B$4,"🔴 LOW",""),""),IF(Q10="MAX",IF(AND(ISNUMBER(F10),ISNUMBER(H10)),IF(H10>F10,"🔴 HIGH",""),""),"")))) | M10: Auto | N10: Gov Cell (report) | O10: 05-06-2026 | P10: Prev day 832 — Cards generated via DM-CSC (Common Service Centre) channel that day. | R10: ADCG-003
C11: Channel — Dr Cooperation / PACS (04 Jun) | D11: cards | G11: 18 | H11: 20 | I11: =IF(AND(ISNUMBER(G11),ISNUMBER(H11)),H11-G11,"") -> 2 | J11: =IF(AND(ISNUMBER(E11),E11>0,ISNUMBER(H11)),H11/E11,"") | K11: In Progress | L11: =IF(M11="Yes","🔴 BOTTOM",IF(M11="No","✓ Cleared",IF(Q11="MIN",IF(AND(ISNUMBER(F11),ISNUMBER(H11)),IF(H11<F11*'Master Dashboard'!$B$4,"🔴 LOW",""),""),IF(Q11="MAX",IF(AND(ISNUMBER(F11),ISNUMBER(H11)),IF(H11>F11,"🔴 HIGH",""),""),"")))) | M11: Auto | N11: Gov Cell (report) | O11: 05-06-2026 | P11: Cards via Dr Cooperation / PACS societies that day. | R11: ADCG-004
C12: Channel — Agriculture Dept (04 Jun) | D12: cards | G12: 16 | H12: 19 | I12: =IF(AND(ISNUMBER(G12),ISNUMBER(H12)),H12-G12,"") -> 3 | J12: =IF(AND(ISNUMBER(E12),E12>0,ISNUMBER(H12)),H12/E12,"") | K12: In Progress | L12: =IF(M12="Yes","🔴 BOTTOM",IF(M12="No","✓ Cleared",IF(Q12="MIN",IF(AND(ISNUMBER(F12),ISNUMBER(H12)),IF(H12<F12*'Master Dashboard'!$B$4,"🔴 LOW",""),""),IF(Q12="MAX",IF(AND(ISNUMBER(F12),ISNUMBER(H12)),IF(H12>F12,"🔴 HIGH",""),""),"")))) | M12: Auto | N12: Gov Cell (report) | O12: 05-06-2026 | P12: Cards via Agriculture Dept that day. | R12: ADCG-005
C13: Channel — ASHA cards (04 Jun) | D13: cards | G13: 511 | H13: 582 | I13: =IF(AND(ISNUMBER(G13),ISNUMBER(H13)),H13-G13,"") -> 71 | J13: =IF(AND(ISNUMBER(E13),E13>0,ISNUMBER(H13)),H13/E13,"") | K13: In Progress | L13: =IF(M13="Yes","🔴 BOTTOM",IF(M13="No","✓ Cleared",IF(Q13="MIN",IF(AND(ISNUMBER(F13),ISNUMBER(H13)),IF(H13<F13*'Master Dashboard'!$B$4,"🔴 LOW",""),""),IF(Q13="MAX",IF(AND(ISNUMBER(F13),ISNUMBER(H13)),IF(H13>F13,"🔴 HIGH",""),""),"")))) | M13: Auto | N13: Gov Cell (report) | O13: 05-06-2026 | P13: Sharp drop since 08 May (was 3961 on 28 Apr) — Cards by ASHA workers that day. | R13: ADCG-006
C14: Channel — Hospital total (04 Jun) | D14: cards | G14: 51 | H14: 40 | I14: =IF(AND(ISNUMBER(G14),ISNUMBER(H14)),H14-G14,"") -> -11 | J14: =IF(AND(ISNUMBER(E14),E14>0,ISNUMBER(H14)),H14/E14,"") | K14: In Progress | L14: =IF(M14="Yes","🔴 BOTTOM",IF(M14="No","✓ Cleared",IF(Q14="MIN",IF(AND(ISNUMBER(F14),ISNUMBER(H14)),IF(H14<F14*'Master Dashboard'!$B$4,"🔴 LOW",""),""),IF(Q14="MAX",IF(AND(ISNUMBER(F14),ISNUMBER(H14)),IF(H14>F14,"🔴 HIGH",""),""),"")))) | M14: Auto | N14: Gov Cell (report) | O14: 05-06-2026 | P14: Govt 33 / Private 7 — Cards issued at hospitals that day (Govt + Private). | R14: ADCG-007
C15: Govt hospital cards (04 Jun) | D15: cards | G15: 47 | H15: 33 | I15: =IF(AND(ISNUMBER(G15),ISNUMBER(H15)),H15-G15,"") -> -14 | J15: =IF(AND(ISNUMBER(E15),E15>0,ISNUMBER(H15)),H15/E15,"") | K15: In Progress | L15: =IF(M15="Yes","🔴 BOTTOM",IF(M15="No","✓ Cleared",IF(Q15="MIN",IF(AND(ISNUMBER(F15),ISNUMBER(H15)),IF(H15<F15*'Master Dashboard'!$B$4,"🔴 LOW",""),""),IF(Q15="MAX",IF(AND(ISNUMBER(F15),ISNUMBER(H15)),IF(H15>F15,"🔴 HIGH",""),""),"")))) | M15: Auto | N15: Gov Cell (report) | O15: 05-06-2026 | P15: Issuance at govt facilities (DH/SDH/AAC) that day. | R15: ADCG-008
C16: Private hospital cards (04 Jun) | D16: cards | E16: 20 | F16: 15 | G16: 2 | H16: 7 | I16: =IF(AND(ISNUMBER(G16),ISNUMBER(H16)),H16-G16,"") -> 5 | J16: =IF(AND(ISNUMBER(E16),E16>0,ISNUMBER(H16)),H16/E16,"") -> 0.35 | K16: In Progress | L16: =IF(M16="Yes","🔴 BOTTOM",IF(M16="No","✓ Cleared",IF(Q16="MIN",IF(AND(ISNUMBER(F16),ISNUMBER(H16)),IF(H16<F16*'Master Dashboard'!$B$4,"🔴 LOW",""),""),IF(Q16="MAX",IF(AND(ISNUMBER(F16),ISNUMBER(H16)),IF(H16>F16,"🔴 HIGH",""),""),"")))) -> 🔴 LOW | M16: Auto | N16: Gov Cell (report) | O16: 05-06-2026 | P16: Private penetration low — Private-hospital issuance that day — low penetration. | Q16: MIN | R16: ADCG-009
C17: Not-Mapped cards (to reconcile) | D17: cards | F17: 100 | H17: 186 | I17: =IF(AND(ISNUMBER(G17),ISNUMBER(H17)),H17-G17,"") | J17: =IF(AND(ISNUMBER(E17),E17>0,ISNUMBER(H17)),H17/E17,"") | K17: Pending/Blocked | L17: =IF(M17="Yes","🔴 BOTTOM",IF(M17="No","✓ Cleared",IF(Q17="MIN",IF(AND(ISNUMBER(F17),ISNUMBER(H17)),IF(H17<F17*'Master Dashboard'!$B$4,"🔴 LOW",""),""),IF(Q17="MAX",IF(AND(ISNUMBER(F17),ISNUMBER(H17)),IF(H17>F17,"🔴 HIGH",""),""),"")))) -> 🔴 HIGH | M17: Auto | N17: Gov Cell (report) | O17: 05-06-2026 | P17: Cumulative not-mapped pool | Q17: MAX | R17: ADCG-010
C18: Phase-18 sheet — nodals NOT filled | D18: nodals | E18: 6 | F18: 0 | H18: 6 | I18: =IF(AND(ISNUMBER(G18),ISNUMBER(H18)),H18-G18,"") | J18: =IF(AND(ISNUMBER(E18),E18>0,ISNUMBER(H18)),H18/E18,"") -> 1 | K18: Pending/Blocked | L18: =IF(M18="Yes","🔴 BOTTOM",IF(M18="No","✓ Cleared",IF(Q18="MIN",IF(AND(ISNUMBER(F18),ISNUMBER(H18)),IF(H18<F18*'Master Dashboard'!$B$4,"🔴 LOW",""),""),IF(Q18="MAX",IF(AND(ISNUMBER(F18),ISNUMBER(H18)),IF(H18>F18,"🔴 HIGH",""),""),"")))) -> 🔴 HIGH | M18: Auto | N18: Gov Cell (report) | O18: 05-06-2026 | P18: Sahnewal, Payal, Khanna, Dakha, Samrala, Atam Nagar | Q18: MAX | R18: ADCG-011
C19: Cards — Atam Nagar (04 Jun) | D19: cards | E19: 50 | F19: 50 | H19: 25 | I19: =IF(AND(ISNUMBER(G19),ISNUMBER(H19)),H19-G19,"") | J19: =IF(AND(ISNUMBER(E19),E19>0,ISNUMBER(H19)),H19/E19,"") -> 0.5 | K19: In Progress | L19: =IF(M19="Yes","🔴 BOTTOM",IF(M19="No","✓ Cleared",IF(Q19="MIN",IF(AND(ISNUMBER(F19),ISNUMBER(H19)),IF(H19<F19*'Master Dashboard'!$B$4,"🔴 LOW",""),""),IF(Q19="MAX",IF(AND(ISNUMBER(F19),ISNUMBER(H19)),IF(H19>F19,"🔴 HIGH",""),""),"")))) -> 🔴 LOW | M19: Auto | N19: Gov Cell (report) | O19: 05-06-2026 | P19: 25 cards + 0 SK — Total MMSBY cards in this AC on 04 Jun (incl. Sewa-Kendra). | Q19: MIN | R19: ADCG-012
C20: Cards — Dakha (04 Jun) | D20: cards | E20: 50 | F20: 50 | H20: 21 | I20: =IF(AND(ISNUMBER(G20),ISNUMBER(H20)),H20-G20,"") | J20: =IF(AND(ISNUMBER(E20),E20>0,ISNUMBER(H20)),H20/E20,"") -> 0.42 | K20: In Progress | L20: =IF(M20="Yes","🔴 BOTTOM",IF(M20="No","✓ Cleared",IF(Q20="MIN",IF(AND(ISNUMBER(F20),ISNUMBER(H20)),IF(H20<F20*'Master Dashboard'!$B$4,"🔴 LOW",""),""),IF(Q20="MAX",IF(AND(ISNUMBER(F20),ISNUMBER(H20)),IF(H20>F20,"🔴 HIGH",""),""),"")))) -> 🔴 LOW | M20: Auto | N20: Gov Cell (report) | O20: 05-06-2026 | P20: 21 cards + 0 SK — Total MMSBY cards in this AC on 04 Jun (incl. Sewa-Kendra). | Q20: MIN | R20: ADCG-013
C21: Cards — Gill (04 Jun) | D21: cards | E21: 50 | F21: 50 | H21: 79 | I21: =IF(AND(ISNUMBER(G21),ISNUMBER(H21)),H21-G21,"") | J21: =IF(AND(ISNUMBER(E21),E21>0,ISNUMBER(H21)),H21/E21,"") -> 1.58 | K21: In Progress | L21: =IF(M21="Yes","🔴 BOTTOM",IF(M21="No","✓ Cleared",IF(Q21="MIN",IF(AND(ISNUMBER(F21),ISNUMBER(H21)),IF(H21<F21*'Master Dashboard'!$B$4,"🔴 LOW",""),""),IF(Q21="MAX",IF(AND(ISNUMBER(F21),ISNUMBER(H21)),IF(H21>F21,"🔴 HIGH",""),""),"")))) | M21: Auto | N21: Gov Cell (report) | O21: 05-06-2026 | P21: 28 cards + 51 SK — Total MMSBY cards in this AC on 04 Jun (incl. Sewa-Kendra). | Q21: MIN | R21: ADCG-014
C22: Cards — Jagraon (04 Jun) | D22: cards | E22: 50 | F22: 50 | H22: 117 | I22: =IF(AND(ISNUMBER(G22),ISNUMBER(H22)),H22-G22,"") | J22: =IF(AND(ISNUMBER(E22),E22>0,ISNUMBER(H22)),H22/E22,"") -> 2.34 | K22: In Progress | L22: =IF(M22="Yes","🔴 BOTTOM",IF(M22="No","✓ Cleared",IF(Q22="MIN",IF(AND(ISNUMBER(F22),ISNUMBER(H22)),IF(H22<F22*'Master Dashboard'!$B$4,"🔴 LOW",""),""),IF(Q22="MAX",IF(AND(ISNUMBER(F22),ISNUMBER(H22)),IF(H22>F22,"🔴 HIGH",""),""),"")))) | M22: Auto | N22: Gov Cell (report) | O22: 05-06-2026 | P22: 68 cards + 49 SK — Total MMSBY cards in this AC on 04 Jun (incl. Sewa-Kendra). | Q22: MIN | R22: ADCG-015
C23: Cards — Khanna (04 Jun) | D23: cards | E23: 50 | F23: 50 | H23: 36 | I23: =IF(AND(ISNUMBER(G23),ISNUMBER(H23)),H23-G23,"") | J23: =IF(AND(ISNUMBER(E23),E23>0,ISNUMBER(H23)),H23/E23,"") -> 0.72 | K23: In Progress | L23: =IF(M23="Yes","🔴 BOTTOM",IF(M23="No","✓ Cleared",IF(Q23="MIN",IF(AND(ISNUMBER(F23),ISNUMBER(H23)),IF(H23<F23*'Master Dashboard'!$B$4,"🔴 LOW",""),""),IF(Q23="MAX",IF(AND(ISNUMBER(F23),ISNUMBER(H23)),IF(H23>F23,"🔴 HIGH",""),""),"")))) -> 🔴 LOW | M23: Auto | N23: Gov Cell (report) | O23: 05-06-2026 | P23: 36 cards + 0 SK — Total MMSBY cards in this AC on 04 Jun (incl. Sewa-Kendra). | Q23: MIN | R23: ADCG-016
C24: Cards — Ludhiana Central (04 Jun) | D24: cards | E24: 50 | F24: 50 | H24: 89 | I24: =IF(AND(ISNUMBER(G24),ISNUMBER(H24)),H24-G24,"") | J24: =IF(AND(ISNUMBER(E24),E24>0,ISNUMBER(H24)),H24/E24,"") -> 1.78 | K24: In Progress | L24: =IF(M24="Yes","🔴 BOTTOM",IF(M24="No","✓ Cleared",IF(Q24="MIN",IF(AND(ISNUMBER(F24),ISNUMBER(H24)),IF(H24<F24*'Master Dashboard'!$B$4,"🔴 LOW",""),""),IF(Q24="MAX",IF(AND(ISNUMBER(F24),ISNUMBER(H24)),IF(H24>F24,"🔴 HIGH",""),""),"")))) | M24: Auto | N24: Gov Cell (report) | O24: 05-06-2026 | P24: 53 cards + 36 SK — Total MMSBY cards in this AC on 04 Jun (incl. Sewa-Kendra). | Q24: MIN | R24: ADCG-017
C25: Cards — Ludhiana East (04 Jun) | D25: cards | E25: 50 | F25: 50 | H25: 62 | I25: =IF(AND(ISNUMBER(G25),ISNUMBER(H25)),H25-G25,"") | J25: =IF(AND(ISNUMBER(E25),E25>0,ISNUMBER(H25)),H25/E25,"") -> 1.24 | K25: In Progress | L25: =IF(M25="Yes","🔴 BOTTOM",IF(M25="No","✓ Cleared",IF(Q25="MIN",IF(AND(ISNUMBER(F25),ISNUMBER(H25)),IF(H25<F25*'Master Dashboard'!$B$4,"🔴 LOW",""),""),IF(Q25="MAX",IF(AND(ISNUMBER(F25),ISNUMBER(H25)),IF(H25>F25,"🔴 HIGH",""),""),"")))) | M25: Auto | N25: Gov Cell (report) | O25: 05-06-2026 | P25: 48 cards + 14 SK — Total MMSBY cards in this AC on 04 Jun (incl. Sewa-Kendra). | Q25: MIN | R25: ADCG-018
C26: Cards — Ludhiana North (04 Jun) | D26: cards | E26: 50 | F26: 50 | H26: 22 | I26: =IF(AND(ISNUMBER(G26),ISNUMBER(H26)),H26-G26,"") | J26: =IF(AND(ISNUMBER(E26),E26>0,ISNUMBER(H26)),H26/E26,"") -> 0.44 | K26: In Progress | L26: =IF(M26="Yes","🔴 BOTTOM",IF(M26="No","✓ Cleared",IF(Q26="MIN",IF(AND(ISNUMBER(F26),ISNUMBER(H26)),IF(H26<F26*'Master Dashboard'!$B$4,"🔴 LOW",""),""),IF(Q26="MAX",IF(AND(ISNUMBER(F26),ISNUMBER(H26)),IF(H26>F26,"🔴 HIGH",""),""),"")))) -> 🔴 LOW | M26: Auto | N26: Gov Cell (report) | O26: 05-06-2026 | P26: 19 cards + 3 SK — Total MMSBY cards in this AC on 04 Jun (incl. Sewa-Kendra). | Q26: MIN | R26: ADCG-019
C27: Cards — Ludhiana South (04 Jun) | D27: cards | E27: 50 | F27: 50 | H27: 15 | I27: =IF(AND(ISNUMBER(G27),ISNUMBER(H27)),H27-G27,"") | J27: =IF(AND(ISNUMBER(E27),E27>0,ISNUMBER(H27)),H27/E27,"") -> 0.3 | K27: In Progress | L27: =IF(M27="Yes","🔴 BOTTOM",IF(M27="No","✓ Cleared",IF(Q27="MIN",IF(AND(ISNUMBER(F27),ISNUMBER(H27)),IF(H27<F27*'Master Dashboard'!$B$4,"🔴 LOW",""),""),IF(Q27="MAX",IF(AND(ISNUMBER(F27),ISNUMBER(H27)),IF(H27>F27,"🔴 HIGH",""),""),"")))) -> 🔴 LOW | M27: Auto | N27: Gov Cell (report) | O27: 05-06-2026 | P27: 15 cards + 0 SK — Total MMSBY cards in this AC on 04 Jun (incl. Sewa-Kendra). | Q27: MIN | R27: ADCG-020
C28: Cards — Ludhiana West (04 Jun) | D28: cards | E28: 50 | F28: 50 | H28: 61 | I28: =IF(AND(ISNUMBER(G28),ISNUMBER(H28)),H28-G28,"") | J28: =IF(AND(ISNUMBER(E28),E28>0,ISNUMBER(H28)),H28/E28,"") -> 1.22 | K28: In Progress | L28: =IF(M28="Yes","🔴 BOTTOM",IF(M28="No","✓ Cleared",IF(Q28="MIN",IF(AND(ISNUMBER(F28),ISNUMBER(H28)),IF(H28<F28*'Master Dashboard'!$B$4,"🔴 LOW",""),""),IF(Q28="MAX",IF(AND(ISNUMBER(F28),ISNUMBER(H28)),IF(H28>F28,"🔴 HIGH",""),""),"")))) | M28: Auto | N28: Gov Cell (report) | O28: 05-06-2026 | P28: 60 cards + 1 SK — Total MMSBY cards in this AC on 04 Jun (incl. Sewa-Kendra). | Q28: MIN | R28: ADCG-021
C29: Cards — Payal (04 Jun) | D29: cards | E29: 50 | F29: 50 | H29: 28 | I29: =IF(AND(ISNUMBER(G29),ISNUMBER(H29)),H29-G29,"") | J29: =IF(AND(ISNUMBER(E29),E29>0,ISNUMBER(H29)),H29/E29,"") -> 0.56 | K29: In Progress | L29: =IF(M29="Yes","🔴 BOTTOM",IF(M29="No","✓ Cleared",IF(Q29="MIN",IF(AND(ISNUMBER(F29),ISNUMBER(H29)),IF(H29<F29*'Master Dashboard'!$B$4,"🔴 LOW",""),""),IF(Q29="MAX",IF(AND(ISNUMBER(F29),ISNUMBER(H29)),IF(H29>F29,"🔴 HIGH",""),""),"")))) -> 🔴 LOW | M29: Auto | N29: Gov Cell (report) | O29: 05-06-2026 | P29: 28 cards + 0 SK — Total MMSBY cards in this AC on 04 Jun (incl. Sewa-Kendra). | Q29: MIN | R29: ADCG-022
... C32: Cards — Samrala (04 Jun) | D32: cards | E32: 50 | F32: 50 | H32: 119 | I32: =IF(AND(ISNUMBER(G32),ISNUMBER(H32)),H32-G32,"") | J32: =IF(AND(ISNUMBER(E32),E32>0,ISNUMBER(H32)),H32/E32,"") -> 2.38 | K32: In Progress | L32: =IF(M32="Yes","🔴 BOTTOM",IF(M32="No","✓ Cleared",IF(Q32="MIN",IF(AND(ISNUMBER(F32),ISNUMBER(H32)),IF(H32<F32*'Master Dashboard'!$B$4,"🔴 LOW",""),""),IF(Q32="MAX",IF(AND(ISNUMBER(F32),ISNUMBER(H32)),IF(H32>F32,"🔴 HIGH",""),""),"")))) | M32: Auto | N32: Gov Cell (report) | O32: 05-06-2026 | P32: 81 cards + 38 SK — Total MMSBY cards in this AC on 04 Jun (incl. Sewa-Kendra). | Q32: MIN | R32: ADCG-025
A33: 2 | B33: AAC & SDH (Aam Aadmi Clinics / SDH) | C33: 📊 AAC Phase 8/9/10 — total sites | H33: 48 | P33: Inaugurated 17 | Work in progress 30 | Problematic 1.
C34: 📊 SHC→AAC Phase 11 — total sites | H34: 32 | P34: Work orders given 28 | In re-tendering 4 (all PHSC). 8 each across IT/Mandi/Panch Raj/PHSC.
C35: AAC Ph 8/9/10 — inaugurated | D35: sites | E35: 48 | F35: 48 | H35: 17 | I35: =IF(AND(ISNUMBER(G35),ISNUMBER(H35)),H35-G35,"") | J35: =IF(AND(ISNUMBER(E35),E35>0,ISNUMBER(H35)),H35/E35,"") -> 0.35416667 | K35: Completed | L35: =IF(M35="Yes","🔴 BOTTOM",IF(M35="No","✓ Cleared",IF(Q35="MIN",IF(AND(ISNUMBER(F35),ISNUMBER(H35)),IF(H35<F35*'Master Dashboard'!$B$4,"🔴 LOW",""),""),IF(Q35="MAX",IF(AND(ISNUMBER(F35),ISNUMBER(H35)),IF(H35>F35,"🔴 HIGH",""),""),"")))) -> 🔴 LOW | M35: Auto | N35: Gov Cell (report) | O35: 05-06-2026 | P35: of 48 total | Q35: MIN | R35: ADCG-035
C36: AAC Ph 8/9/10 — work in progress | D36: sites | H36: 30 | I36: =IF(AND(ISNUMBER(G36),ISNUMBER(H36)),H36-G36,"") | J36: =IF(AND(ISNUMBER(E36),E36>0,ISNUMBER(H36)),H36/E36,"") | K36: In Progress | L36: =IF(M36="Yes","🔴 BOTTOM",IF(M36="No","✓ Cleared",IF(Q36="MIN",IF(AND(ISNUMBER(F36),ISNUMBER(H36)),IF(H36<F36*'Master Dashboard'!$B$4,"🔴 LOW",""),""),IF(Q36="MAX",IF(AND(ISNUMBER(F36),ISNUMBER(H36)),IF(H36>F36,"🔴 HIGH",""),""),"")))) | M36: Auto | N36: Gov Cell (report) | O36: 05-06-2026 | R36: ADCG-036
C37: AAC — at >=95% completion | D37: sites | H37: 10 | I37: =IF(AND(ISNUMBER(G37),ISNUMBER(H37)),H37-G37,"") | J37: =IF(AND(ISNUMBER(E37),E37>0,ISNUMBER(H37)),H37/E37,"") | K37: In Progress | L37: =IF(M37="Yes","🔴 BOTTOM",IF(M37="No","✓ Cleared",IF(Q37="MIN",IF(AND(ISNUMBER(F37),ISNUMBER(H37)),IF(H37<F37*'Master Dashboard'!$B$4,"🔴 LOW",""),""),IF(Q37="MAX",IF(AND(ISNUMBER(F37),ISNUMBER(H37)),IF(H37>F37,"🔴 HIGH",""),""),"")))) | M37: Auto | N37: Gov Cell (report) | O37: 05-06-2026 | R37: ADCG-037
C38: AAC — at 90% completion | D38: sites | H38: 2 | I38: =IF(AND(ISNUMBER(G38),ISNUMBER(H38)),H38-G38,"") | J38: =IF(AND(ISNUMBER(E38),E38>0,ISNUMBER(H38)),H38/E38,"") | K38: In Progress | L38: =IF(M38="Yes","🔴 BOTTOM",IF(M38="No","✓ Cleared",IF(Q38="MIN",IF(AND(ISNUMBER(F38),ISNUMBER(H38)),IF(H38<F38*'Master Dashboard'!$B$4,"🔴 LOW",""),""),IF(Q38="MAX",IF(AND(ISNUMBER(F38),ISNUMBER(H38)),IF(H38>F38,"🔴 HIGH",""),""),"")))) | M38: Auto | N38: Gov Cell (report) | O38: 05-06-2026 | R38: ADCG-038
C39: AAC — at 80% completion | D39: sites | H39: 4 | I39: =IF(AND(ISNUMBER(G39),ISNUMBER(H39)),H39-G39,"") | J39: =IF(AND(ISNUMBER(E39),E39>0,ISNUMBER(H39)),H39/E39,"") | K39: In Progress | L39: =IF(M39="Yes","🔴 BOTTOM",IF(M39="No","✓ Cleared",IF(Q39="MIN",IF(AND(ISNUMBER(F39),ISNUMBER(H39)),IF(H39<F39*'Master Dashboard'!$B$4,"🔴 LOW",""),""),IF(Q39="MAX",IF(AND(ISNUMBER(F39),ISNUMBER(H39)),IF(H39>F39,"🔴 HIGH",""),""),"")))) | M39: Auto | N39: Gov Cell (report) | O39: 05-06-2026 | R39: ADCG-039
C40: AAC — at 70% completion | D40: sites | H40: 7 | I40: =IF(AND(ISNUMBER(G40),ISNUMBER(H40)),H40-G40,"") | J40: =IF(AND(ISNUMBER(E40),E40>0,ISNUMBER(H40)),H40/E40,"") | K40: In Progress | L40: =IF(M40="Yes","🔴 BOTTOM",IF(M40="No","✓ Cleared",IF(Q40="MIN",IF(AND(ISNUMBER(F40),ISNUMBER(H40)),IF(H40<F40*'Master Dashboard'!$B$4,"🔴 LOW",""),""),IF(Q40="MAX",IF(AND(ISNUMBER(F40),ISNUMBER(H40)),IF(H40>F40,"🔴 HIGH",""),""),"")))) | M40: Auto | N40: Gov Cell (report) | O40: 05-06-2026 | R40: ADCG-040
C41: AAC — at 60% completion | D41: sites | H41: 6 | I41: =IF(AND(ISNUMBER(G41),ISNUMBER(H41)),H41-G41,"") | J41: =IF(AND(ISNUMBER(E41),E41>0,ISNUMBER(H41)),H41/E41,"") | K41: In Progress | L41: =IF(M41="Yes","🔴 BOTTOM",IF(M41="No","✓ Cleared",IF(Q41="MIN",IF(AND(ISNUMBER(F41),ISNUMBER(H41)),IF(H41<F41*'Master Dashboard'!$B$4,"🔴 LOW",""),""),IF(Q41="MAX",IF(AND(ISNUMBER(F41),ISNUMBER(H41)),IF(H41>F41,"🔴 HIGH",""),""),"")))) | M41: Auto | N41: Gov Cell (report) | O41: 05-06-2026 | R41: ADCG-041
C42: AAC — problematic site | D42: sites | E42: 0 | F42: 0 | H42: 1 | I42: =IF(AND(ISNUMBER(G42),ISNUMBER(H42)),H42-G42,"") | J42: =IF(AND(ISNUMBER(E42),E42>0,ISNUMBER(H42)),H42/E42,"") | K42: Pending/Blocked | L42: =IF(M42="Yes","🔴 BOTTOM",IF(M42="No","✓ Cleared",IF(Q42="MIN",IF(AND(ISNUMBER(F42),ISNUMBER(H42)),IF(H42<F42*'Master Dashboard'!$B$4,"🔴 LOW",""),""),IF(Q42="MAX",IF(AND(ISNUMBER(F42),ISNUMBER(H42)),IF(H42>F42,"🔴 HIGH",""),""),"")))) -> 🔴 HIGH | M42: Auto | N42: Gov Cell (report) | O42: 05-06-2026 | Q42: MAX | R42: ADCG-042
C43: SHC->AAC Ph 11 — work orders given | D43: sites | E43: 32 | F43: 32 | H43: 28 | I43: =IF(AND(ISNUMBER(G43),ISNUMBER(H43)),H43-G43,"") | J43: =IF(AND(ISNUMBER(E43),E43>0,ISNUMBER(H43)),H43/E43,"") -> 0.875 | K43: In Progress | L43: =IF(M43="Yes","🔴 BOTTOM",IF(M43="No","✓ Cleared",IF(Q43="MIN",IF(AND(ISNUMBER(F43),ISNUMBER(H43)),IF(H43<F43*'Master Dashboard'!$B$4,"🔴 LOW",""),""),IF(Q43="MAX",IF(AND(ISNUMBER(F43),ISNUMBER(H43)),IF(H43>F43,"🔴 HIGH",""),""),"")))) -> 🔴 LOW | M43: Auto | N43: Gov Cell (report) | O43: 05-06-2026 | P43: IT 8 / Mandi 8 / Panch Raj 8 / PHSC 4 | Q43: MIN | R43: ADCG-043
C44: SHC->AAC — in re-tendering | D44: sites | E44: 0 | F44: 0 | H44: 4 | I44: =IF(AND(ISNUMBER(G44),ISNUMBER(H44)),H44-G44,"") | J44: =IF(AND(ISNUMBER(E44),E44>0,ISNUMBER(H44)),H44/E44,"") | K44: Pending/Blocked | L44: =IF(M44="Yes","🔴 BOTTOM",IF(M44="No","✓ Cleared",IF(Q44="MIN",IF(AND(ISNUMBER(F44),ISNUMBER(H44)),IF(H44<F44*'Master Dashboard'!$B$4,"🔴 LOW",""),""),IF(Q44="MAX",IF(AND(ISNUMBER(F44),ISNUMBER(H44)),IF(H44>F44,"🔴 HIGH",""),""),"")))) -> 🔴 HIGH | M44: Auto | N44: Gov Cell (report) | O44: 05-06-2026 | P44: All 4 at PHSC: 2 work orders pending at Chief PHSC, 2 cancelled by MD PHSC & re-tendering. Threeke alt site — Sarpanch NOC awaited. | Q44: MAX | R44: ADCG-044
A45: 3 | B45: Census 2026 — HLB Progress | C45: 📊 Total HLBs (House Listing Blocks) | H45: 3778 | P45: All 3,778 in progress; 0 not started. Completed: 1,408 (37%).
C46: 📊 Census houses — expected vs listed | H46: 718019 | P46: 7,18,019 of 8,59,510 expected houses listed (84%).
C47: District — HLBs completed | D47: HLBs | E47: 3778 | F47: 1889 | H47: 1408 | I47: =IF(AND(ISNUMBER(G47),ISNUMBER(H47)),H47-G47,"") | J47: =IF(AND(ISNUMBER(E47),E47>0,ISNUMBER(H47)),H47/E47,"") -> 0.37268396 | K47: In Progress | L47: =IF(M47="Yes","🔴 BOTTOM",IF(M47="No","✓ Cleared",IF(Q47="MIN",IF(AND(ISNUMBER(F47),ISNUMBER(H47)),IF(H47<F47*'Master Dashboard'!$B$4,"🔴 LOW",""),""),IF(Q47="MAX",IF(AND(ISNUMBER(F47),ISNUMBER(H47)),IF(H47>F47,"🔴 HIGH",""),""),"")))) -> 🔴 LOW | M47: Auto | N47: Gov Cell (report) | O47: 05-06-2026 | P47: All 3778 in progress; 0 not started | Q47: MIN | R47: ADCG-045
C48: District — census houses listed | D48: houses | E48: 859510 | F48: 773559 | H48: 718019 | I48: =IF(AND(ISNUMBER(G48),ISNUMBER(H48)),H48-G48,"") | J48: =IF(AND(ISNUMBER(E48),E48>0,ISNUMBER(H48)),H48/E48,"") -> 0.83538179 | K48: In Progress | L48: =IF(M48="Yes","🔴 BOTTOM",IF(M48="No","✓ Cleared",IF(Q48="MIN",IF(AND(ISNUMBER(F48),ISNUMBER(H48)),IF(H48<F48*'Master Dashboard'!$B$4,"🔴 LOW",""),""),IF(Q48="MAX",IF(AND(ISNUMBER(F48),ISNUMBER(H48)),IF(H48>F48,"🔴 HIGH",""),""),"")))) -> 🔴 LOW | M48: Auto | N48: Gov Cell (report) | O48: 05-06-2026 | P48: 84% against expected | Q48: MIN | R48: ADCG-046
C49: HLBs completed — Tehsil Samrala | D49: HLBs | E49: 348 | F49: 174 | H49: 196 | I49: =IF(AND(ISNUMBER(G49),ISNUMBER(H49)),H49-G49,"") | J49: =IF(AND(ISNUMBER(E49),E49>0,ISNUMBER(H49)),H49/E49,"") -> 0.56321839 | K49: In Progress | L49: =IF(M49="Yes","🔴 BOTTOM",IF(M49="No","✓ Cleared",IF(Q49="MIN",IF(AND(ISNUMBER(F49),ISNUMBER(H49)),IF(H49<F49*'Master Dashboard'!$B$4,"🔴 LOW",""),""),IF(Q49="MAX",IF(AND(ISNUMBER(F49),ISNUMBER(H49)),IF(H49>F49,"🔴 HIGH",""),""),"")))) | M49: Auto | N49: Gov Cell (report) | O49: 05-06-2026 | P49: Houses 61,278/65,019 (94%) | Q49: MIN | R49: ADCG-047
C50: HLBs completed — Tehsil Khanna | D50: HLBs | E50: 158 | F50: 79 | H50: 135 | I50: =IF(AND(ISNUMBER(G50),ISNUMBER(H50)),H50-G50,"") | J50: =IF(AND(ISNUMBER(E50),E50>0,ISNUMBER(H50)),H50/E50,"") -> 0.85443038 | K50: In Progress | L50: =IF(M50="Yes","🔴 BOTTOM",IF(M50="No","✓ Cleared",IF(Q50="MIN",IF(AND(ISNUMBER(F50),ISNUMBER(H50)),IF(H50<F50*'Master Dashboard'!$B$4,"🔴 LOW",""),""),IF(Q50="MAX",IF(AND(ISNUMBER(F50),ISNUMBER(H50)),IF(H50>F50,"🔴 HIGH",""),""),"")))) | M50: Auto | N50: Gov Cell (report) | O50: 05-06-2026 | P50: Houses 32,959/32,579 (101%) | Q50: MIN | R50: ADCG-048
C51: HLBs completed — Tehsil Payal | D51: HLBs | E51: 302 | F51: 151 | H51: 139 | I51: =IF(AND(ISNUMBER(G51),ISNUMBER(H51)),H51-G51,"") | J51: =IF(AND(ISNUMBER(E51),E51>0,ISNUMBER(H51)),H51/E51,"") -> 0.4602649 | K51: In Progress | L51: =IF(M51="Yes","🔴 BOTTOM",IF(M51="No","✓ Cleared",IF(Q51="MIN",IF(AND(ISNUMBER(F51),ISNUMBER(H51)),IF(H51<F51*'Master Dashboard'!$B$4,"🔴 LOW",""),""),IF(Q51="MAX",IF(AND(ISNUMBER(F51),ISNUMBER(H51)),IF(H51>F51,"🔴 HIGH",""),""),"")))) -> 🔴 LOW | M51: Auto | N51: Gov Cell (report) | O51: 05-06-2026 | P51: Houses 57,331/64,602 (89%) | Q51: MIN | R51: ADCG-049
C52: HLBs completed — Tehsil Ludhiana East | D52: HLBs | E52: 994 | F52: 497 | H52: 230 | I52: =IF(AND(ISNUMBER(G52),ISNUMBER(H52)),H52-G52,"") | J52: =IF(AND(ISNUMBER(E52),E52>0,ISNUMBER(H52)),H52/E52,"") -> 0.23138833 | K52: In Progress | L52: =IF(M52="Yes","🔴 BOTTOM",IF(M52="No","✓ Cleared",IF(Q52="MIN",IF(AND(ISNUMBER(F52),ISNUMBER(H52)),IF(H52<F52*'Master Dashboard'!$B$4,"🔴 LOW",""),""),IF(Q52="MAX",IF(AND(ISNUMBER(F52),ISNUMBER(H52)),IF(H52>F52,"🔴 HIGH",""),""),"")))) -> 🔴 LOW | M52: Auto | N52: Gov Cell (report) | O52: 05-06-2026 | P52: Houses 159,534/211,624 (75%) | Q52: MIN | R52: ADCG-050
C53: HLBs completed — Tehsil Ludhiana West | D53: HLBs | E53: 679 | F53: 340 | H53: 16 | I53: =IF(AND(ISNUMBER(G53),ISNUMBER(H53)),H53-G53,"") | J53: =IF(AND(ISNUMBER(E53),E53>0,ISNUMBER(H53)),H53/E53,"") -> 0.023564065 | K53: In Progress | L53: =IF(M53="Yes","🔴 BOTTOM",IF(M53="No","✓ Cleared",IF(Q53="MIN",IF(AND(ISNUMBER(F53),ISNUMBER(H53)),IF(H53<F53*'Master Dashboard'!$B$4,"🔴 LOW",""),""),IF(Q53="MAX",IF(AND(ISNUMBER(F53),ISNUMBER(H53)),IF(H53>F53,"🔴 HIGH",""),""),"")))) -> 🔴 LOW | M53: Auto | N53: Gov Cell (report) | O53: 05-06-2026 | P53: Houses 133,747/189,633 (71%) | Q53: MIN | R53: ADCG-051
C54: HLBs completed — Tehsil Raikot | D54: HLBs | E54: 274 | F54: 137 | H54: 122 | I54: =IF(AND(ISNUMBER(G54),ISNUMBER(H54)),H54-G54,"") | J54: =IF(AND(ISNUMBER(E54),E54>0,ISNUMBER(H54)),H54/E54,"") -> 0.44525547 | K54: In Progress | L54: =IF(M54="Yes","🔴 BOTTOM",IF(M54="No","✓ Cleared",IF(Q54="MIN",IF(AND(ISNUMBER(F54),ISNUMBER(H54)),IF(H54<F54*'Master Dashboard'!$B$4,"🔴 LOW",""),""),IF(Q54="MAX",IF(AND(ISNUMBER(F54),ISNUMBER(H54)),IF(H54>F54,"🔴 HIGH",""),""),"")))) -> 🔴 LOW | M54: Auto | N54: Gov Cell (report) | O54: 05-06-2026 | P54: Houses 56,132/60,791 (92%) | Q54: MIN | R54: ADCG-052
C55: HLBs completed — Tehsil Jagraon | D55: HLBs | E55: 435 | F55: 218 | H55: 278 | I55: =IF(AND(ISNUMBER(G55),ISNUMBER(H55)),H55-G55,"") | J55: =IF(AND(ISNUMBER(E55),E55>0,ISNUMBER(H55)),H55/E55,"") -> 0.63908046 | K55: In Progress | L55: =IF(M55="Yes","🔴 BOTTOM",IF(M55="No","✓ Cleared",IF(Q55="MIN",IF(AND(ISNUMBER(F55),ISNUMBER(H55)),IF(H55<F55*'Master Dashboard'!$B$4,"🔴 LOW",""),""),IF(Q55="MAX",IF(AND(ISNUMBER(F55),ISNUMBER(H55)),IF(H55>F55,"🔴 HIGH",""),""),"")))) | M55: Auto | N55: Gov Cell (report) | O55: 05-06-2026 | P55: Houses 91,305/96,859 (94%) | Q55: MIN | R55: ADCG-053
C56: HLBs completed — MC Macchhiwara | D56: HLBs | E56: 49 | F56: 24 | H56: 33 | I56: =IF(AND(ISNUMBER(G56),ISNUMBER(H56)),H56-G56,"") | J56: =IF(AND(ISNUMBER(E56),E56>0,ISNUMBER(H56)),H56/E56,"") -> 0.67346939 | K56: In Progress | L56: =IF(M56="Yes","🔴 BOTTOM",IF(M56="No","✓ Cleared",IF(Q56="MIN",IF(AND(ISNUMBER(F56),ISNUMBER(H56)),IF(H56<F56*'Master Dashboard'!$B$4,"🔴 LOW",""),""),IF(Q56="MAX",IF(AND(ISNUMBER(F56),ISNUMBER(H56)),IF(H56>F56,"🔴 HIGH",""),""),"")))) | M56: Auto | N56: Gov Cell (report) | O56: 05-06-2026 | P56: Houses 11,625/12,156 (96%) | Q56: MIN | R56: ADCG-054
C57: HLBs completed — MC Samrala | D57: HLBs | E57: 38 | F57: 19 | H57: 30 | I57: =IF(AND(ISNUMBER(G57),ISNUMBER(H57)),H57-G57,"") | J57: =IF(AND(ISNUMBER(E57),E57>0,ISNUMBER(H57)),H57/E57,"") -> 0.78947368 | K57: In Progress | L57: =IF(M57="Yes","🔴 BOTTOM",IF(M57="No","✓ Cleared",IF(Q57="MIN",IF(AND(ISNUMBER(F57),ISNUMBER(H57)),IF(H57<F57*'Master Dashboard'!$B$4,"🔴 LOW",""),""),IF(Q57="MAX",IF(AND(ISNUMBER(F57),ISNUMBER(H57)),IF(H57>F57,"🔴 HIGH",""),""),"")))) | M57: Auto | N57: Gov Cell (report) | O57: 05-06-2026 | P57: Houses 9,706/9,628 (101%) | Q57: MIN | R57: ADCG-055
C58: HLBs completed — MC Khanna | D58: HLBs | E58: 224 | F58: 112 | H58: 125 | I58: =IF(AND(ISNUMBER(G58),ISNUMBER(H58)),H58-G58,"") | J58: =IF(AND(ISNUMBER(E58),E58>0,ISNUMBER(H58)),H58/E58,"") -> 0.55803571 | K58: In Progress | L58: =IF(M58="Yes","🔴 BOTTOM",IF(M58="No","✓ Cleared",IF(Q58="MIN",IF(AND(ISNUMBER(F58),ISNUMBER(H58)),IF(H58<F58*'Master Dashboard'!$B$4,"🔴 LOW",""),""),IF(Q58="MAX",IF(AND(ISNUMBER(F58),ISNUMBER(H58)),IF(H58>F58,"🔴 HIGH",""),""),"")))) | M58: Auto | N58: Gov Cell (report) | O58: 05-06-2026 | P58: Houses 37,058/43,958 (84%) | Q58: MIN | R58: ADCG-056
... C65: HLBs completed — MC Jagraon | D65: HLBs | E65: 87 | F65: 44 | H65: 16 | I65: =IF(AND(ISNUMBER(G65),ISNUMBER(H65)),H65-G65,"") | J65: =IF(AND(ISNUMBER(E65),E65>0,ISNUMBER(H65)),H65/E65,"") -> 0.18390805 | K65: In Progress | L65: =IF(M65="Yes","🔴 BOTTOM",IF(M65="No","✓ Cleared",IF(Q65="MIN",IF(AND(ISNUMBER(F65),ISNUMBER(H65)),IF(H65<F65*'Master Dashboard'!$B$4,"🔴 LOW",""),""),IF(Q65="MAX",IF(AND(ISNUMBER(F65),ISNUMBER(H65)),IF(H65>F65,"🔴 HIGH",""),""),"")))) -> 🔴 LOW | M65: Auto | N65: Gov Cell (report) | O65: 05-06-2026 | P65: Houses 20,131/24,117 (83%) | Q65: MIN | R65: ADCG-063
A66: 4 | B66: SIR — Electors Mapped (AC-wise) | C66: 📊 Total electors (district) | H66: 2685915 | P66: Mapped 20,21,328 (75.26%) | Not mapped 6,64,587. 8 ACs below the 75% bar.
C67: 57-Khanna — electors mapped | D67: electors | E67: 174276 | F67: 130707 | H67: 134167 | I67: =IF(AND(ISNUMBER(G67),ISNUMBER(H67)),H67-G67,"") | J67: =IF(AND(ISNUMBER(E67),E67>0,ISNUMBER(H67)),H67/E67,"") -> 0.76985357 | K67: On Track | L67: =IF(M67="Yes","🔴 BOTTOM",IF(M67="No","✓ Cleared",IF(Q67="MIN",IF(AND(ISNUMBER(F67),ISNUMBER(H67)),IF(H67<F67*'Master Dashboard'!$B$4,"🔴 LOW",""),""),IF(Q67="MAX",IF(AND(ISNUMBER(F67),ISNUMBER(H67)),IF(H67>F67,"🔴 HIGH",""),""),"")))) | M67: Auto | N67: Gov Cell (report) | O67: 05-06-2026 | P67: Not mapped 40,109 (77.0%) — Electors mapped of total in this AC; bar = 75% of total electors. | Q67: MIN | R67: ADCG-064
C68: 58-Samrala — electors mapped | D68: electors | E68: 176828 | F68: 132621 | H68: 154962 | I68: =IF(AND(ISNUMBER(G68),ISNUMBER(H68)),H68-G68,"") | J68: =IF(AND(ISNUMBER(E68),E68>0,ISNUMBER(H68)),H68/E68,"") -> 0.87634311 | K68: On Track | L68: =IF(M68="Yes","🔴 BOTTOM",IF(M68="No","✓ Cleared",IF(Q68="MIN",IF(AND(ISNUMBER(F68),ISNUMBER(H68)),IF(H68<F68*'Master Dashboard'!$B$4,"🔴 LOW",""),""),IF(Q68="MAX",IF(AND(ISNUMBER(F68),ISNUMBER(H68)),IF(H68>F68,"🔴 HIGH",""),""),"")))) | M68: Auto | N68: Gov Cell (report) | O68: 05-06-2026 | P68: Not mapped 21,866 (87.6%) — Electors mapped of total in this AC; bar = 75% of total electors. | Q68: MIN | R68: ADCG-065
C69: 59-Sahnewal — electors mapped | D69: electors | E69: 274011 | F69: 205508 | H69: 193740 | I69: =IF(AND(ISNUMBER(G69),ISNUMBER(H69)),H69-G69,"") | J69: =IF(AND(ISNUMBER(E69),E69>0,ISNUMBER(H69)),H69/E69,"") -> 0.70705191 | K69: In Progress | L69: =IF(M69="Yes","🔴 BOTTOM",IF(M69="No","✓ Cleared",IF(Q69="MIN",IF(AND(ISNUMBER(F69),ISNUMBER(H69)),IF(H69<F69*'Master Dashboard'!$B$4,"🔴 LOW",""),""),IF(Q69="MAX",IF(AND(ISNUMBER(F69),ISNUMBER(H69)),IF(H69>F69,"🔴 HIGH",""),""),"")))) -> 🔴 LOW | M69: Auto | N69: Gov Cell (report) | O69: 05-06-2026 | P69: Not mapped 80,271 (70.7%) — Electors mapped of total in this AC; bar = 75% of total electors. | Q69: MIN | R69: ADCG-066
C70: 60-Ludhiana East — electors mapped | D70: electors | E70: 228802 | F70: 171602 | H70: 156290 | I70: =IF(AND(ISNUMBER(G70),ISNUMBER(H70)),H70-G70,"") | J70: =IF(AND(ISNUMBER(E70),E70>0,ISNUMBER(H70)),H70/E70,"") -> 0.68307969 | K70: In Progress | L70: =IF(M70="Yes","🔴 BOTTOM",IF(M70="No","✓ Cleared",IF(Q70="MIN",IF(AND(ISNUMBER(F70),ISNUMBER(H70)),IF(H70<F70*'Master Dashboard'!$B$4,"🔴 LOW",""),""),IF(Q70="MAX",IF(AND(ISNUMBER(F70),ISNUMBER(H70)),IF(H70>F70,"🔴 HIGH",""),""),"")))) -> 🔴 LOW | M70: Auto | N70: Gov Cell (report) | O70: 05-06-2026 | P70: Not mapped 72,512 (68.3%) — Electors mapped of total in this AC; bar = 75% of total electors. | Q70: MIN | R70: ADCG-067
C71: 61-Ludhiana South — electors mapped | D71: electors | E71: 183343 | F71: 137507 | H71: 109236 | I71: =IF(AND(ISNUMBER(G71),ISNUMBER(H71)),H71-G71,"") | J71: =IF(AND(ISNUMBER(E71),E71>0,ISNUMBER(H71)),H71/E71,"") -> 0.59580131 | K71: In Progress | L71: =IF(M71="Yes","🔴 BOTTOM",IF(M71="No","✓ Cleared",IF(Q71="MIN",IF(AND(ISNUMBER(F71),ISNUMBER(H71)),IF(H71<F71*'Master Dashboard'!$B$4,"🔴 LOW",""),""),IF(Q71="MAX",IF(AND(ISNUMBER(F71),ISNUMBER(H71)),IF(H71>F71,"🔴 HIGH",""),""),"")))) -> 🔴 LOW | M71: Auto | N71: Gov Cell (report) | O71: 05-06-2026 | P71: Not mapped 74,107 (59.6%) — Electors mapped of total in this AC; bar = 75% of total electors. | Q71: MIN | R71: ADCG-068
C72: 62-Atam Nagar — electors mapped | D72: electors | E72: 160607 | F72: 120455 | H72: 106731 | I72: =IF(AND(ISNUMBER(G72),ISNUMBER(H72)),H72-G72,"") | J72: =IF(AND(ISNUMBER(E72),E72>0,ISNUMBER(H72)),H72/E72,"") -> 0.66454762 | K72: In Progress | L72: =IF(M72="Yes","🔴 BOTTOM",IF(M72="No","✓ Cleared",IF(Q72="MIN",IF(AND(ISNUMBER(F72),ISNUMBER(H72)),IF(H72<F72*'Master Dashboard'!$B$4,"🔴 LOW",""),""),IF(Q72="MAX",IF(AND(ISNUMBER(F72),ISNUMBER(H72)),IF(H72>F72,"🔴 HIGH",""),""),"")))) -> 🔴 LOW | M72: Auto | N72: Gov Cell (report) | O72: 05-06-2026 | P72: Not mapped 53,876 (66.5%) — Electors mapped of total in this AC; bar = 75% of total electors. | Q72: MIN | R72: ADCG-069
C73: 63-Ludhiana Central — electors mapped | D73: electors | E73: 149728 | F73: 112296 | H73: 103728 | I73: =IF(AND(ISNUMBER(G73),ISNUMBER(H73)),H73-G73,"") | J73: =IF(AND(ISNUMBER(E73),E73>0,ISNUMBER(H73)),H73/E73,"") -> 0.69277623 | K73: In Progress | L73: =IF(M73="Yes","🔴 BOTTOM",IF(M73="No","✓ Cleared",IF(Q73="MIN",IF(AND(ISNUMBER(F73),ISNUMBER(H73)),IF(H73<F73*'Master Dashboard'!$B$4,"🔴 LOW",""),""),IF(Q73="MAX",IF(AND(ISNUMBER(F73),ISNUMBER(H73)),IF(H73>F73,"🔴 HIGH",""),""),"")))) -> 🔴 LOW | M73: Auto | N73: Gov Cell (report) | O73: 05-06-2026 | P73: Not mapped 46,000 (69.3%) — Electors mapped of total in this AC; bar = 75% of total electors. | Q73: MIN | R73: ADCG-070
C74: 64-Ludhiana West — electors mapped | D74: electors | E74: 169596 | F74: 127197 | H74: 112402 | I74: =IF(AND(ISNUMBER(G74),ISNUMBER(H74)),H74-G74,"") | J74: =IF(AND(ISNUMBER(E74),E74>0,ISNUMBER(H74)),H74/E74,"") -> 0.66276327 | K74: In Progress | L74: =IF(M74="Yes","🔴 BOTTOM",IF(M74="No","✓ Cleared",IF(Q74="MIN",IF(AND(ISNUMBER(F74),ISNUMBER(H74)),IF(H74<F74*'Master Dashboard'!$B$4,"🔴 LOW",""),""),IF(Q74="MAX",IF(AND(ISNUMBER(F74),ISNUMBER(H74)),IF(H74>F74,"🔴 HIGH",""),""),"")))) -> 🔴 LOW | M74: Auto | N74: Gov Cell (report) | O74: 05-06-2026 | P74: Not mapped 57,194 (66.3%) — Electors mapped of total in this AC; bar = 75% of total electors. | Q74: MIN | R74: ADCG-071
C75: 65-Ludhiana North — electors mapped | D75: electors | E75: 203121 | F75: 152341 | H75: 142413 | I75: =IF(AND(ISNUMBER(G75),ISNUMBER(H75)),H75-G75,"") | J75: =IF(AND(ISNUMBER(E75),E75>0,ISNUMBER(H75)),H75/E75,"") -> 0.70112396 | K75: In Progress | L75: =IF(M75="Yes","🔴 BOTTOM",IF(M75="No","✓ Cleared",IF(Q75="MIN",IF(AND(ISNUMBER(F75),ISNUMBER(H75)),IF(H75<F75*'Master Dashboard'!$B$4,"🔴 LOW",""),""),IF(Q75="MAX",IF(AND(ISNUMBER(F75),ISNUMBER(H75)),IF(H75>F75,"🔴 HIGH",""),""),"")))) -> 🔴 LOW | M75: Auto | N75: Gov Cell (report) | O75: 05-06-2026 | P75: Not mapped 60,708 (70.1%) — Electors mapped of total in this AC; bar = 75% of total electors. | Q75: MIN | R75: ADCG-072
C76: 66-Gill — electors mapped | D76: electors | E76: 284384 | F76: 213288 | H76: 212563 | I76: =IF(AND(ISNUMBER(G76),ISNUMBER(H76)),H76-G76,"") | J76: =IF(AND(ISNUMBER(E76),E76>0,ISNUMBER(H76)),H76/E76,"") -> 0.74745063 | K76: In Progress | L76: =IF(M76="Yes","🔴 BOTTOM",IF(M76="No","✓ Cleared",IF(Q76="MIN",IF(AND(ISNUMBER(F76),ISNUMBER(H76)),IF(H76<F76*'Master Dashboard'!$B$4,"🔴 LOW",""),""),IF(Q76="MAX",IF(AND(ISNUMBER(F76),ISNUMBER(H76)),IF(H76>F76,"🔴 HIGH",""),""),"")))) -> 🔴 LOW | M76: Auto | N76: Gov Cell (report) | O76: 05-06-2026 | P76: Not mapped 71,821 (74.8%) — Electors mapped of total in this AC; bar = 75% of total electors. | Q76: MIN | R76: ADCG-073
C77: 67-Payal — electors mapped | D77: electors | E77: 166556 | F77: 124917 | H77: 147687 | I77: =IF(AND(ISNUMBER(G77),ISNUMBER(H77)),H77-G77,"") | J77: =IF(AND(ISNUMBER(E77),E77>0,ISNUMBER(H77)),H77/E77,"") -> 0.88671078 | K77: On Track | L77: =IF(M77="Yes","🔴 BOTTOM",IF(M77="No","✓ Cleared",IF(Q77="MIN",IF(AND(ISNUMBER(F77),ISNUMBER(H77)),IF(H77<F77*'Master Dashboard'!$B$4,"🔴 LOW",""),""),IF(Q77="MAX",IF(AND(ISNUMBER(F77),ISNUMBER(H77)),IF(H77>F77,"🔴 HIGH",""),""),"")))) | M77: Auto | N77: Gov Cell (report) | O77: 05-06-2026 | P77: Not mapped 18,869 (88.7%) — Electors mapped of total in this AC; bar = 75% of total electors. | Q77: MIN | R77: ADCG-074
C78: 68-Dakha — electors mapped | D78: electors | E78: 184119 | F78: 138089 | H78: 160838 | I78: =IF(AND(ISNUMBER(G78),ISNUMBER(H78)),H78-G78,"") | J78: =IF(AND(ISNUMBER(E78),E78>0,ISNUMBER(H78)),H78/E78,"") -> 0.8735546 | K78: On Track | L78: =IF(M78="Yes","🔴 BOTTOM",IF(M78="No","✓ Cleared",IF(Q78="MIN",IF(AND(ISNUMBER(F78),ISNUMBER(H78)),IF(H78<F78*'Master Dashboard'!$B$4,"🔴 LOW",""),""),IF(Q78="MAX",IF(AND(ISNUMBER(F78),ISNUMBER(H78)),IF(H78>F78,"🔴 HIGH",""),""),"")))) | M78: Auto | N78: Gov Cell (report) | O78: 05-06-2026 | P78: Not mapped 23,281 (87.4%) — Electors mapped of total in this AC; bar = 75% of total electors. | Q78: MIN | R78: ADCG-075
... C81: District — electors mapped | D81: electors | E81: 2685915 | F81: 2014436 | H81: 2021328 | I81: =IF(AND(ISNUMBER(G81),ISNUMBER(H81)),H81-G81,"") | J81: =IF(AND(ISNUMBER(E81),E81>0,ISNUMBER(H81)),H81/E81,"") -> 0.75256589 | K81: In Progress | L81: =IF(M81="Yes","🔴 BOTTOM",IF(M81="No","✓ Cleared",IF(Q81="MIN",IF(AND(ISNUMBER(F81),ISNUMBER(H81)),IF(H81<F81*'Master Dashboard'!$B$4,"🔴 LOW",""),""),IF(Q81="MAX",IF(AND(ISNUMBER(F81),ISNUMBER(H81)),IF(H81>F81,"🔴 HIGH",""),""),"")))) | M81: Auto | N81: Gov Cell (report) | O81: 05-06-2026 | P81: Not mapped 664,587 (75.26%) — Electors mapped of total in this AC; bar = 75% of total electors. | Q81: MIN | R81: ADCG-078
A82: 5 | B82: SIR — EFDIATRIBUTED (AC-wise) | C82: 📊 Total electors (district) | H82: 2685915 | P82: Mapped 20,21,328 (75.26%) | Not mapped 6,64,587. 8 ACs below the 75% bar.
C83: 57-Khanna — electors mapped | D83: electors | E83: 174276 | F83: 130707 | H83: 134167 | I83: =IF(AND(ISNUMBER(G83),ISNUMBER(H83)),H83-G83,"") | J83: =IF(AND(ISNUMBER(E83),E83>0,ISNUMBER(H83)),H83/E83,"") -> 0.76985357 | K83: On Track | L83: =IF(M83="Yes","🔴 BOTTOM",IF(M83="No","✓ Cleared",IF(Q83="MIN",IF(AND(ISNUMBER(F83),ISNUMBER(H83)),IF(H83<F83*'Master Dashboard'!$B$4,"🔴 LOW",""),""),IF(Q83="MAX",IF(AND(ISNUMBER(F83),ISNUMBER(H83)),IF(H83>F83,"🔴 HIGH",""),""),"")))) | M83: Auto | N83: Gov Cell (report) | O83: 05-06-2026 | P83: Not mapped 40,109 (77.0%) — Electors mapped of total in this AC; bar = 75% of total electors. | Q83: MIN | R83: ADCG-064
C84: 58-Samrala — electors mapped | D84: electors | E84: 176828 | F84: 132621 | H84: 154962 | I84: =IF(AND(ISNUMBER(G84),ISNUMBER(H84)),H84-G84,"") | J84: =IF(AND(ISNUMBER(E84),E84>0,ISNUMBER(H84)),H84/E84,"") -> 0.87634311 | K84: On Track | L84: =IF(M84="Yes","🔴 BOTTOM",IF(M84="No","✓ Cleared",IF(Q84="MIN",IF(AND(ISNUMBER(F84),ISNUMBER(H84)),IF(H84<F84*'Master Dashboard'!$B$4,"🔴 LOW",""),""),IF(Q84="MAX",IF(AND(ISNUMBER(F84),ISNUMBER(H84)),IF(H84>F84,"🔴 HIGH",""),""),"")))) | M84: Auto | N84: Gov Cell (report) | O84: 05-06-2026 | P84: Not mapped 21,866 (87.6%) — Electors mapped of total in this AC; bar = 75% of total electors. | Q84: MIN | R84: ADCG-065
C85: 59-Sahnewal — electors mapped | D85: electors | E85: 274011 | F85: 205508 | H85: 193740 | I85: =IF(AND(ISNUMBER(G85),ISNUMBER(H85)),H85-G85,"") | J85: =IF(AND(ISNUMBER(E85),E85>0,ISNUMBER(H85)),H85/E85,"") -> 0.70705191 | K85: In Progress | L85: =IF(M85="Yes","🔴 BOTTOM",IF(M85="No","✓ Cleared",IF(Q85="MIN",IF(AND(ISNUMBER(F85),ISNUMBER(H85)),IF(H85<F85*'Master Dashboard'!$B$4,"🔴 LOW",""),""),IF(Q85="MAX",IF(AND(ISNUMBER(F85),ISNUMBER(H85)),IF(H85>F85,"🔴 HIGH",""),""),"")))) -> 🔴 LOW | M85: Auto | N85: Gov Cell (report) | O85: 05-06-2026 | P85: Not mapped 80,271 (70.7%) — Electors mapped of total in this AC; bar = 75% of total electors. | Q85: MIN | R85: ADCG-066
C86: 60-Ludhiana East — electors mapped | D86: electors | E86: 228802 | F86: 171602 | H86: 156290 | I86: =IF(AND(ISNUMBER(G86),ISNUMBER(H86)),H86-G86,"") | J86: =IF(AND(ISNUMBER(E86),E86>0,ISNUMBER(H86)),H86/E86,"") -> 0.68307969 | K86: In Progress | L86: =IF(M86="Yes","🔴 BOTTOM",IF(M86="No","✓ Cleared",IF(Q86="MIN",IF(AND(ISNUMBER(F86),ISNUMBER(H86)),IF(H86<F86*'Master Dashboard'!$B$4,"🔴 LOW",""),""),IF(Q86="MAX",IF(AND(ISNUMBER(F86),ISNUMBER(H86)),IF(H86>F86,"🔴 HIGH",""),""),"")))) -> 🔴 LOW | M86: Auto | N86: Gov Cell (report) | O86: 05-06-2026 | P86: Not mapped 72,512 (68.3%) — Electors mapped of total in this AC; bar = 75% of total electors. | Q86: MIN | R86: ADCG-067
C87: 61-Ludhiana South — electors mapped | D87: electors | E87: 183343 | F87: 137507 | H87: 109236 | I87: =IF(AND(ISNUMBER(G87),ISNUMBER(H87)),H87-G87,"") | J87: =IF(AND(ISNUMBER(E87),E87>0,ISNUMBER(H87)),H87/E87,"") -> 0.59580131 | K87: In Progress | L87: =IF(M87="Yes","🔴 BOTTOM",IF(M87="No","✓ Cleared",IF(Q87="MIN",IF(AND(ISNUMBER(F87),ISNUMBER(H87)),IF(H87<F87*'Master Dashboard'!$B$4,"🔴 LOW",""),""),IF(Q87="MAX",IF(AND(ISNUMBER(F87),ISNUMBER(H87)),IF(H87>F87,"🔴 HIGH",""),""),"")))) -> 🔴 LOW | M87: Auto | N87: Gov Cell (report) | O87: 05-06-2026 | P87: Not mapped 74,107 (59.6%) — Electors mapped of total in this AC; bar = 75% of total electors. | Q87: MIN | R87: ADCG-068
C88: 62-Atam Nagar — electors mapped | D88: electors | E88: 160607 | F88: 120455 | H88: 106731 | I88: =IF(AND(ISNUMBER(G88),ISNUMBER(H88)),H88-G88,"") | J88: =IF(AND(ISNUMBER(E88),E88>0,ISNUMBER(H88)),H88/E88,"") -> 0.66454762 | K88: In Progress | L88: =IF(M88="Yes","🔴 BOTTOM",IF(M88="No","✓ Cleared",IF(Q88="MIN",IF(AND(ISNUMBER(F88),ISNUMBER(H88)),IF(H88<F88*'Master Dashboard'!$B$4,"🔴 LOW",""),""),IF(Q88="MAX",IF(AND(ISNUMBER(F88),ISNUMBER(H88)),IF(H88>F88,"🔴 HIGH",""),""),"")))) -> 🔴 LOW | M88: Auto | N88: Gov Cell (report) | O88: 05-06-2026 | P88: Not mapped 53,876 (66.5%) — Electors mapped of total in this AC; bar = 75% of total electors. | Q88: MIN | R88: ADCG-069
C89: 63-Ludhiana Central — electors mapped | D89: electors | E89: 149728 | F89: 112296 | H89: 103728 | I89: =IF(AND(ISNUMBER(G89),ISNUMBER(H89)),H89-G89,"") | J89: =IF(AND(ISNUMBER(E89),E89>0,ISNUMBER(H89)),H89/E89,"") -> 0.69277623 | K89: In Progress | L89: =IF(M89="Yes","🔴 BOTTOM",IF(M89="No","✓ Cleared",IF(Q89="MIN",IF(AND(ISNUMBER(F89),ISNUMBER(H89)),IF(H89<F89*'Master Dashboard'!$B$4,"🔴 LOW",""),""),IF(Q89="MAX",IF(AND(ISNUMBER(F89),ISNUMBER(H89)),IF(H89>F89,"🔴 HIGH",""),""),"")))) -> 🔴 LOW | M89: Auto | N89: Gov Cell (report) | O89: 05-06-2026 | P89: Not mapped 46,000 (69.3%) — Electors mapped of total in this AC; bar = 75% of total electors. | Q89: MIN | R89: ADCG-070
C90: 64-Ludhiana West — electors mapped | D90: electors | E90: 169596 | F90: 127197 | H90: 112402 | I90: =IF(AND(ISNUMBER(G90),ISNUMBER(H90)),H90-G90,"") | J90: =IF(AND(ISNUMBER(E90),E90>0,ISNUMBER(H90)),H90/E90,"") -> 0.66276327 | K90: In Progress | L90: =IF(M90="Yes","🔴 BOTTOM",IF(M90="No","✓ Cleared",IF(Q90="MIN",IF(AND(ISNUMBER(F90),ISNUMBER(H90)),IF(H90<F90*'Master Dashboard'!$B$4,"🔴 LOW",""),""),IF(Q90="MAX",IF(AND(ISNUMBER(F90),ISNUMBER(H90)),IF(H90>F90,"🔴 HIGH",""),""),"")))) -> 🔴 LOW | M90: Auto | N90: Gov Cell (report) | O90: 05-06-2026 | P90: Not mapped 57,194 (66.3%) — Electors mapped of total in this AC; bar = 75% of total electors. | Q90: MIN | R90: ADCG-071
C91: 65-Ludhiana North — electors mapped | D91: electors | E91: 203121 | F91: 152341 | H91: 142413 | I91: =IF(AND(ISNUMBER(G91),ISNUMBER(H91)),H91-G91,"") | J91: =IF(AND(ISNUMBER(E91),E91>0,ISNUMBER(H91)),H91/E91,"") -> 0.70112396 | K91: In Progress | L91: =IF(M91="Yes","🔴 BOTTOM",IF(M91="No","✓ Cleared",IF(Q91="MIN",IF(AND(ISNUMBER(F91),ISNUMBER(H91)),IF(H91<F91*'Master Dashboard'!$B$4,"🔴 LOW",""),""),IF(Q91="MAX",IF(AND(ISNUMBER(F91),ISNUMBER(H91)),IF(H91>F91,"🔴 HIGH",""),""),"")))) -> 🔴 LOW | M91: Auto | N91: Gov Cell (report) | O91: 05-06-2026 | P91: Not mapped 60,708 (70.1%) — Electors mapped of total in this AC; bar = 75% of total electors. | Q91: MIN | R91: ADCG-072
C92: 66-Gill — electors mapped | D92: electors | E92: 284384 | F92: 213288 | H92: 212563 | I92: =IF(AND(ISNUMBER(G92),ISNUMBER(H92)),H92-G92,"") | J92: =IF(AND(ISNUMBER(E92),E92>0,ISNUMBER(H92)),H92/E92,"") -> 0.74745063 | K92: In Progress | L92: =IF(M92="Yes","🔴 BOTTOM",IF(M92="No","✓ Cleared",IF(Q92="MIN",IF(AND(ISNUMBER(F92),ISNUMBER(H92)),IF(H92<F92*'Master Dashboard'!$B$4,"🔴 LOW",""),""),IF(Q92="MAX",IF(AND(ISNUMBER(F92),ISNUMBER(H92)),IF(H92>F92,"🔴 HIGH",""),""),"")))) -> 🔴 LOW | M92: Auto | N92: Gov Cell (report) | O92: 05-06-2026 | P92: Not mapped 71,821 (74.8%) — Electors mapped of total in this AC; bar = 75% of total electors. | Q92: MIN | R92: ADCG-073
C93: 67-Payal — electors mapped | D93: electors | E93: 166556 | F93: 124917 | H93: 147687 | I93: =IF(AND(ISNUMBER(G93),ISNUMBER(H93)),H93-G93,"") | J93: =IF(AND(ISNUMBER(E93),E93>0,ISNUMBER(H93)),H93/E93,"") -> 0.88671078 | K93: On Track | L93: =IF(M93="Yes","🔴 BOTTOM",IF(M93="No","✓ Cleared",IF(Q93="MIN",IF(AND(ISNUMBER(F93),ISNUMBER(H93)),IF(H93<F93*'Master Dashboard'!$B$4,"🔴 LOW",""),""),IF(Q93="MAX",IF(AND(ISNUMBER(F93),ISNUMBER(H93)),IF(H93>F93,"🔴 HIGH",""),""),"")))) | M93: Auto | N93: Gov Cell (report) | O93: 05-06-2026 | P93: Not mapped 18,869 (88.7%) — Electors mapped of total in this AC; bar = 75% of total electors. | Q93: MIN | R93: ADCG-074
C94: 68-Dakha — electors mapped | D94: electors | E94: 184119 | F94: 138089 | H94: 160838 | I94: =IF(AND(ISNUMBER(G94),ISNUMBER(H94)),H94-G94,"") | J94: =IF(AND(ISNUMBER(E94),E94>0,ISNUMBER(H94)),H94/E94,"") -> 0.8735546 | K94: On Track | L94: =IF(M94="Yes","🔴 BOTTOM",IF(M94="No","✓ Cleared",IF(Q94="MIN",IF(AND(ISNUMBER(F94),ISNUMBER(H94)),IF(H94<F94*'Master Dashboard'!$B$4,"🔴 LOW",""),""),IF(Q94="MAX",IF(AND(ISNUMBER(F94),ISNUMBER(H94)),IF(H94>F94,"🔴 HIGH",""),""),"")))) | M94: Auto | N94: Gov Cell (report) | O94: 05-06-2026 | P94: Not mapped 23,281 (87.4%) — Electors mapped of total in this AC; bar = 75% of total electors. | Q94: MIN | R94: ADCG-075
A95: 6 | B95: Stubble Burning | C95: 📊 Environmental Compensation cases | H95: 93 | P95: EC imposed Rs 4,90,000 | Red entries 67 | FIRs 1 | Field visits pending 108.
C96: Environmental Compensation — cases | D96: cases | H96: 93 | I96: =IF(AND(ISNUMBER(G96),ISNUMBER(H96)),H96-G96,"") | J96: =IF(AND(ISNUMBER(E96),E96>0,ISNUMBER(H96)),H96/E96,"") | K96: In Progress | L96: =IF(M96="Yes","🔴 BOTTOM",IF(M96="No","✓ Cleared",IF(Q96="MIN",IF(AND(ISNUMBER(F96),ISNUMBER(H96)),IF(H96<F96*'Master Dashboard'!$B$4,"🔴 LOW",""),""),IF(Q96="MAX",IF(AND(ISNUMBER(F96),ISNUMBER(H96)),IF(H96>F96,"🔴 HIGH",""),""),"")))) | M96: Auto | N96: Gov Cell (report) | O96: 05-06-2026 | P96: Total EC imposed Rs 4,90,000 | R96: ADCG-094
C97: Red entries (as on 17.05) | D97: entries | E97: 0 | F97: 0 | H97: 67 | I97: =IF(AND(ISNUMBER(G97),ISNUMBER(H97)),H97-G97,"") | J97: =IF(AND(ISNUMBER(E97),E97>0,ISNUMBER(H97)),H97/E97,"") | K97: Pending/Blocked | L97: =IF(M97="Yes","🔴 BOTTOM",IF(M97="No","✓ Cleared",IF(Q97="MIN",IF(AND(ISNUMBER(F97),ISNUMBER(H97)),IF(H97<F97*'Master Dashboard'!$B$4,"🔴 LOW",""),""),IF(Q97="MAX",IF(AND(ISNUMBER(F97),ISNUMBER(H97)),IF(H97>F97,"🔴 HIGH",""),""),"")))) -> 🔴 HIGH | M97: Auto | N97: Gov Cell (report) | O97: 05-06-2026 | P97: Raikot & Jagraon flagged | Q97: MAX | R97: ADCG-095
C98: FIRs filed | D98: FIRs | H98: 1 | I98: =IF(AND(ISNUMBER(G98),ISNUMBER(H98)),H98-G98,"") | J98: =IF(AND(ISNUMBER(E98),E98>0,ISNUMBER(H98)),H98/E98,"") | K98: In Progress | L98: =IF(M98="Yes","🔴 BOTTOM",IF(M98="No","✓ Cleared",IF(Q98="MIN",IF(AND(ISNUMBER(F98),ISNUMBER(H98)),IF(H98<F98*'Master Dashboard'!$B$4,"🔴 LOW",""),""),IF(Q98="MAX",IF(AND(ISNUMBER(F98),ISNUMBER(H98)),IF(H98>F98,"🔴 HIGH",""),""),"")))) | M98: Auto | N98: Gov Cell (report) | O98: 05-06-2026 | R98: ADCG-096
C99: Visits pending (of incidents) | D99: visits | E99: 0 | F99: 0 | H99: 108 | I99: =IF(AND(ISNUMBER(G99),ISNUMBER(H99)),H99-G99,"") | J99: =IF(AND(ISNUMBER(E99),E99>0,ISNUMBER(H99)),H99/E99,"") | K99: Pending/Blocked | L99: =IF(M99="Yes","🔴 BOTTOM",IF(M99="No","✓ Cleared",IF(Q99="MIN",IF(AND(ISNUMBER(F99),ISNUMBER(H99)),IF(H99<F99*'Master Dashboard'!$B$4,"🔴 LOW",""),""),IF(Q99="MAX",IF(AND(ISNUMBER(F99),ISNUMBER(H99)),IF(H99>F99,"🔴 HIGH",""),""),"")))) -> 🔴 HIGH | M99: Auto | N99: Gov Cell (report) | O99: 05-06-2026 | Q99: MAX | R99: ADCG-097
A100: 7 | B100: Revenue — Uncontested Mutation Pendency | C100: 📊 Highest pendency officer | H100: 653 | P100: NT Ludhiana East (653) is the single highest in the district. Target: keep each below 200.
C101: Mutations pending — NT Ludhiana East | D101: cases | F101: 200 | G101: 688 | H101: 653 | I101: =IF(AND(ISNUMBER(G101),ISNUMBER(H101)),H101-G101,"") -> -35 | J101: =IF(AND(ISNUMBER(E101),E101>0,ISNUMBER(H101)),H101/E101,"") | K101: Pending/Blocked | L101: =IF(M101="Yes","🔴 BOTTOM",IF(M101="No","✓ Cleared",IF(Q101="MIN",IF(AND(ISNUMBER(F101),ISNUMBER(H101)),IF(H101<F101*'Master Dashboard'!$B$4,"🔴 LOW",""),""),IF(Q101="MAX",IF(AND(ISNUMBER(F101),ISNUMBER(H101)),IF(H101>F101,"🔴 HIGH",""),""),"")))) -> 🔴 HIGH | M101: Auto | N101: Gov Cell (report) | O101: 05-06-2026 | P101: Uncontested mutations pending with this officer; Change = movement since last review. | Q101: MAX | R101: ADCG-100
C102: Mutations pending — NT Ludhiana West | D102: cases | F102: 200 | G102: 207 | H102: 220 | I102: =IF(AND(ISNUMBER(G102),ISNUMBER(H102)),H102-G102,"") -> 13 | J102: =IF(AND(ISNUMBER(E102),E102>0,ISNUMBER(H102)),H102/E102,"") | K102: Pending/Blocked | L102: =IF(M102="Yes","🔴 BOTTOM",IF(M102="No","✓ Cleared",IF(Q102="MIN",IF(AND(ISNUMBER(F102),ISNUMBER(H102)),IF(H102<F102*'Master Dashboard'!$B$4,"🔴 LOW",""),""),IF(Q102="MAX",IF(AND(ISNUMBER(F102),ISNUMBER(H102)),IF(H102>F102,"🔴 HIGH",""),""),"")))) -> 🔴 HIGH | M102: Auto | N102: Gov Cell (report) | O102: 05-06-2026 | P102: Uncontested mutations pending with this officer; Change = movement since last review. | Q102: MAX | R102: ADCG-101
C103: Mutations pending — T Ludhiana West | D103: cases | F103: 200 | G103: 175 | H103: 201 | I103: =IF(AND(ISNUMBER(G103),ISNUMBER(H103)),H103-G103,"") -> 26 | J103: =IF(AND(ISNUMBER(E103),E103>0,ISNUMBER(H103)),H103/E103,"") | K103: Pending/Blocked | L103: =IF(M103="Yes","🔴 BOTTOM",IF(M103="No","✓ Cleared",IF(Q103="MIN",IF(AND(ISNUMBER(F103),ISNUMBER(H103)),IF(H103<F103*'Master Dashboard'!$B$4,"🔴 LOW",""),""),IF(Q103="MAX",IF(AND(ISNUMBER(F103),ISNUMBER(H103)),IF(H103>F103,"🔴 HIGH",""),""),"")))) -> 🔴 HIGH | M103: Auto | N103: Gov Cell (report) | O103: 05-06-2026 | P103: Uncontested mutations pending with this officer; Change = movement since last review. | Q103: MAX | R103: ADCG-102
C104: Mutations pending — NT Ludhiana South | D104: cases | F104: 200 | G104: 180 | H104: 180 | I104: =IF(AND(ISNUMBER(G104),ISNUMBER(H104)),H104-G104,"") -> 0 | J104: =IF(AND(ISNUMBER(E104),E104>0,ISNUMBER(H104)),H104/E104,"") | K104: In Progress | L104: =IF(M104="Yes","🔴 BOTTOM",IF(M104="No","✓ Cleared",IF(Q104="MIN",IF(AND(ISNUMBER(F104),ISNUMBER(H104)),IF(H104<F104*'Master Dashboard'!$B$4,"🔴 LOW",""),""),IF(Q104="MAX",IF(AND(ISNUMBER(F104),ISNUMBER(H104)),IF(H104>F104,"🔴 HIGH",""),""),"")))) | M104: Auto | N104: Gov Cell (report) | O104: 05-06-2026 | P104: Uncontested mutations pending with this officer; Change = movement since last review. | Q104: MAX | R104: ADCG-103
C105: Mutations pending — T Raikot | D105: cases | F105: 200 | G105: 48 | H105: 166 | I105: =IF(AND(ISNUMBER(G105),ISNUMBER(H105)),H105-G105,"") -> 118 | J105: =IF(AND(ISNUMBER(E105),E105>0,ISNUMBER(H105)),H105/E105,"") | K105: In Progress | L105: =IF(M105="Yes","🔴 BOTTOM",IF(M105="No","✓ Cleared",IF(Q105="MIN",IF(AND(ISNUMBER(F105),ISNUMBER(H105)),IF(H105<F105*'Master Dashboard'!$B$4,"🔴 LOW",""),""),IF(Q105="MAX",IF(AND(ISNUMBER(F105),ISNUMBER(H105)),IF(H105>F105,"🔴 HIGH",""),""),"")))) | M105: Auto | N105: Gov Cell (report) | O105: 05-06-2026 | P105: Sharp rise +118 — immediate attention — Uncontested mutations pending with this officer; Change = movement since last review. | Q105: MAX | R105: ADCG-104
C106: Mutations pending — T Ludhiana South | D106: cases | F106: 200 | G106: 123 | H106: 119 | I106: =IF(AND(ISNUMBER(G106),ISNUMBER(H106)),H106-G106,"") -> -4 | J106: =IF(AND(ISNUMBER(E106),E106>0,ISNUMBER(H106)),H106/E106,"") | K106: In Progress | L106: =IF(M106="Yes","🔴 BOTTOM",IF(M106="No","✓ Cleared",IF(Q106="MIN",IF(AND(ISNUMBER(F106),ISNUMBER(H106)),IF(H106<F106*'Master Dashboard'!$B$4,"🔴 LOW",""),""),IF(Q106="MAX",IF(AND(ISNUMBER(F106),ISNUMBER(H106)),IF(H106>F106,"🔴 HIGH",""),""),"")))) | M106: Auto | N106: Gov Cell (report) | O106: 05-06-2026 | P106: Uncontested mutations pending with this officer; Change = movement since last review. | Q106: MAX | R106: ADCG-105
C107: Mutations pending — NT Sidhwan Bet | D107: cases | F107: 200 | G107: 61 | H107: 82 | I107: =IF(AND(ISNUMBER(G107),ISNUMBER(H107)),H107-G107,"") -> 21 | J107: =IF(AND(ISNUMBER(E107),E107>0,ISNUMBER(H107)),H107/E107,"") | K107: In Progress | L107: =IF(M107="Yes","🔴 BOTTOM",IF(M107="No","✓ Cleared",IF(Q107="MIN",IF(AND(ISNUMBER(F107),ISNUMBER(H107)),IF(H107<F107*'Master Dashboard'!$B$4,"🔴 LOW",""),""),IF(Q107="MAX",IF(AND(ISNUMBER(F107),ISNUMBER(H107)),IF(H107>F107,"🔴 HIGH",""),""),"")))) | M107: Auto | N107: Gov Cell (report) | O107: 05-06-2026 | P107: Uncontested mutations pending with this officer; Change = movement since last review. | Q107: MAX | R107: ADCG-106
C108: Mutations pending — NT-2 Sahnewal | D108: cases | F108: 200 | G108: 79 | H108: 69 | I108: =IF(AND(ISNUMBER(G108),ISNUMBER(H108)),H108-G108,"") -> -10 | J108: =IF(AND(ISNUMBER(E108),E108>0,ISNUMBER(H108)),H108/E108,"") | K108: In Progress | L108: =IF(M108="Yes","🔴 BOTTOM",IF(M108="No","✓ Cleared",IF(Q108="MIN",IF(AND(ISNUMBER(F108),ISNUMBER(H108)),IF(H108<F108*'Master Dashboard'!$B$4,"🔴 LOW",""),""),IF(Q108="MAX",IF(AND(ISNUMBER(F108),ISNUMBER(H108)),IF(H108>F108,"🔴 HIGH",""),""),"")))) | M108: Auto | N108: Gov Cell (report) | O108: 05-06-2026 | P108: Uncontested mutations pending with this officer; Change = movement since last review. | Q108: MAX | R108: ADCG-107
C109: Mutations pending — NT Raikot | D109: cases | F109: 200 | G109: 135 | H109: 67 | I109: =IF(AND(ISNUMBER(G109),ISNUMBER(H109)),H109-G109,"") -> -68 | J109: =IF(AND(ISNUMBER(E109),E109>0,ISNUMBER(H109)),H109/E109,"") | K109: In Progress | L109: =IF(M109="Yes","🔴 BOTTOM",IF(M109="No","✓ Cleared",IF(Q109="MIN",IF(AND(ISNUMBER(F109),ISNUMBER(H109)),IF(H109<F109*'Master Dashboard'!$B$4,"🔴 LOW",""),""),IF(Q109="MAX",IF(AND(ISNUMBER(F109),ISNUMBER(H109)),IF(H109>F109,"🔴 HIGH",""),""),"")))) | M109: Auto | N109: Gov Cell (report) | O109: 05-06-2026 | P109: Uncontested mutations pending with this officer; Change = movement since last review. | Q109: MAX | R109: ADCG-108
C110: Mutations pending — NT Koom Kalan | D110: cases | F110: 200 | G110: 44 | H110: 57 | I110: =IF(AND(ISNUMBER(G110),ISNUMBER(H110)),H110-G110,"") -> 13 | J110: =IF(AND(ISNUMBER(E110),E110>0,ISNUMBER(H110)),H110/E110,"") | K110: In Progress | L110: =IF(M110="Yes","🔴 BOTTOM",IF(M110="No","✓ Cleared",IF(Q110="MIN",IF(AND(ISNUMBER(F110),ISNUMBER(H110)),IF(H110<F110*'Master Dashboard'!$B$4,"🔴 LOW",""),""),IF(Q110="MAX",IF(AND(ISNUMBER(F110),ISNUMBER(H110)),IF(H110>F110,"🔴 HIGH",""),""),"")))) | M110: Auto | N110: Gov Cell (report) | O110: 05-06-2026 | P110: Uncontested mutations pending with this officer; Change = movement since last review. | Q110: MAX | R110: ADCG-109
...

Sheet ADC (RD)
A1: ADC (RD) — Priority Agenda Review | DC Ludhiana (MASTER)
A2: Sr | B2: Priority Agenda | C2: KPI / Metric | D2: Concerned Officer / Unit | E2: Target / Total | F2: Flag Bar | G2: Last Value | H2: Current Value | I2: Change | J2: Achieved % | K2: Status | L2: Auto-Flag | M2: Bottom Performer | N2: Updated By | O2: Update Date | P2: Remarks / Context / Pending Action | Q2: Rule | R2: Key
A3: ▣ SCHEMES — metric-based (fed from officer workbook)
A4: 1 | B4: Mavan Dhiyan Satikar Yojana (MMMDSY) | C4: 📊 Mahila Satkar Sakhis registered | H4: 14548 | P4: of 25,556 target (56.92%, was 55.29%). Remaining 11,008.
C5: 📊 Anganwadi readiness | H5: Paint 72.8% | Furniture 100% | P5: Paintwork 1,810/2,487; chairs/tables/printing 100%. Nodals: BDPO 6/12, MCL 2/14.
C6: Mahila Satkar Sakhis — registered | D6: sakhis | E6: 25556 | F6: 20445 | G6: 14107 | H6: 14548 | I6: =IF(AND(ISNUMBER(G6),ISNUMBER(H6)),H6-G6,"") -> 441 | J6: =IF(AND(ISNUMBER(E6),E6>0,ISNUMBER(H6)),H6/E6,"") -> 0.56925967 | K6: In Progress | L6: =IF(M6="Yes","🔴 BOTTOM",IF(M6="No","✓ Cleared",IF(Q6="MIN",IF(AND(ISNUMBER(F6),ISNUMBER(H6)),IF(H6<F6*'Master Dashboard'!$B$4,"🔴 LOW",""),""),IF(Q6="MAX",IF(AND(ISNUMBER(F6),ISNUMBER(H6)),IF(H6>F6,"🔴 HIGH",""),""),"")))) -> 🔴 LOW | M6: Auto | N6: Gov Cell (report) | O6: 05-06-2026 | P6: Remaining 11,008 | 56.92% (was 55.29%) | Q6: MIN | R6: ADCRD-001
C7: Anganwadi Centres — paintwork done | D7: centres | E7: 2487 | F7: 2238 | G7: 1776 | H7: 1810 | I7: =IF(AND(ISNUMBER(G7),ISNUMBER(H7)),H7-G7,"") -> 34 | J7: =IF(AND(ISNUMBER(E7),E7>0,ISNUMBER(H7)),H7/E7,"") -> 0.72778448 | K7: In Progress | L7: =IF(M7="Yes","🔴 BOTTOM",IF(M7="No","✓ Cleared",IF(Q7="MIN",IF(AND(ISNUMBER(F7),ISNUMBER(H7)),IF(H7<F7*'Master Dashboard'!$B$4,"🔴 LOW",""),""),IF(Q7="MAX",IF(AND(ISNUMBER(F7),ISNUMBER(H7)),IF(H7>F7,"🔴 HIGH",""),""),"")))) -> 🔴 LOW | M7: Auto | N7: Gov Cell (report) | O7: 05-06-2026 | P7: Remaining 677 | 72.77% (was 71.4%) | Q7: MIN | R7: ADCRD-002
C8: Anganwadi Centres — chairs supplied | D8: centres | E8: 2487 | F8: 2487 | G8: 2487 | H8: 2487 | I8: =IF(AND(ISNUMBER(G8),ISNUMBER(H8)),H8-G8,"") -> 0 | J8: =IF(AND(ISNUMBER(E8),E8>0,ISNUMBER(H8)),H8/E8,"") -> 1 | K8: Completed | L8: =IF(M8="Yes","🔴 BOTTOM",IF(M8="No","✓ Cleared",IF(Q8="MIN",IF(AND(ISNUMBER(F8),ISNUMBER(H8)),IF(H8<F8*'Master Dashboard'!$B$4,"🔴 LOW",""),""),IF(Q8="MAX",IF(AND(ISNUMBER(F8),ISNUMBER(H8)),IF(H8>F8,"🔴 HIGH",""),""),"")))) | M8: Auto | N8: Gov Cell (report) | O8: 05-06-2026 | P8: 100% | Q8: MIN | R8: ADCRD-003
C9: Anganwadi Centres — tables supplied | D9: centres | E9: 2487 | F9: 2487 | G9: 2487 | H9: 2487 | I9: =IF(AND(ISNUMBER(G9),ISNUMBER(H9)),H9-G9,"") -> 0 | J9: =IF(AND(ISNUMBER(E9),E9>0,ISNUMBER(H9)),H9/E9,"") -> 1 | K9: Completed | L9: =IF(M9="Yes","🔴 BOTTOM",IF(M9="No","✓ Cleared",IF(Q9="MIN",IF(AND(ISNUMBER(F9),ISNUMBER(H9)),IF(H9<F9*'Master Dashboard'!$B$4,"🔴 LOW",""),""),IF(Q9="MAX",IF(AND(ISNUMBER(F9),ISNUMBER(H9)),IF(H9>F9,"🔴 HIGH",""),""),"")))) | M9: Auto | N9: Gov Cell (report) | O9: 05-06-2026 | P9: 100% | Q9: MIN | R9: ADCRD-004
C10: Anganwadi Centres — printing material | D10: centres | E10: 2487 | F10: 2487 | G10: 2487 | H10: 2487 | I10: =IF(AND(ISNUMBER(G10),ISNUMBER(H10)),H10-G10,"") -> 0 | J10: =IF(AND(ISNUMBER(E10),E10>0,ISNUMBER(H10)),H10/E10,"") -> 1 | K10: Completed | L10: =IF(M10="Yes","🔴 BOTTOM",IF(M10="No","✓ Cleared",IF(Q10="MIN",IF(AND(ISNUMBER(F10),ISNUMBER(H10)),IF(H10<F10*'Master Dashboard'!$B$4,"🔴 LOW",""),""),IF(Q10="MAX",IF(AND(ISNUMBER(F10),ISNUMBER(H10)),IF(H10>F10,"🔴 HIGH",""),""),"")))) | M10: Auto | N10: Gov Cell (report) | O10: 05-06-2026 | P10: 100% | Q10: MIN | R10: ADCRD-005
C11: BDPO Nodals appointed | D11: nodals | E11: 12 | F11: 12 | G11: 0 | H11: 6 | I11: =IF(AND(ISNUMBER(G11),ISNUMBER(H11)),H11-G11,"") -> 6 | J11: =IF(AND(ISNUMBER(E11),E11>0,ISNUMBER(H11)),H11/E11,"") -> 0.5 | K11: In Progress | L11: =IF(M11="Yes","🔴 BOTTOM",IF(M11="No","✓ Cleared",IF(Q11="MIN",IF(AND(ISNUMBER(F11),ISNUMBER(H11)),IF(H11<F11*'Master Dashboard'!$B$4,"🔴 LOW",""),""),IF(Q11="MAX",IF(AND(ISNUMBER(F11),ISNUMBER(H11)),IF(H11>F11,"🔴 HIGH",""),""),"")))) -> 🔴 LOW | M11: Auto | N11: Gov Cell (report) | O11: 05-06-2026 | P11: 50% (was 0%) | Q11: MIN | R11: ADCRD-006
C12: MCL Nodals appointed | D12: nodals | E12: 14 | F12: 14 | G12: 2 | H12: 2 | I12: =IF(AND(ISNUMBER(G12),ISNUMBER(H12)),H12-G12,"") -> 0 | J12: =IF(AND(ISNUMBER(E12),E12>0,ISNUMBER(H12)),H12/E12,"") -> 0.14285714 | K12: Pending/Blocked | L12: =IF(M12="Yes","🔴 BOTTOM",IF(M12="No","✓ Cleared",IF(Q12="MIN",IF(AND(ISNUMBER(F12),ISNUMBER(H12)),IF(H12<F12*'Master Dashboard'!$B$4,"🔴 LOW",""),""),IF(Q12="MAX",IF(AND(ISNUMBER(F12),ISNUMBER(H12)),IF(H12>F12,"🔴 HIGH",""),""),"")))) -> 🔴 LOW | M12: Auto | N12: Gov Cell (report) | O12: 05-06-2026 | P12: 14.2% — stalled | Q12: MIN | R12: ADCRD-007
A13: 2 | B13: Rangla Punjab — Phase I | C13: 📊 Total works proposed | H13: 433 | P13: District total, Phase I. Sanctioned amount Rs 34.99 Cr.
C14: 📊 Works started | H14: 431 | P14: 431 of 433 started (Total − Not started).
C15: 📊 Works in progress | H15: 326 | P15: Currently under execution.
C16: 📊 Works completed | H16: 105 | P16: Physically complete.
C17: 📊 Works NOT started | H17: 2 | P17: DD Animal Husbandry (1) + XEN Prov. Divn B&R (1).
C18: Phase I — works completed (district) | D18: works | E18: 433 | F18: 433 | H18: 105 | I18: =IF(AND(ISNUMBER(G18),ISNUMBER(H18)),H18-G18,"") | J18: =IF(AND(ISNUMBER(E18),E18>0,ISNUMBER(H18)),H18/E18,"") -> 0.24249423 | K18: In Progress | L18: =IF(M18="Yes","🔴 BOTTOM",IF(M18="No","✓ Cleared",IF(Q18="MIN",IF(AND(ISNUMBER(F18),ISNUMBER(H18)),IF(H18<F18*'Master Dashboard'!$B$4,"🔴 LOW",""),""),IF(Q18="MAX",IF(AND(ISNUMBER(F18),ISNUMBER(H18)),IF(H18>F18,"🔴 HIGH",""),""),"")))) -> 🔴 LOW | M18: Auto | N18: Gov Cell (report) | O18: 05-06-2026 | P18: 326 in progress; 2 not started | Q18: MIN | R18: ADCRD-008
C19: P-I completed — BDPO Doraha | D19: works | E19: 34 | F19: 1 | H19: 29 | I19: =IF(AND(ISNUMBER(G19),ISNUMBER(H19)),H19-G19,"") | J19: =IF(AND(ISNUMBER(E19),E19>0,ISNUMBER(H19)),H19/E19,"") -> 0.85294118 | K19: In Progress | L19: =IF(M19="Yes","🔴 BOTTOM",IF(M19="No","✓ Cleared",IF(Q19="MIN",IF(AND(ISNUMBER(F19),ISNUMBER(H19)),IF(H19<F19*'Master Dashboard'!$B$4,"🔴 LOW",""),""),IF(Q19="MAX",IF(AND(ISNUMBER(F19),ISNUMBER(H19)),IF(H19>F19,"🔴 HIGH",""),""),"")))) | M19: Auto | N19: Gov Cell (report) | O19: 05-06-2026 | P19: of 34 proposed — Phase-I works physically completed by this agency of its proposed total. | Q19: MIN | R19: ADCRD-009
C20: P-I completed — BDPO Jagraon | D20: works | E20: 42 | F20: 1 | H20: 4 | I20: =IF(AND(ISNUMBER(G20),ISNUMBER(H20)),H20-G20,"") | J20: =IF(AND(ISNUMBER(E20),E20>0,ISNUMBER(H20)),H20/E20,"") -> 0.095238095 | K20: In Progress | L20: =IF(M20="Yes","🔴 BOTTOM",IF(M20="No","✓ Cleared",IF(Q20="MIN",IF(AND(ISNUMBER(F20),ISNUMBER(H20)),IF(H20<F20*'Master Dashboard'!$B$4,"🔴 LOW",""),""),IF(Q20="MAX",IF(AND(ISNUMBER(F20),ISNUMBER(H20)),IF(H20>F20,"🔴 HIGH",""),""),"")))) | M20: Auto | N20: Gov Cell (report) | O20: 05-06-2026 | P20: of 42 proposed — Phase-I works physically completed by this agency of its proposed total. | Q20: MIN | R20: ADCRD-010
C21: P-I completed — BDPO Khanna | D21: works | E21: 26 | F21: 1 | H21: 0 | I21: =IF(AND(ISNUMBER(G21),ISNUMBER(H21)),H21-G21,"") | J21: =IF(AND(ISNUMBER(E21),E21>0,ISNUMBER(H21)),H21/E21,"") -> 0 | K21: In Progress | L21: =IF(M21="Yes","🔴 BOTTOM",IF(M21="No","✓ Cleared",IF(Q21="MIN",IF(AND(ISNUMBER(F21),ISNUMBER(H21)),IF(H21<F21*'Master Dashboard'!$B$4,"🔴 LOW",""),""),IF(Q21="MAX",IF(AND(ISNUMBER(F21),ISNUMBER(H21)),IF(H21>F21,"🔴 HIGH",""),""),"")))) -> 🔴 LOW | M21: Auto | N21: Gov Cell (report) | O21: 05-06-2026 | P21: of 26 proposed — Phase-I works physically completed by this agency of its proposed total. | Q21: MIN | R21: ADCRD-011
C22: P-I completed — BDPO Ludhiana One | D22: works | E22: 76 | F22: 1 | H22: 0 | I22: =IF(AND(ISNUMBER(G22),ISNUMBER(H22)),H22-G22,"") | J22: =IF(AND(ISNUMBER(E22),E22>0,ISNUMBER(H22)),H22/E22,"") -> 0 | K22: In Progress | L22: =IF(M22="Yes","🔴 BOTTOM",IF(M22="No","✓ Cleared",IF(Q22="MIN",IF(AND(ISNUMBER(F22),ISNUMBER(H22)),IF(H22<F22*'Master Dashboard'!$B$4,"🔴 LOW",""),""),IF(Q22="MAX",IF(AND(ISNUMBER(F22),ISNUMBER(H22)),IF(H22>F22,"🔴 HIGH",""),""),"")))) -> 🔴 LOW | M22: Auto | N22: Gov Cell (report) | O22: 05-06-2026 | P22: of 76 proposed — Phase-I works physically completed by this agency of its proposed total. | Q22: MIN | R22: ADCRD-012
C23: P-I completed — BDPO Ludhiana Two | D23: works | E23: 48 | F23: 1 | H23: 1 | I23: =IF(AND(ISNUMBER(G23),ISNUMBER(H23)),H23-G23,"") | J23: =IF(AND(ISNUMBER(E23),E23>0,ISNUMBER(H23)),H23/E23,"") -> 0.020833333 | K23: In Progress | L23: =IF(M23="Yes","🔴 BOTTOM",IF(M23="No","✓ Cleared",IF(Q23="MIN",IF(AND(ISNUMBER(F23),ISNUMBER(H23)),IF(H23<F23*'Master Dashboard'!$B$4,"🔴 LOW",""),""),IF(Q23="MAX",IF(AND(ISNUMBER(F23),ISNUMBER(H23)),IF(H23>F23,"🔴 HIGH",""),""),"")))) | M23: Auto | N23: Gov Cell (report) | O23: 05-06-2026 | P23: of 48 proposed — Phase-I works physically completed by this agency of its proposed total. | Q23: MIN | R23: ADCRD-013
C24: P-I completed — BDPO Maloud | D24: works | E24: 33 | F24: 1 | H24: 19 | I24: =IF(AND(ISNUMBER(G24),ISNUMBER(H24)),H24-G24,"") | J24: =IF(AND(ISNUMBER(E24),E24>0,ISNUMBER(H24)),H24/E24,"") -> 0.57575758 | K24: In Progress | L24: =IF(M24="Yes","🔴 BOTTOM",IF(M24="No","✓ Cleared",IF(Q24="MIN",IF(AND(ISNUMBER(F24),ISNUMBER(H24)),IF(H24<F24*'Master Dashboard'!$B$4,"🔴 LOW",""),""),IF(Q24="MAX",IF(AND(ISNUMBER(F24),ISNUMBER(H24)),IF(H24>F24,"🔴 HIGH",""),""),"")))) | M24: Auto | N24: Gov Cell (report) | O24: 05-06-2026 | P24: of 33 proposed — Phase-I works physically completed by this agency of its proposed total. | Q24: MIN | R24: ADCRD-014
C25: P-I completed — BDPO Raikot | D25: works | E25: 21 | F25: 1 | H25: 21 | I25: =IF(AND(ISNUMBER(G25),ISNUMBER(H25)),H25-G25,"") | J25: =IF(AND(ISNUMBER(E25),E25>0,ISNUMBER(H25)),H25/E25,"") -> 1 | K25: In Progress | L25: =IF(M25="Yes","🔴 BOTTOM",IF(M25="No","✓ Cleared",IF(Q25="MIN",IF(AND(ISNUMBER(F25),ISNUMBER(H25)),IF(H25<F25*'Master Dashboard'!$B$4,"🔴 LOW",""),""),IF(Q25="MAX",IF(AND(ISNUMBER(F25),ISNUMBER(H25)),IF(H25>F25,"🔴 HIGH",""),""),"")))) | M25: Auto | N25: Gov Cell (report) | O25: 05-06-2026 | P25: of 21 proposed — Phase-I works physically completed by this agency of its proposed total. | Q25: MIN | R25: ADCRD-015
C26: P-I completed — BDPO Samrala | D26: works | E26: 34 | F26: 1 | H26: 17 | I26: =IF(AND(ISNUMBER(G26),ISNUMBER(H26)),H26-G26,"") | J26: =IF(AND(ISNUMBER(E26),E26>0,ISNUMBER(H26)),H26/E26,"") -> 0.5 | K26: In Progress | L26: =IF(M26="Yes","🔴 BOTTOM",IF(M26="No","✓ Cleared",IF(Q26="MIN",IF(AND(ISNUMBER(F26),ISNUMBER(H26)),IF(H26<F26*'Master Dashboard'!$B$4,"🔴 LOW",""),""),IF(Q26="MAX",IF(AND(ISNUMBER(F26),ISNUMBER(H26)),IF(H26>F26,"🔴 HIGH",""),""),"")))) | M26: Auto | N26: Gov Cell (report) | O26: 05-06-2026 | P26: of 34 proposed — Phase-I works physically completed by this agency of its proposed total. | Q26: MIN | R26: ADCRD-016
C27: P-I completed — BDPO Sidhwan Bet | D27: works | E27: 24 | F27: 1 | H27: 10 | I27: =IF(AND(ISNUMBER(G27),ISNUMBER(H27)),H27-G27,"") | J27: =IF(AND(ISNUMBER(E27),E27>0,ISNUMBER(H27)),H27/E27,"") -> 0.41666667 | K27: In Progress | L27: =IF(M27="Yes","🔴 BOTTOM",IF(M27="No","✓ Cleared",IF(Q27="MIN",IF(AND(ISNUMBER(F27),ISNUMBER(H27)),IF(H27<F27*'Master Dashboard'!$B$4,"🔴 LOW",""),""),IF(Q27="MAX",IF(AND(ISNUMBER(F27),ISNUMBER(H27)),IF(H27>F27,"🔴 HIGH",""),""),"")))) | M27: Auto | N27: Gov Cell (report) | O27: 05-06-2026 | P27: of 24 proposed — Phase-I works physically completed by this agency of its proposed total. | Q27: MIN | R27: ADCRD-017
C28: P-I completed — BDPO Sudhar | D28: works | E28: 27 | F28: 1 | H28: 0 | I28: =IF(AND(ISNUMBER(G28),ISNUMBER(H28)),H28-G28,"") | J28: =IF(AND(ISNUMBER(E28),E28>0,ISNUMBER(H28)),H28/E28,"") -> 0 | K28: In Progress | L28: =IF(M28="Yes","🔴 BOTTOM",IF(M28="No","✓ Cleared",IF(Q28="MIN",IF(AND(ISNUMBER(F28),ISNUMBER(H28)),IF(H28<F28*'Master Dashboard'!$B$4,"🔴 LOW",""),""),IF(Q28="MAX",IF(AND(ISNUMBER(F28),ISNUMBER(H28)),IF(H28>F28,"🔴 HIGH",""),""),"")))) -> 🔴 LOW | M28: Auto | N28: Gov Cell (report) | O28: 05-06-2026 | P28: of 27 proposed — Phase-I works physically completed by this agency of its proposed total. | Q28: MIN | R28: ADCRD-018
C29: P-I completed — BDPO Pakhowal | D29: works | E29: 13 | F29: 1 | H29: 1 | I29: =IF(AND(ISNUMBER(G29),ISNUMBER(H29)),H29-G29,"") | J29: =IF(AND(ISNUMBER(E29),E29>0,ISNUMBER(H29)),H29/E29,"") -> 0.076923077 | K29: In Progress | L29: =IF(M29="Yes","🔴 BOTTOM",IF(M29="No","✓ Cleared",IF(Q29="MIN",IF(AND(ISNUMBER(F29),ISNUMBER(H29)),IF(H29<F29*'Master Dashboard'!$B$4,"🔴 LOW",""),""),IF(Q29="MAX",IF(AND(ISNUMBER(F29),ISNUMBER(H29)),IF(H29>F29,"🔴 HIGH",""),""),"")))) | M29: Auto | N29: Gov Cell (report) | O29: 05-06-2026 | P29: of 13 proposed — Phase-I works physically completed by this agency of its proposed total. | Q29: MIN | R29: ADCRD-019
C30: P-I completed — MCL | D30: works | E30: 39 | F30: 1 | H30: 0 | I30: =IF(AND(ISNUMBER(G30),ISNUMBER(H30)),H30-G30,"") | J30: =IF(AND(ISNUMBER(E30),E30>0,ISNUMBER(H30)),H30/E30,"") -> 0 | K30: In Progress | L30: =IF(M30="Yes","🔴 BOTTOM",IF(M30="No","✓ Cleared",IF(Q30="MIN",IF(AND(ISNUMBER(F30),ISNUMBER(H30)),IF(H30<F30*'Master Dashboard'!$B$4,"🔴 LOW",""),""),IF(Q30="MAX",IF(AND(ISNUMBER(F30),ISNUMBER(H30)),IF(H30>F30,"🔴 HIGH",""),""),"")))) -> 🔴 LOW | M30: Auto | N30: Gov Cell (report) | O30: 05-06-2026 | P30: of 39 proposed — Phase-I works physically completed by this agency of its proposed total. | Q30: MIN | R30: ADCRD-020
A31: 3 | B31: Rangla Punjab — Phase II | C31: 📊 Total works proposed | H31: 400 | P31: District total, Phase II. Sanctioned amount Rs 31.79 Cr.
C32: 📊 Works started | H32: 90 | P32: 90 of 400 started (Total − Not started).
C33: 📊 Works in progress | H33: 79 | P33: Currently under execution.
C34: 📊 Works completed | H34: 11 | P34: Physically complete.
C35: 📊 Works NOT started | H35: 310 | P35: All to begin by 5 June. Largest: MCL 73, Jagraon 43, Dehlon 30, Khanna 28.
C36: Phase II — works completed (district) | D36: works | E36: 400 | F36: 400 | H36: 11 | I36: =IF(AND(ISNUMBER(G36),ISNUMBER(H36)),H36-G36,"") | J36: =IF(AND(ISNUMBER(E36),E36>0,ISNUMBER(H36)),H36/E36,"") -> 0.0275 | K36: Pending/Blocked | L36: =IF(M36="Yes","🔴 BOTTOM",IF(M36="No","✓ Cleared",IF(Q36="MIN",IF(AND(ISNUMBER(F36),ISNUMBER(H36)),IF(H36<F36*'Master Dashboard'!$B$4,"🔴 LOW",""),""),IF(Q36="MAX",IF(AND(ISNUMBER(F36),ISNUMBER(H36)),IF(H36>F36,"🔴 HIGH",""),""),"")))) -> 🔴 LOW | M36: Auto | N36: Gov Cell (report) | O36: 05-06-2026 | P36: 79 in progress; 310 NOT started | Q36: MIN | R36: ADCRD-021
C37: Phase II — works NOT started (district) | D37: works | E37: 0 | F37: 0 | H37: 310 | I37: =IF(AND(ISNUMBER(G37),ISNUMBER(H37)),H37-G37,"") | J37: =IF(AND(ISNUMBER(E37),E37>0,ISNUMBER(H37)),H37/E37,"") | K37: Pending/Blocked | L37: =IF(M37="Yes","🔴 BOTTOM",IF(M37="No","✓ Cleared",IF(Q37="MIN",IF(AND(ISNUMBER(F37),ISNUMBER(H37)),IF(H37<F37*'Master Dashboard'!$B$4,"🔴 LOW",""),""),IF(Q37="MAX",IF(AND(ISNUMBER(F37),ISNUMBER(H37)),IF(H37>F37,"🔴 HIGH",""),""),"")))) -> 🔴 HIGH | M37: Auto | N37: Gov Cell (report) | O37: 05-06-2026 | P37: To start by 5 Jun | Q37: MAX | R37: ADCRD-022
C38: P-II not started — MCL | D38: works | E38: 0 | F38: 20 | H38: 73 | I38: =IF(AND(ISNUMBER(G38),ISNUMBER(H38)),H38-G38,"") | J38: =IF(AND(ISNUMBER(E38),E38>0,ISNUMBER(H38)),H38/E38,"") | K38: Pending/Blocked | L38: =IF(M38="Yes","🔴 BOTTOM",IF(M38="No","✓ Cleared",IF(Q38="MIN",IF(AND(ISNUMBER(F38),ISNUMBER(H38)),IF(H38<F38*'Master Dashboard'!$B$4,"🔴 LOW",""),""),IF(Q38="MAX",IF(AND(ISNUMBER(F38),ISNUMBER(H38)),IF(H38>F38,"🔴 HIGH",""),""),"")))) -> 🔴 HIGH | M38: Auto | N38: Gov Cell (report) | O38: 05-06-2026 | P38: of 73 proposed — Phase-II works not yet started by this agency of its proposed total. | Q38: MAX | R38: ADCRD-023
C39: P-II not started — BDPO Jagraon | D39: works | E39: 0 | F39: 20 | H39: 43 | I39: =IF(AND(ISNUMBER(G39),ISNUMBER(H39)),H39-G39,"") | J39: =IF(AND(ISNUMBER(E39),E39>0,ISNUMBER(H39)),H39/E39,"") | K39: Pending/Blocked | L39: =IF(M39="Yes","🔴 BOTTOM",IF(M39="No","✓ Cleared",IF(Q39="MIN",IF(AND(ISNUMBER(F39),ISNUMBER(H39)),IF(H39<F39*'Master Dashboard'!$B$4,"🔴 LOW",""),""),IF(Q39="MAX",IF(AND(ISNUMBER(F39),ISNUMBER(H39)),IF(H39>F39,"🔴 HIGH",""),""),"")))) -> 🔴 HIGH | M39: Auto | N39: Gov Cell (report) | O39: 05-06-2026 | P39: of 44 proposed — Phase-II works not yet started by this agency of its proposed total. | Q39: MAX | R39: ADCRD-024
C40: P-II not started — BDPO Khanna | D40: works | E40: 0 | F40: 20 | H40: 28 | I40: =IF(AND(ISNUMBER(G40),ISNUMBER(H40)),H40-G40,"") | J40: =IF(AND(ISNUMBER(E40),E40>0,ISNUMBER(H40)),H40/E40,"") | K40: Pending/Blocked | L40: =IF(M40="Yes","🔴 BOTTOM",IF(M40="No","✓ Cleared",IF(Q40="MIN",IF(AND(ISNUMBER(F40),ISNUMBER(H40)),IF(H40<F40*'Master Dashboard'!$B$4,"🔴 LOW",""),""),IF(Q40="MAX",IF(AND(ISNUMBER(F40),ISNUMBER(H40)),IF(H40>F40,"🔴 HIGH",""),""),"")))) -> 🔴 HIGH | M40: Auto | N40: Gov Cell (report) | O40: 05-06-2026 | P40: of 28 proposed — Phase-II works not yet started by this agency of its proposed total. | Q40: MAX | R40: ADCRD-025
C41: P-II not started — BDPO Dehlon | D41: works | E41: 0 | F41: 20 | H41: 30 | I41: =IF(AND(ISNUMBER(G41),ISNUMBER(H41)),H41-G41,"") | J41: =IF(AND(ISNUMBER(E41),E41>0,ISNUMBER(H41)),H41/E41,"") | K41: Pending/Blocked | L41: =IF(M41="Yes","🔴 BOTTOM",IF(M41="No","✓ Cleared",IF(Q41="MIN",IF(AND(ISNUMBER(F41),ISNUMBER(H41)),IF(H41<F41*'Master Dashboard'!$B$4,"🔴 LOW",""),""),IF(Q41="MAX",IF(AND(ISNUMBER(F41),ISNUMBER(H41)),IF(H41>F41,"🔴 HIGH",""),""),"")))) -> 🔴 HIGH | M41: Auto | N41: Gov Cell (report) | O41: 05-06-2026 | P41: of 30 proposed — Phase-II works not yet started by this agency of its proposed total. | Q41: MAX | R41: ADCRD-026
C42: P-II not started — BDPO Ludhiana One | D42: works | E42: 0 | F42: 20 | H42: 21 | I42: =IF(AND(ISNUMBER(G42),ISNUMBER(H42)),H42-G42,"") | J42: =IF(AND(ISNUMBER(E42),E42>0,ISNUMBER(H42)),H42/E42,"") | K42: Pending/Blocked | L42: =IF(M42="Yes","🔴 BOTTOM",IF(M42="No","✓ Cleared",IF(Q42="MIN",IF(AND(ISNUMBER(F42),ISNUMBER(H42)),IF(H42<F42*'Master Dashboard'!$B$4,"🔴 LOW",""),""),IF(Q42="MAX",IF(AND(ISNUMBER(F42),ISNUMBER(H42)),IF(H42>F42,"🔴 HIGH",""),""),"")))) -> 🔴 HIGH | M42: Auto | N42: Gov Cell (report) | O42: 05-06-2026 | P42: of 21 proposed — Phase-II works not yet started by this agency of its proposed total. | Q42: MAX | R42: ADCRD-027
C43: P-II not started — BDPO Doraha | D43: works | E43: 0 | F43: 20 | H43: 19 | I43: =IF(AND(ISNUMBER(G43),ISNUMBER(H43)),H43-G43,"") | J43: =IF(AND(ISNUMBER(E43),E43>0,ISNUMBER(H43)),H43/E43,"") | K43: Pending/Blocked | L43: =IF(M43="Yes","🔴 BOTTOM",IF(M43="No","✓ Cleared",IF(Q43="MIN",IF(AND(ISNUMBER(F43),ISNUMBER(H43)),IF(H43<F43*'Master Dashboard'!$B$4,"🔴 LOW",""),""),IF(Q43="MAX",IF(AND(ISNUMBER(F43),ISNUMBER(H43)),IF(H43>F43,"🔴 HIGH",""),""),"")))) | M43: Auto | N43: Gov Cell (report) | O43: 05-06-2026 | P43: of 43 proposed — Phase-II works not yet started by this agency of its proposed total. | Q43: MAX | R43: ADCRD-028
C44: P-II not started — BDPO Samrala | D44: works | E44: 0 | F44: 20 | H44: 19 | I44: =IF(AND(ISNUMBER(G44),ISNUMBER(H44)),H44-G44,"") | J44: =IF(AND(ISNUMBER(E44),E44>0,ISNUMBER(H44)),H44/E44,"") | K44: Pending/Blocked | L44: =IF(M44="Yes","🔴 BOTTOM",IF(M44="No","✓ Cleared",IF(Q44="MIN",IF(AND(ISNUMBER(F44),ISNUMBER(H44)),IF(H44<F44*'Master Dashboard'!$B$4,"🔴 LOW",""),""),IF(Q44="MAX",IF(AND(ISNUMBER(F44),ISNUMBER(H44)),IF(H44>F44,"🔴 HIGH",""),""),"")))) | M44: Auto | N44: Gov Cell (report) | O44: 05-06-2026 | P44: of 19 proposed — Phase-II works not yet started by this agency of its proposed total. | Q44: MAX | R44: ADCRD-029
C45: P-II not started — BDPO Maloud | D45: works | E45: 0 | F45: 20 | H45: 16 | I45: =IF(AND(ISNUMBER(G45),ISNUMBER(H45)),H45-G45,"") | J45: =IF(AND(ISNUMBER(E45),E45>0,ISNUMBER(H45)),H45/E45,"") | K45: Pending/Blocked | L45: =IF(M45="Yes","🔴 BOTTOM",IF(M45="No","✓ Cleared",IF(Q45="MIN",IF(AND(ISNUMBER(F45),ISNUMBER(H45)),IF(H45<F45*'Master Dashboard'!$B$4,"🔴 LOW",""),""),IF(Q45="MAX",IF(AND(ISNUMBER(F45),ISNUMBER(H45)),IF(H45>F45,"🔴 HIGH",""),""),"")))) | M45: Auto | N45: Gov Cell (report) | O45: 05-06-2026 | P45: of 19 proposed — Phase-II works not yet started by this agency of its proposed total. | Q45: MAX | R45: ADCRD-030
C46: P-II not started — BDPO Ludhiana Two | D46: works | E46: 0 | F46: 20 | H46: 47 | I46: =IF(AND(ISNUMBER(G46),ISNUMBER(H46)),H46-G46,"") | J46: =IF(AND(ISNUMBER(E46),E46>0,ISNUMBER(H46)),H46/E46,"") | K46: Pending/Blocked | L46: =IF(M46="Yes","🔴 BOTTOM",IF(M46="No","✓ Cleared",IF(Q46="MIN",IF(AND(ISNUMBER(F46),ISNUMBER(H46)),IF(H46<F46*'Master Dashboard'!$B$4,"🔴 LOW",""),""),IF(Q46="MAX",IF(AND(ISNUMBER(F46),ISNUMBER(H46)),IF(H46>F46,"🔴 HIGH",""),""),"")))) -> 🔴 HIGH | M46: Auto | N46: Gov Cell (report) | O46: 05-06-2026 | P46: of 48 proposed — Phase-II works not yet started by this agency of its proposed total. | Q46: MAX | R46: ADCRD-031
C47: P-II not started — BDPO Machhiwara | D47: works | E47: 0 | F47: 20 | H47: 4 | I47: =IF(AND(ISNUMBER(G47),ISNUMBER(H47)),H47-G47,"") | J47: =IF(AND(ISNUMBER(E47),E47>0,ISNUMBER(H47)),H47/E47,"") | K47: Pending/Blocked | L47: =IF(M47="Yes","🔴 BOTTOM",IF(M47="No","✓ Cleared",IF(Q47="MIN",IF(AND(ISNUMBER(F47),ISNUMBER(H47)),IF(H47<F47*'Master Dashboard'!$B$4,"🔴 LOW",""),""),IF(Q47="MAX",IF(AND(ISNUMBER(F47),ISNUMBER(H47)),IF(H47>F47,"🔴 HIGH",""),""),"")))) | M47: Auto | N47: Gov Cell (report) | O47: 05-06-2026 | P47: of 33 proposed — Phase-II works not yet started by this agency of its proposed total. | Q47: MAX | R47: ADCRD-032
... C49: P-II not started — EONC Raikot | D49: works | E49: 0 | F49: 20 | H49: 6 | I49: =IF(AND(ISNUMBER(G49),ISNUMBER(H49)),H49-G49,"") | J49: =IF(AND(ISNUMBER(E49),E49>0,ISNUMBER(H49)),H49/E49,"") | K49: Pending/Blocked | L49: =IF(M49="Yes","🔴 BOTTOM",IF(M49="No","✓ Cleared",IF(Q49="MIN",IF(AND(ISNUMBER(F49),ISNUMBER(H49)),IF(H49<F49*'Master Dashboard'!$B$4,"🔴 LOW",""),""),IF(Q49="MAX",IF(AND(ISNUMBER(F49),ISNUMBER(H49)),IF(H49>F49,"🔴 HIGH",""),""),"")))) | M49: Auto | N49: Gov Cell (report) | O49: 05-06-2026 | P49: of 7 proposed — Phase-II works not yet started by this agency of its proposed total. | Q49: MAX | R49: ADCRD-034
A50: 4 | B50: Mission Chardi Kalan | C50: 📊 Schools | H50: 9 proj | tender 9 | started 9 | done 0 | P50: Civil structure almost complete; UC & post-work photos pending from DEO.
C51: 📊 Hospitals | H51: 6 proj | tender 4 | started 0 | done 0 | P51: 2 tenders pending; 2 file-approved on portal; 2 estimates pending from XEN. PWD Kanech tender pending.
C52: Schools — tender done | D52: proj | E52: 9 | F52: 9 | H52: 9 | I52: =IF(AND(ISNUMBER(G52),ISNUMBER(H52)),H52-G52,"") | J52: =IF(AND(ISNUMBER(E52),E52>0,ISNUMBER(H52)),H52/E52,"") -> 1 | K52: In Progress | L52: =IF(M52="Yes","🔴 BOTTOM",IF(M52="No","✓ Cleared",IF(Q52="MIN",IF(AND(ISNUMBER(F52),ISNUMBER(H52)),IF(H52<F52*'Master Dashboard'!$B$4,"🔴 LOW",""),""),IF(Q52="MAX",IF(AND(ISNUMBER(F52),ISNUMBER(H52)),IF(H52>F52,"🔴 HIGH",""),""),"")))) | M52: Auto | N52: Gov Cell (report) | O52: 05-06-2026 | P52: 9 projects; work started 9 | Q52: MIN | R52: ADCRD-035
C53: Schools — work completed | D53: proj | E53: 9 | F53: 9 | H53: 0 | I53: =IF(AND(ISNUMBER(G53),ISNUMBER(H53)),H53-G53,"") | J53: =IF(AND(ISNUMBER(E53),E53>0,ISNUMBER(H53)),H53/E53,"") -> 0 | K53: In Progress | L53: =IF(M53="Yes","🔴 BOTTOM",IF(M53="No","✓ Cleared",IF(Q53="MIN",IF(AND(ISNUMBER(F53),ISNUMBER(H53)),IF(H53<F53*'Master Dashboard'!$B$4,"🔴 LOW",""),""),IF(Q53="MAX",IF(AND(ISNUMBER(F53),ISNUMBER(H53)),IF(H53>F53,"🔴 HIGH",""),""),"")))) -> 🔴 LOW | M53: Auto | N53: Gov Cell (report) | O53: 05-06-2026 | P53: UC submitted 0; civil almost done | Q53: MIN | R53: ADCRD-036
C54: Hospitals — tender done | D54: proj | E54: 6 | F54: 6 | H54: 4 | I54: =IF(AND(ISNUMBER(G54),ISNUMBER(H54)),H54-G54,"") | J54: =IF(AND(ISNUMBER(E54),E54>0,ISNUMBER(H54)),H54/E54,"") -> 0.66666667 | K54: Pending/Blocked | L54: =IF(M54="Yes","🔴 BOTTOM",IF(M54="No","✓ Cleared",IF(Q54="MIN",IF(AND(ISNUMBER(F54),ISNUMBER(H54)),IF(H54<F54*'Master Dashboard'!$B$4,"🔴 LOW",""),""),IF(Q54="MAX",IF(AND(ISNUMBER(F54),ISNUMBER(H54)),IF(H54>F54,"🔴 HIGH",""),""),"")))) -> 🔴 LOW | M54: Auto | N54: Gov Cell (report) | O54: 05-06-2026 | P54: 6 projects | Q54: MIN | R54: ADCRD-037
C55: Hospitals — work started | D55: proj | E55: 6 | F55: 6 | H55: 0 | I55: =IF(AND(ISNUMBER(G55),ISNUMBER(H55)),H55-G55,"") | J55: =IF(AND(ISNUMBER(E55),E55>0,ISNUMBER(H55)),H55/E55,"") -> 0 | K55: Pending/Blocked | L55: =IF(M55="Yes","🔴 BOTTOM",IF(M55="No","✓ Cleared",IF(Q55="MIN",IF(AND(ISNUMBER(F55),ISNUMBER(H55)),IF(H55<F55*'Master Dashboard'!$B$4,"🔴 LOW",""),""),IF(Q55="MAX",IF(AND(ISNUMBER(F55),ISNUMBER(H55)),IF(H55>F55,"🔴 HIGH",""),""),"")))) -> 🔴 LOW | M55: Auto | N55: Gov Cell (report) | O55: 05-06-2026 | P55: PWD Kanech tender pending | Q55: MIN | R55: ADCRD-038
A56: 5 | B56: Meri Yogyata Meri Pehchan | C56: Applications received | D56: apps | H56: 1544 | I56: =IF(AND(ISNUMBER(G56),ISNUMBER(H56)),H56-G56,"") | J56: =IF(AND(ISNUMBER(E56),E56>0,ISNUMBER(H56)),H56/E56,"") | K56: Not Started | L56: =IF(M56="Yes","🔴 BOTTOM",IF(M56="No","✓ Cleared",IF(Q56="MIN",IF(AND(ISNUMBER(F56),ISNUMBER(H56)),IF(H56<F56*'Master Dashboard'!$B$4,"🔴 LOW",""),""),IF(Q56="MAX",IF(AND(ISNUMBER(F56),ISNUMBER(H56)),IF(H56>F56,"🔴 HIGH",""),""),"")))) | M56: Auto | N56: Gov Cell (report) | O56: 05-06-2026 | P56: 291 name boards ready for installation | R56: ADCRD-040
C57: Installations done | D57: no. | E57: 1544 | F57: 772 | H57: 291 | I57: =IF(AND(ISNUMBER(G57),ISNUMBER(H57)),H57-G57,"") | J57: =IF(AND(ISNUMBER(E57),E57>0,ISNUMBER(H57)),H57/E57,"") -> 0.1884715 | K57: Not Started | L57: =IF(M57="Yes","🔴 BOTTOM",IF(M57="No","✓ Cleared",IF(Q57="MIN",IF(AND(ISNUMBER(F57),ISNUMBER(H57)),IF(H57<F57*'Master Dashboard'!$B$4,"🔴 LOW",""),""),IF(Q57="MAX",IF(AND(ISNUMBER(F57),ISNUMBER(H57)),IF(H57>F57,"🔴 HIGH",""),""),"")))) -> 🔴 LOW | M57: Auto | N57: Gov Cell (report) | O57: 05-06-2026 | P57: Pilot village planned; Rs8L budget | Q57: MIN | R57: ADCRD-041
A58: 6 | B58: Dengue & Vector Borne Disease | C58: 📊 Houses visited (district) | H58: 34565 | P58: Containers checked 66,456 | Positive 13 | Breeding-in-houses 11 | Challans 15 | Camps 206.
C59: Houses visited (district) | D59: houses | H59: 34565 | I59: =IF(AND(ISNUMBER(G59),ISNUMBER(H59)),H59-G59,"") | J59: =IF(AND(ISNUMBER(E59),E59>0,ISNUMBER(H59)),H59/E59,"") | K59: In Progress | L59: =IF(M59="Yes","🔴 BOTTOM",IF(M59="No","✓ Cleared",IF(Q59="MIN",IF(AND(ISNUMBER(F59),ISNUMBER(H59)),IF(H59<F59*'Master Dashboard'!$B$4,"🔴 LOW",""),""),IF(Q59="MAX",IF(AND(ISNUMBER(F59),ISNUMBER(H59)),IF(H59>F59,"🔴 HIGH",""),""),"")))) | M59: Auto | N59: Gov Cell (report) | O59: 05-06-2026 | P59: Block-wise survey | R59: ADCRD-042
C60: Containers checked | D60: no. | H60: 66456 | I60: =IF(AND(ISNUMBER(G60),ISNUMBER(H60)),H60-G60,"") | J60: =IF(AND(ISNUMBER(E60),E60>0,ISNUMBER(H60)),H60/E60,"") | K60: In Progress | L60: =IF(M60="Yes","🔴 BOTTOM",IF(M60="No","✓ Cleared",IF(Q60="MIN",IF(AND(ISNUMBER(F60),ISNUMBER(H60)),IF(H60<F60*'Master Dashboard'!$B$4,"🔴 LOW",""),""),IF(Q60="MAX",IF(AND(ISNUMBER(F60),ISNUMBER(H60)),IF(H60>F60,"🔴 HIGH",""),""),"")))) | M60: Auto | N60: Gov Cell (report) | O60: 05-06-2026 | R60: ADCRD-043
C61: Positive containers | D61: no. | E61: 0 | F61: 0 | H61: 13 | I61: =IF(AND(ISNUMBER(G61),ISNUMBER(H61)),H61-G61,"") | J61: =IF(AND(ISNUMBER(E61),E61>0,ISNUMBER(H61)),H61/E61,"") | K61: In Progress | L61: =IF(M61="Yes","🔴 BOTTOM",IF(M61="No","✓ Cleared",IF(Q61="MIN",IF(AND(ISNUMBER(F61),ISNUMBER(H61)),IF(H61<F61*'Master Dashboard'!$B$4,"🔴 LOW",""),""),IF(Q61="MAX",IF(AND(ISNUMBER(F61),ISNUMBER(H61)),IF(H61>F61,"🔴 HIGH",""),""),"")))) -> 🔴 HIGH | M61: Auto | N61: Gov Cell (report) | O61: 05-06-2026 | Q61: MAX | R61: ADCRD-044
C62: Breeding found in houses | D62: cases | E62: 0 | F62: 0 | H62: 11 | I62: =IF(AND(ISNUMBER(G62),ISNUMBER(H62)),H62-G62,"") | J62: =IF(AND(ISNUMBER(E62),E62>0,ISNUMBER(H62)),H62/E62,"") | K62: In Progress | L62: =IF(M62="Yes","🔴 BOTTOM",IF(M62="No","✓ Cleared",IF(Q62="MIN",IF(AND(ISNUMBER(F62),ISNUMBER(H62)),IF(H62<F62*'Master Dashboard'!$B$4,"🔴 LOW",""),""),IF(Q62="MAX",IF(AND(ISNUMBER(F62),ISNUMBER(H62)),IF(H62>F62,"🔴 HIGH",""),""),"")))) -> 🔴 HIGH | M62: Auto | N62: Gov Cell (report) | O62: 05-06-2026 | Q62: MAX | R62: ADCRD-045
C63: Challans issued (health) | D63: no. | H63: 15 | I63: =IF(AND(ISNUMBER(G63),ISNUMBER(H63)),H63-G63,"") | J63: =IF(AND(ISNUMBER(E63),E63>0,ISNUMBER(H63)),H63/E63,"") | K63: In Progress | L63: =IF(M63="Yes","🔴 BOTTOM",IF(M63="No","✓ Cleared",IF(Q63="MIN",IF(AND(ISNUMBER(F63),ISNUMBER(H63)),IF(H63<F63*'Master Dashboard'!$B$4,"🔴 LOW",""),""),IF(Q63="MAX",IF(AND(ISNUMBER(F63),ISNUMBER(H63)),IF(H63>F63,"🔴 HIGH",""),""),"")))) | M63: Auto | N63: Gov Cell (report) | O63: 05-06-2026 | R63: ADCRD-046
C64: Camps organised | D64: no. | H64: 206 | I64: =IF(AND(ISNUMBER(G64),ISNUMBER(H64)),H64-G64,"") | J64: =IF(AND(ISNUMBER(E64),E64>0,ISNUMBER(H64)),H64/E64,"") | K64: In Progress | L64: =IF(M64="Yes","🔴 BOTTOM",IF(M64="No","✓ Cleared",IF(Q64="MIN",IF(AND(ISNUMBER(F64),ISNUMBER(H64)),IF(H64<F64*'Master Dashboard'!$B$4,"🔴 LOW",""),""),IF(Q64="MAX",IF(AND(ISNUMBER(F64),ISNUMBER(H64)),IF(H64>F64,"🔴 HIGH",""),""),"")))) | M64: Auto | N64: Gov Cell (report) | O64: 05-06-2026 | R64: ADCRD-047
C65: Block: Raikot — houses visited | D65: houses | E65: 500 | F65: 200 | H65: 0 | I65: =IF(AND(ISNUMBER(G65),ISNUMBER(H65)),H65-G65,"") | J65: =IF(AND(ISNUMBER(E65),E65>0,ISNUMBER(H65)),H65/E65,"") -> 0 | K65: Pending/Blocked | L65: =IF(M65="Yes","🔴 BOTTOM",IF(M65="No","✓ Cleared",IF(Q65="MIN",IF(AND(ISNUMBER(F65),ISNUMBER(H65)),IF(H65<F65*'Master Dashboard'!$B$4,"🔴 LOW",""),""),IF(Q65="MAX",IF(AND(ISNUMBER(F65),ISNUMBER(H65)),IF(H65>F65,"🔴 HIGH",""),""),"")))) -> 🔴 LOW | M65: Auto | N65: Gov Cell (report) | O65: 05-06-2026 | P65: Zero activity — flag | Q65: MIN | R65: ADCRD-048
C66: Block: Khanna — houses visited | D66: houses | E66: 500 | F66: 200 | H66: 256 | I66: =IF(AND(ISNUMBER(G66),ISNUMBER(H66)),H66-G66,"") | J66: =IF(AND(ISNUMBER(E66),E66>0,ISNUMBER(H66)),H66/E66,"") -> 0.512 | K66: In Progress | L66: =IF(M66="Yes","🔴 BOTTOM",IF(M66="No","✓ Cleared",IF(Q66="MIN",IF(AND(ISNUMBER(F66),ISNUMBER(H66)),IF(H66<F66*'Master Dashboard'!$B$4,"🔴 LOW",""),""),IF(Q66="MAX",IF(AND(ISNUMBER(F66),ISNUMBER(H66)),IF(H66>F66,"🔴 HIGH",""),""),"")))) | M66: Auto | N66: Gov Cell (report) | O66: 05-06-2026 | Q66: MIN | R66: ADCRD-049
C67: Block: Dehlon — houses visited | D67: houses | E67: 500 | F67: 200 | H67: 314 | I67: =IF(AND(ISNUMBER(G67),ISNUMBER(H67)),H67-G67,"") | J67: =IF(AND(ISNUMBER(E67),E67>0,ISNUMBER(H67)),H67/E67,"") -> 0.628 | K67: In Progress | L67: =IF(M67="Yes","🔴 BOTTOM",IF(M67="No","✓ Cleared",IF(Q67="MIN",IF(AND(ISNUMBER(F67),ISNUMBER(H67)),IF(H67<F67*'Master Dashboard'!$B$4,"🔴 LOW",""),""),IF(Q67="MAX",IF(AND(ISNUMBER(F67),ISNUMBER(H67)),IF(H67>F67,"🔴 HIGH",""),""),"")))) | M67: Auto | N67: Gov Cell (report) | O67: 05-06-2026 | Q67: MIN | R67: ADCRD-050
C68: Medicine stock adequate? (Y/N) | D68: Y/N | I68: =IF(AND(ISNUMBER(G68),ISNUMBER(H68)),H68-G68,"") | J68: =IF(AND(ISNUMBER(E68),E68>0,ISNUMBER(H68)),H68/E68,"") | K68: On Track | L68: =IF(M68="Yes","🔴 BOTTOM",IF(M68="No","✓ Cleared",IF(Q68="MIN",IF(AND(ISNUMBER(F68),ISNUMBER(H68)),IF(H68<F68*'Master Dashboard'!$B$4,"🔴 LOW",""),""),IF(Q68="MAX",IF(AND(ISNUMBER(F68),ISNUMBER(H68)),IF(H68>F68,"🔴 HIGH",""),""),"")))) | M68: Auto | P68: SDP kit demand raised to Director MOHFW | R68: ADCRD-051
A69: 7 | B69: Parks, Playgrounds & Anganwadis | C69: Anganwadi Centres — completed | D69: centres | E69: 87 | F69: 87 | H69: 87 | I69: =IF(AND(ISNUMBER(G69),ISNUMBER(H69)),H69-G69,"") | J69: =IF(AND(ISNUMBER(E69),E69>0,ISNUMBER(H69)),H69/E69,"") -> 1 | K69: Completed | L69: =IF(M69="Yes","🔴 BOTTOM",IF(M69="No","✓ Cleared",IF(Q69="MIN",IF(AND(ISNUMBER(F69),ISNUMBER(H69)),IF(H69<F69*'Master Dashboard'!$B$4,"🔴 LOW",""),""),IF(Q69="MAX",IF(AND(ISNUMBER(F69),ISNUMBER(H69)),IF(H69>F69,"🔴 HIGH",""),""),"")))) | M69: Auto | N69: Gov Cell (report) | O69: 05-06-2026 | P69: 100% | Q69: MIN | R69: ADCRD-052
C70: Playgrounds Phase 2 — ready for inauguration | D70: grounds | H70: 12 | I70: =IF(AND(ISNUMBER(G70),ISNUMBER(H70)),H70-G70,"") | J70: =IF(AND(ISNUMBER(E70),E70>0,ISNUMBER(H70)),H70/E70,"") | K70: On Track | L70: =IF(M70="Yes","🔴 BOTTOM",IF(M70="No","✓ Cleared",IF(Q70="MIN",IF(AND(ISNUMBER(F70),ISNUMBER(H70)),IF(H70<F70*'Master Dashboard'!$B$4,"🔴 LOW",""),""),IF(Q70="MAX",IF(AND(ISNUMBER(F70),ISNUMBER(H70)),IF(H70>F70,"🔴 HIGH",""),""),"")))) | M70: Auto | N70: Gov Cell (report) | O70: 05-06-2026 | P70: Phase-1: 8 handed over 04.05 | R70: ADCRD-053
C71: Parks Phase 2 (of 100) initiated? (Y/N) | D71: Y/N | I71: =IF(AND(ISNUMBER(G71),ISNUMBER(H71)),H71-G71,"") | J71: =IF(AND(ISNUMBER(E71),E71>0,ISNUMBER(H71)),H71/E71,"") | K71: In Progress | L71: =IF(M71="Yes","🔴 BOTTOM",IF(M71="No","✓ Cleared",IF(Q71="MIN",IF(AND(ISNUMBER(F71),ISNUMBER(H71)),IF(H71<F71*'Master Dashboard'!$B$4,"🔴 LOW",""),""),IF(Q71="MAX",IF(AND(ISNUMBER(F71),ISNUMBER(H71)),IF(H71>F71,"🔴 HIGH",""),""),"")))) | M71: Auto | P71: JC Vineet Rs5 Cr proposal | R71: ADCRD-054
A72: 8 | B72: Socio-Economic Drug Census | C72: 📊 Survey completed (district) | H72: 72079 | P72: of 7,31,750 target (9.9%). Active supervisors 137; enumerators 998.
C73: Survey — completed (district) | D73: houses | E73: 731750 | F73: 73175 | H73: 72079 | I73: =IF(AND(ISNUMBER(G73),ISNUMBER(H73)),H73-G73,"") | J73: =IF(AND(ISNUMBER(E73),E73>0,ISNUMBER(H73)),H73/E73,"") -> 0.098502221 | K73: In Progress | L73: =IF(M73="Yes","🔴 BOTTOM",IF(M73="No","✓ Cleared",IF(Q73="MIN",IF(AND(ISNUMBER(F73),ISNUMBER(H73)),IF(H73<F73*'Master Dashboard'!$B$4,"🔴 LOW",""),""),IF(Q73="MAX",IF(AND(ISNUMBER(F73),ISNUMBER(H73)),IF(H73>F73,"🔴 HIGH",""),""),"")))) -> 🔴 LOW | M73: Auto | N73: Gov Cell (report) | O73: 05-06-2026 | P73: 9.9% | active supervisors 137; enumerators 998 | Q73: MIN | R73: ADCRD-057
C74: Survey completed — Jagraon | D74: houses | E74: 48500 | F74: 4850 | H74: 3417 | I74: =IF(AND(ISNUMBER(G74),ISNUMBER(H74)),H74-G74,"") | J74: =IF(AND(ISNUMBER(E74),E74>0,ISNUMBER(H74)),H74/E74,"") -> 0.070453608 | K74: In Progress | L74: =IF(M74="Yes","🔴 BOTTOM",IF(M74="No","✓ Cleared",IF(Q74="MIN",IF(AND(ISNUMBER(F74),ISNUMBER(H74)),IF(H74<F74*'Master Dashboard'!$B$4,"🔴 LOW",""),""),IF(Q74="MAX",IF(AND(ISNUMBER(F74),ISNUMBER(H74)),IF(H74>F74,"🔴 HIGH",""),""),"")))) -> 🔴 LOW | M74: Auto | N74: Gov Cell (report) | O74: 05-06-2026 | P74: 7.0% of 48,500 — Drug-census houses surveyed of this assembly's target. | Q74: MIN | R74: ADCRD-058
C75: Survey completed — Dakha | D75: houses | E75: 54250 | F75: 5425 | H75: 12345 | I75: =IF(AND(ISNUMBER(G75),ISNUMBER(H75)),H75-G75,"") | J75: =IF(AND(ISNUMBER(E75),E75>0,ISNUMBER(H75)),H75/E75,"") -> 0.2275576 | K75: In Progress | L75: =IF(M75="Yes","🔴 BOTTOM",IF(M75="No","✓ Cleared",IF(Q75="MIN",IF(AND(ISNUMBER(F75),ISNUMBER(H75)),IF(H75<F75*'Master Dashboard'!$B$4,"🔴 LOW",""),""),IF(Q75="MAX",IF(AND(ISNUMBER(F75),ISNUMBER(H75)),IF(H75>F75,"🔴 HIGH",""),""),"")))) | M75: Auto | N75: Gov Cell (report) | O75: 05-06-2026 | P75: 22.8% of 54,250 — Drug-census houses surveyed of this assembly's target. | Q75: MIN | R75: ADCRD-059
C76: Survey completed — Raikot | D76: houses | E76: 47000 | F76: 4700 | H76: 11686 | I76: =IF(AND(ISNUMBER(G76),ISNUMBER(H76)),H76-G76,"") | J76: =IF(AND(ISNUMBER(E76),E76>0,ISNUMBER(H76)),H76/E76,"") -> 0.2486383 | K76: In Progress | L76: =IF(M76="Yes","🔴 BOTTOM",IF(M76="No","✓ Cleared",IF(Q76="MIN",IF(AND(ISNUMBER(F76),ISNUMBER(H76)),IF(H76<F76*'Master Dashboard'!$B$4,"🔴 LOW",""),""),IF(Q76="MAX",IF(AND(ISNUMBER(F76),ISNUMBER(H76)),IF(H76>F76,"🔴 HIGH",""),""),"")))) | M76: Auto | N76: Gov Cell (report) | O76: 05-06-2026 | P76: 24.9% of 47,000 — Drug-census houses surveyed of this assembly's target. | Q76: MIN | R76: ADCRD-060
C77: Survey completed — Gill | D77: houses | E77: 74500 | F77: 7450 | H77: 13633 | I77: =IF(AND(ISNUMBER(G77),ISNUMBER(H77)),H77-G77,"") | J77: =IF(AND(ISNUMBER(E77),E77>0,ISNUMBER(H77)),H77/E77,"") -> 0.18299329 | K77: In Progress | L77: =IF(M77="Yes","🔴 BOTTOM",IF(M77="No","✓ Cleared",IF(Q77="MIN",IF(AND(ISNUMBER(F77),ISNUMBER(H77)),IF(H77<F77*'Master Dashboard'!$B$4,"🔴 LOW",""),""),IF(Q77="MAX",IF(AND(ISNUMBER(F77),ISNUMBER(H77)),IF(H77>F77,"🔴 HIGH",""),""),"")))) | M77: Auto | N77: Gov Cell (report) | O77: 05-06-2026 | P77: 18.3% of 74,500 — Drug-census houses surveyed of this assembly's target. | Q77: MIN | R77: ADCRD-061
C78: Survey completed — Ldh-East | D78: houses | E78: 55500 | F78: 5550 | H78: 708 | I78: =IF(AND(ISNUMBER(G78),ISNUMBER(H78)),H78-G78,"") | J78: =IF(AND(ISNUMBER(E78),E78>0,ISNUMBER(H78)),H78/E78,"") -> 0.012756757 | K78: In Progress | L78: =IF(M78="Yes","🔴 BOTTOM",IF(M78="No","✓ Cleared",IF(Q78="MIN",IF(AND(ISNUMBER(F78),ISNUMBER(H78)),IF(H78<F78*'Master Dashboard'!$B$4,"🔴 LOW",""),""),IF(Q78="MAX",IF(AND(ISNUMBER(F78),ISNUMBER(H78)),IF(H78>F78,"🔴 HIGH",""),""),"")))) -> 🔴 LOW | M78: Auto | N78: Gov Cell (report) | O78: 05-06-2026 | P78: 1.3% of 55,500 — Drug-census houses surveyed of this assembly's target. | Q78: MIN | R78: ADCRD-062
C79: Survey completed — Sahnewal | D79: houses | E79: 69750 | F79: 6975 | H79: 2425 | I79: =IF(AND(ISNUMBER(G79),ISNUMBER(H79)),H79-G79,"") | J79: =IF(AND(ISNUMBER(E79),E79>0,ISNUMBER(H79)),H79/E79,"") -> 0.034767025 | K79: In Progress | L79: =IF(M79="Yes","🔴 BOTTOM",IF(M79="No","✓ Cleared",IF(Q79="MIN",IF(AND(ISNUMBER(F79),ISNUMBER(H79)),IF(H79<F79*'Master Dashboard'!$B$4,"🔴 LOW",""),""),IF(Q79="MAX",IF(AND(ISNUMBER(F79),ISNUMBER(H79)),IF(H79>F79,"🔴 HIGH",""),""),"")))) -> 🔴 LOW | M79: Auto | N79: Gov Cell (report) | O79: 05-06-2026 | P79: 3.5% of 69,750 — Drug-census houses surveyed of this assembly's target. | Q79: MIN | R79: ADCRD-063
C80: Survey completed — Samrala | D80: houses | E80: 54500 | F80: 5450 | H80: 4706 | I80: =IF(AND(ISNUMBER(G80),ISNUMBER(H80)),H80-G80,"") | J80: =IF(AND(ISNUMBER(E80),E80>0,ISNUMBER(H80)),H80/E80,"") -> 0.086348624 | K80: In Progress | L80: =IF(M80="Yes","🔴 BOTTOM",IF(M80="No","✓ Cleared",IF(Q80="MIN",IF(AND(ISNUMBER(F80),ISNUMBER(H80)),IF(H80<F80*'Master Dashboard'!$B$4,"🔴 LOW",""),""),IF(Q80="MAX",IF(AND(ISNUMBER(F80),ISNUMBER(H80)),IF(H80>F80,"🔴 HIGH",""),""),"")))) -> 🔴 LOW | M80: Auto | N80: Gov Cell (report) | O80: 05-06-2026 | P80: 8.6% of 54,500 — Drug-census houses surveyed of this assembly's target. | Q80: MIN | R80: ADCRD-064
C81: Survey completed — Khanna | D81: houses | E81: 48000 | F81: 4800 | H81: 4405 | I81: =IF(AND(ISNUMBER(G81),ISNUMBER(H81)),H81-G81,"") | J81: =IF(AND(ISNUMBER(E81),E81>0,ISNUMBER(H81)),H81/E81,"") -> 0.091770833 | K81: In Progress | L81: =IF(M81="Yes","🔴 BOTTOM",IF(M81="No","✓ Cleared",IF(Q81="MIN",IF(AND(ISNUMBER(F81),ISNUMBER(H81)),IF(H81<F81*'Master Dashboard'!$B$4,"🔴 LOW",""),""),IF(Q81="MAX",IF(AND(ISNUMBER(F81),ISNUMBER(H81)),IF(H81>F81,"🔴 HIGH",""),""),"")))) -> 🔴 LOW | M81: Auto | N81: Gov Cell (report) | O81: 05-06-2026 | P81: 9.2% of 48,000 — Drug-census houses surveyed of this assembly's target. | Q81: MIN | R81: ADCRD-065
C82: Survey completed — Payal | D82: houses | E82: 51750 | F82: 5175 | H82: 13952 | I82: =IF(AND(ISNUMBER(G82),ISNUMBER(H82)),H82-G82,"") | J82: =IF(AND(ISNUMBER(E82),E82>0,ISNUMBER(H82)),H82/E82,"") -> 0.26960386 | K82: In Progress | L82: =IF(M82="Yes","🔴 BOTTOM",IF(M82="No","✓ Cleared",IF(Q82="MIN",IF(AND(ISNUMBER(F82),ISNUMBER(H82)),IF(H82<F82*'Master Dashboard'!$B$4,"🔴 LOW",""),""),IF(Q82="MAX",IF(AND(ISNUMBER(F82),ISNUMBER(H82)),IF(H82>F82,"🔴 HIGH",""),""),"")))) | M82: Auto | N82: Gov Cell (report) | O82: 05-06-2026 | P82: 27.0% of 51,750 — Drug-census houses surveyed of this assembly's target. | Q82: MIN | R82: ADCRD-066
C83: Survey completed — Ldh-South | D83: houses | E83: 43500 | F83: 4350 | H83: 199 | I83: =IF(AND(ISNUMBER(G83),ISNUMBER(H83)),H83-G83,"") | J83: =IF(AND(ISNUMBER(E83),E83>0,ISNUMBER(H83)),H83/E83,"") -> 0.0045747126 | K83: In Progress | L83: =IF(M83="Yes","🔴 BOTTOM",IF(M83="No","✓ Cleared",IF(Q83="MIN",IF(AND(ISNUMBER(F83),ISNUMBER(H83)),IF(H83<F83*'Master Dashboard'!$B$4,"🔴 LOW",""),""),IF(Q83="MAX",IF(AND(ISNUMBER(F83),ISNUMBER(H83)),IF(H83>F83,"🔴 HIGH",""),""),"")))) -> 🔴 LOW | M83: Auto | N83: Gov Cell (report) | O83: 05-06-2026 | P83: 0.5% of 43,500 — Drug-census houses surveyed of this assembly's target. | Q83: MIN | R83: ADCRD-067
C84: Survey completed — Ldh-Central | D84: houses | E84: 44500 | F84: 4450 | H84: 465 | I84: =IF(AND(ISNUMBER(G84),ISNUMBER(H84)),H84-G84,"") | J84: =IF(AND(ISNUMBER(E84),E84>0,ISNUMBER(H84)),H84/E84,"") -> 0.010449438 | K84: In Progress | L84: =IF(M84="Yes","🔴 BOTTOM",IF(M84="No","✓ Cleared",IF(Q84="MIN",IF(AND(ISNUMBER(F84),ISNUMBER(H84)),IF(H84<F84*'Master Dashboard'!$B$4,"🔴 LOW",""),""),IF(Q84="MAX",IF(AND(ISNUMBER(F84),ISNUMBER(H84)),IF(H84>F84,"🔴 HIGH",""),""),"")))) -> 🔴 LOW | M84: Auto | N84: Gov Cell (report) | O84: 05-06-2026 | P84: 1.0% of 44,500 — Drug-census houses surveyed of this assembly's target. | Q84: MIN | R84: ADCRD-068
... C87: Survey completed — Atam Nagar | D87: houses | E87: 41750 | F87: 4175 | H87: 3686 | I87: =IF(AND(ISNUMBER(G87),ISNUMBER(H87)),H87-G87,"") | J87: =IF(AND(ISNUMBER(E87),E87>0,ISNUMBER(H87)),H87/E87,"") -> 0.088287425 | K87: In Progress | L87: =IF(M87="Yes","🔴 BOTTOM",IF(M87="No","✓ Cleared",IF(Q87="MIN",IF(AND(ISNUMBER(F87),ISNUMBER(H87)),IF(H87<F87*'Master Dashboard'!$B$4,"🔴 LOW",""),""),IF(Q87="MAX",IF(AND(ISNUMBER(F87),ISNUMBER(H87)),IF(H87>F87,"🔴 HIGH",""),""),"")))) -> 🔴 LOW | M87: Auto | N87: Gov Cell (report) | O87: 05-06-2026 | P87: 8.8% of 41,750 — Drug-census houses surveyed of this assembly's target. | Q87: MIN | R87: ADCRD-071
A88: ▣ PRIORITY TASKS — qualitative / assigned tasks
A89: 9 | B89: Punjab Nirman | C89: Status update / UCs from BDPOs | D89: status | I89: =IF(AND(ISNUMBER(G89),ISNUMBER(H89)),H89-G89,"") | J89: =IF(AND(ISNUMBER(E89),E89>0,ISNUMBER(H89)),H89/E89,"") | K89: In Progress | L89: =IF(M89="Yes","🔴 BOTTOM",IF(M89="No","✓ Cleared",IF(Q89="MIN",IF(AND(ISNUMBER(F89),ISNUMBER(H89)),IF(H89<F89*'Master Dashboard'!$B$4,"🔴 LOW",""),""),IF(Q89="MAX",IF(AND(ISNUMBER(F89),ISNUMBER(H89)),IF(H89>F89,"🔴 HIGH",""),""),"")))) | M89: Auto | P89: Pending | R89: ADCRD-039
A90: 10 | B90: Dhanasu / Gow Shala | C90: Dhanasu — amount released (of Rs18L) | D90: Rs lakh | E90: 18 | F90: 18 | H90: 10 | I90: =IF(AND(ISNUMBER(G90),ISNUMBER(H90)),H90-G90,"") | J90: =IF(AND(ISNUMBER(E90),E90>0,ISNUMBER(H90)),H90/E90,"") -> 0.55555556 | K90: In Progress | L90: =IF(M90="Yes","🔴 BOTTOM",IF(M90="No","✓ Cleared",IF(Q90="MIN",IF(AND(ISNUMBER(F90),ISNUMBER(H90)),IF(H90<F90*'Master Dashboard'!$B$4,"🔴 LOW",""),""),IF(Q90="MAX",IF(AND(ISNUMBER(F90),ISNUMBER(H90)),IF(H90>F90,"🔴 HIGH",""),""),"")))) -> 🔴 LOW | M90: Auto | N90: Gov Cell (report) | O90: 05-06-2026 | P90: Rs2.74L sanctioned further | Q90: MIN | R90: ADCRD-055
C91: Gow Shala Mar-26 payment (Rs15.47L) released? (Y/N) | D91: Y/N | I91: =IF(AND(ISNUMBER(G91),ISNUMBER(H91)),H91-G91,"") | J91: =IF(AND(ISNUMBER(E91),E91>0,ISNUMBER(H91)),H91/E91,"") | K91: Pending/Blocked | L91: =IF(M91="Yes","🔴 BOTTOM",IF(M91="No","✓ Cleared",IF(Q91="MIN",IF(AND(ISNUMBER(F91),ISNUMBER(H91)),IF(H91<F91*'Master Dashboard'!$B$4,"🔴 LOW",""),""),IF(Q91="MAX",IF(AND(ISNUMBER(F91),ISNUMBER(H91)),IF(H91>F91,"🔴 HIGH",""),""),"")))) | M91: Auto | P91: To be released by MCL | R91: ADCRD-056

Sheet ADC (UD)
A1: ADC (UD) — Priority Agenda Review | DC Ludhiana (MASTER)
A2: Sr | B2: Priority Agenda | C2: KPI / Metric | D2: Concerned Officer / Unit | E2: Target / Total | F2: Flag Bar | G2: Last Value | H2: Current Value | I2: Change | J2: Achieved % | K2: Status | L2: Auto-Flag | M2: Bottom Performer | N2: Updated By | O2: Update Date | P2: Remarks / Context / Pending Action | Q2: Rule | R2: Key
A3: ▣ PRIORITY TASKS — qualitative / assigned tasks
A4: 1 | B4: MM Tirath Yatra Yojana | C4: Bills pending (count) | D4: bills | H4: 0 | I4: =IF(AND(ISNUMBER(G4),ISNUMBER(H4)),H4-G4,"") | J4: =IF(AND(ISNUMBER(E4),E4>0,ISNUMBER(H4)),H4/E4,"") | K4: In Progress | L4: =IF(M4="Yes","🔴 BOTTOM",IF(M4="No","✓ Cleared",IF(Q4="MIN",IF(AND(ISNUMBER(F4),ISNUMBER(H4)),IF(H4<F4*'Master Dashboard'!$B$4,"🔴 LOW",""),""),IF(Q4="MAX",IF(AND(ISNUMBER(F4),ISNUMBER(H4)),IF(H4>F4,"🔴 HIGH",""),""),"")))) | M4: Auto | N4: Gov Cell (report) | O4: 05-06-2026 | P4: Cleared till 04 May 2026; none pending | R4: ADCUD-001
C5: All bills up to date cleared? (Y/N) | D5: Y/N | I5: =IF(AND(ISNUMBER(G5),ISNUMBER(H5)),H5-G5,"") | J5: =IF(AND(ISNUMBER(E5),E5>0,ISNUMBER(H5)),H5/E5,"") | K5: In Progress | L5: =IF(M5="Yes","🔴 BOTTOM",IF(M5="No","✓ Cleared",IF(Q5="MIN",IF(AND(ISNUMBER(F5),ISNUMBER(H5)),IF(H5<F5*'Master Dashboard'!$B$4,"🔴 LOW",""),""),IF(Q5="MAX",IF(AND(ISNUMBER(F5),ISNUMBER(H5)),IF(H5>F5,"🔴 HIGH",""),""),"")))) | M5: Auto | R5: ADCUD-002
A6: 2 | B6: Buddha Dariya — NGT / Dairies / CBG | C6: Dairies identified (Rajpur/Haibowal) | D6: no. | H6: 6 | I6: =IF(AND(ISNUMBER(G6),ISNUMBER(H6)),H6-G6,"") | J6: =IF(AND(ISNUMBER(E6),E6>0,ISNUMBER(H6)),H6/E6,"") | K6: In Progress | M6: Auto | N6: Gov Cell (report) | O6: 05-06-2026 | P6: Disconnection done; MCL direction passed | R6: ADCUD-003
C7: Tajpur — dairies disconnected | D7: no. | E7: 21 | F7: 21 | H7: 16 | I7: =IF(AND(ISNUMBER(G7),ISNUMBER(H7)),H7-G7,"") | J7: =IF(AND(ISNUMBER(E7),E7>0,ISNUMBER(H7)),H7/E7,"") -> 0.76190476 | K7: In Progress | L7: =IF(M7="Yes","🔴 BOTTOM",IF(M7="No","✓ Cleared",IF(Q7="MIN",IF(AND(ISNUMBER(F7),ISNUMBER(H7)),IF(H7<F7*'Master Dashboard'!$B$4,"🔴 LOW",""),""),IF(Q7="MAX",IF(AND(ISNUMBER(F7),ISNUMBER(H7)),IF(H7>F7,"🔴 HIGH",""),""),"")))) -> 🔴 LOW | M7: Auto | N7: Gov Cell (report) | O7: 05-06-2026 | P7: 21 dairies out of complex | Q7: MIN | R7: ADCUD-004
C8: CBG plant — site identified? (Y/N) | D8: Y/N | I8: =IF(AND(ISNUMBER(G8),ISNUMBER(H8)),H8-G8,"") | J8: =IF(AND(ISNUMBER(E8),E8>0,ISNUMBER(H8)),H8/E8,"") | K8: Pending/Blocked | L8: =IF(M8="Yes","🔴 BOTTOM",IF(M8="No","✓ Cleared",IF(Q8="MIN",IF(AND(ISNUMBER(F8),ISNUMBER(H8)),IF(H8<F8*'Master Dashboard'!$B$4,"🔴 LOW",""),""),IF(Q8="MAX",IF(AND(ISNUMBER(F8),ISNUMBER(H8)),IF(H8>F8,"🔴 HIGH",""),""),"")))) | M8: Auto | P8: Jamalpur dump site found for carcass | R8: ADCUD-005
C9: CETP/STP — ATR report submitted? (Y/N) | D9: Y/N | I9: =IF(AND(ISNUMBER(G9),ISNUMBER(H9)),H9-G9,"") | J9: =IF(AND(ISNUMBER(E9),E9>0,ISNUMBER(H9)),H9/E9,"") | K9: In Progress | L9: =IF(M9="Yes","🔴 BOTTOM",IF(M9="No","✓ Cleared",IF(Q9="MIN",IF(AND(ISNUMBER(F9),ISNUMBER(H9)),IF(H9<F9*'Master Dashboard'!$B$4,"🔴 LOW",""),""),IF(Q9="MAX",IF(AND(ISNUMBER(F9),ISNUMBER(H9)),IF(H9>F9,"🔴 HIGH",""),""),"")))) | M9: Auto | P9: STP under construction at MC Raikot | R9: ADCUD-006
A10: 3 | B10: WTP — Water Treatment Plant | C10: WTPs with NO land available | D10: sites | E10: 0 | F10: 0 | H10: 3 | I10: =IF(AND(ISNUMBER(G10),ISNUMBER(H10)),H10-G10,"") | J10: =IF(AND(ISNUMBER(E10),E10>0,ISNUMBER(H10)),H10/E10,"") | K10: Pending/Blocked | L10: =IF(M10="Yes","🔴 BOTTOM",IF(M10="No","✓ Cleared",IF(Q10="MIN",IF(AND(ISNUMBER(F10),ISNUMBER(H10)),IF(H10<F10*'Master Dashboard'!$B$4,"🔴 LOW",""),""),IF(Q10="MAX",IF(AND(ISNUMBER(F10),ISNUMBER(H10)),IF(H10>F10,"🔴 HIGH",""),""),"")))) -> 🔴 HIGH | M10: Auto | N10: Gov Cell (report) | O10: 05-06-2026 | P10: MC Doraha, Maloud, Sahnewal | Q10: MAX | R10: ADCUD-007
C11: Mullanpur Dakha — completion status | D11: status | I11: =IF(AND(ISNUMBER(G11),ISNUMBER(H11)),H11-G11,"") | J11: =IF(AND(ISNUMBER(E11),E11>0,ISNUMBER(H11)),H11/E11,"") | K11: In Progress | L11: =IF(M11="Yes","🔴 BOTTOM",IF(M11="No","✓ Cleared",IF(Q11="MIN",IF(AND(ISNUMBER(F11),ISNUMBER(H11)),IF(H11<F11*'Master Dashboard'!$B$4,"🔴 LOW",""),""),IF(Q11="MAX",IF(AND(ISNUMBER(F11),ISNUMBER(H11)),IF(H11>F11,"🔴 HIGH",""),""),"")))) | M11: Auto | P11: Priority; Council land pending | R11: ADCUD-008
A12: 4 | B12: IT / MC Land Price Fixation | C12: Price Fixation Committee meeting held? (Y/N) | D12: Y/N | I12: =IF(AND(ISNUMBER(G12),ISNUMBER(H12)),H12-G12,"") | J12: =IF(AND(ISNUMBER(E12),E12>0,ISNUMBER(H12)),H12/E12,"") | K12: Pending/Blocked | L12: =IF(M12="Yes","🔴 BOTTOM",IF(M12="No","✓ Cleared",IF(Q12="MIN",IF(AND(ISNUMBER(F12),ISNUMBER(H12)),IF(H12<F12*'Master Dashboard'!$B$4,"🔴 LOW",""),""),IF(Q12="MAX",IF(AND(ISNUMBER(F12),ISNUMBER(H12)),IF(H12>F12,"🔴 HIGH",""),""),"")))) | M12: Auto | P12: IT case under process | R12: ADCUD-009

Sheet ADC (J)
A1: ADC (J) — Priority Agenda Review | DC Ludhiana (MASTER)
A2: Sr | B2: Priority Agenda | C2: KPI / Metric | D2: Concerned Officer / Unit | E2: Target / Total | F2: Flag Bar | G2: Last Value | H2: Current Value | I2: Change | J2: Achieved % | K2: Status | L2: Auto-Flag | M2: Bottom Performer | N2: Updated By | O2: Update Date | P2: Remarks / Context / Pending Action | Q2: Rule | R2: Key
A3: ▣ PRIORITY TASKS — qualitative / assigned tasks
A4: 1 | B4: YnV Bills | C4: Phase I bills — status | D4: bills | I4: =IF(AND(ISNUMBER(G4),ISNUMBER(H4)),H4-G4,"") | J4: =IF(AND(ISNUMBER(E4),E4>0,ISNUMBER(H4)),H4/E4,"") | K4: In Progress | L4: =IF(M4="Yes","🔴 BOTTOM",IF(M4="No","✓ Cleared",IF(Q4="MIN",IF(AND(ISNUMBER(F4),ISNUMBER(H4)),IF(H4<F4*'Master Dashboard'!$B$4,"🔴 LOW",""),""),IF(Q4="MAX",IF(AND(ISNUMBER(F4),ISNUMBER(H4)),IF(H4>F4,"🔴 HIGH",""),""),"")))) | M4: Auto | P4: Phase 1 complete; Phase 2 mtg 5/6 Jun | R4: ADCJ-001
C5: Phase III — E-rickshaws on road | D5: no. | E5: 4 | F5: 4 | H5: 4 | I5: =IF(AND(ISNUMBER(G5),ISNUMBER(H5)),H5-G5,"") | J5: =IF(AND(ISNUMBER(E5),E5>0,ISNUMBER(H5)),H5/E5,"") -> 1 | K5: In Progress | L5: =IF(M5="Yes","🔴 BOTTOM",IF(M5="No","✓ Cleared",IF(Q5="MIN",IF(AND(ISNUMBER(F5),ISNUMBER(H5)),IF(H5<F5*'Master Dashboard'!$B$4,"🔴 LOW",""),""),IF(Q5="MAX",IF(AND(ISNUMBER(F5),ISNUMBER(H5)),IF(H5>F5,"🔴 HIGH",""),""),"")))) | M5: Auto | N5: Gov Cell (report) | O5: 05-06-2026 | P5: Campaign started 8 May | Q5: MIN | R5: ADCJ-002
C6: SAARC Knit & PP bills mismatch — meeting held? (Y/N) | D6: Y/N | I6: =IF(AND(ISNUMBER(G6),ISNUMBER(H6)),H6-G6,"") | J6: =IF(AND(ISNUMBER(E6),E6>0,ISNUMBER(H6)),H6/E6,"") | K6: Pending/Blocked | L6: =IF(M6="Yes","🔴 BOTTOM",IF(M6="No","✓ Cleared",IF(Q6="MIN",IF(AND(ISNUMBER(F6),ISNUMBER(H6)),IF(H6<F6*'Master Dashboard'!$B$4,"🔴 LOW",""),""),IF(Q6="MAX",IF(AND(ISNUMBER(F6),ISNUMBER(H6)),IF(H6>F6,"🔴 HIGH",""),""),"")))) | M6: Auto | R6: ADCJ-003
A7: 2 | B7: Halwara Airport | C7: 📊 Infrastructure works completed | H7: 7 | P7: of 38 total; 31 ongoing. Operational target was 15 May; electricity damage noted.
C8: Infrastructure works — completed | D8: works | E8: 38 | F8: 38 | H8: 7 | I8: =IF(AND(ISNUMBER(G8),ISNUMBER(H8)),H8-G8,"") | J8: =IF(AND(ISNUMBER(E8),E8>0,ISNUMBER(H8)),H8/E8,"") -> 0.18421053 | K8: In Progress | L8: =IF(M8="Yes","🔴 BOTTOM",IF(M8="No","✓ Cleared",IF(Q8="MIN",IF(AND(ISNUMBER(F8),ISNUMBER(H8)),IF(H8<F8*'Master Dashboard'!$B$4,"🔴 LOW",""),""),IF(Q8="MAX",IF(AND(ISNUMBER(F8),ISNUMBER(H8)),IF(H8>F8,"🔴 HIGH",""),""),"")))) -> 🔴 LOW | M8: Auto | N8: Gov Cell (report) | O8: 05-06-2026 | P8: 31 ongoing; target 20 May | Q8: MIN | R8: ADCJ-004
C9: Security accommodation — done? (Y/N) | D9: Y/N | H9: Completed | I9: =IF(AND(ISNUMBER(G9),ISNUMBER(H9)),H9-G9,"") | J9: =IF(AND(ISNUMBER(E9),E9>0,ISNUMBER(H9)),H9/E9,"") | K9: Completed | L9: =IF(M9="Yes","🔴 BOTTOM",IF(M9="No","✓ Cleared",IF(Q9="MIN",IF(AND(ISNUMBER(F9),ISNUMBER(H9)),IF(H9<F9*'Master Dashboard'!$B$4,"🔴 LOW",""),""),IF(Q9="MAX",IF(AND(ISNUMBER(F9),ISNUMBER(H9)),IF(H9>F9,"🔴 HIGH",""),""),"")))) | M9: Auto | N9: Gov Cell (report) | O9: 05-06-2026 | P9: Training of personnel ongoing | R9: ADCJ-005
C10: LIAL — VC held? (Y/N) | D10: Y/N | I10: =IF(AND(ISNUMBER(G10),ISNUMBER(H10)),H10-G10,"") | J10: =IF(AND(ISNUMBER(E10),E10>0,ISNUMBER(H10)),H10/E10,"") | K10: Pending/Blocked | L10: =IF(M10="Yes","🔴 BOTTOM",IF(M10="No","✓ Cleared",IF(Q10="MIN",IF(AND(ISNUMBER(F10),ISNUMBER(H10)),IF(H10<F10*'Master Dashboard'!$B$4,"🔴 LOW",""),""),IF(Q10="MAX",IF(AND(ISNUMBER(F10),ISNUMBER(H10)),IF(H10>F10,"🔴 HIGH",""),""),"")))) | M10: Auto | R10: ADCJ-006
A11: 3 | B11: Flood Protection — Bet Area | C11: Bet area desilting — tenders failed | D11: no. | E11: 0 | F11: 0 | H11: 3 | I11: =IF(AND(ISNUMBER(G11),ISNUMBER(H11)),H11-G11,"") | J11: =IF(AND(ISNUMBER(E11),E11>0,ISNUMBER(H11)),H11/E11,"") | K11: Pending/Blocked | L11: =IF(M11="Yes","🔴 BOTTOM",IF(M11="No","✓ Cleared",IF(Q11="MIN",IF(AND(ISNUMBER(F11),ISNUMBER(H11)),IF(H11<F11*'Master Dashboard'!$B$4,"🔴 LOW",""),""),IF(Q11="MAX",IF(AND(ISNUMBER(F11),ISNUMBER(H11)),IF(H11>F11,"🔴 HIGH",""),""),"")))) -> 🔴 HIGH | M11: Auto | N11: Gov Cell (report) | O11: 05-06-2026 | P11: 8 kila; next date 22 May | Q11: MAX | R11: ADCJ-007
C12: Khaira Bet — forest objections | D12: no. | E12: 0 | F12: 0 | H12: 8 | I12: =IF(AND(ISNUMBER(G12),ISNUMBER(H12)),H12-G12,"") | J12: =IF(AND(ISNUMBER(E12),E12>0,ISNUMBER(H12)),H12/E12,"") | K12: Pending/Blocked | L12: =IF(M12="Yes","🔴 BOTTOM",IF(M12="No","✓ Cleared",IF(Q12="MIN",IF(AND(ISNUMBER(F12),ISNUMBER(H12)),IF(H12<F12*'Master Dashboard'!$B$4,"🔴 LOW",""),""),IF(Q12="MAX",IF(AND(ISNUMBER(F12),ISNUMBER(H12)),IF(H12>F12,"🔴 HIGH",""),""),"")))) -> 🔴 HIGH | M12: Auto | N12: Gov Cell (report) | O12: 05-06-2026 | P12: Forest land; meeting 4 Jun | Q12: MAX | R12: ADCJ-008
C13: DDMA flood equipment (Rs5L Red Cross) — tender floated? (Y/N) | D13: Y/N | I13: =IF(AND(ISNUMBER(G13),ISNUMBER(H13)),H13-G13,"") | J13: =IF(AND(ISNUMBER(E13),E13>0,ISNUMBER(H13)),H13/E13,"") | K13: In Progress | L13: =IF(M13="Yes","🔴 BOTTOM",IF(M13="No","✓ Cleared",IF(Q13="MIN",IF(AND(ISNUMBER(F13),ISNUMBER(H13)),IF(H13<F13*'Master Dashboard'!$B$4,"🔴 LOW",""),""),IF(Q13="MAX",IF(AND(ISNUMBER(F13),ISNUMBER(H13)),IF(H13>F13,"🔴 HIGH",""),""),"")))) | M13: Auto | P13: XEN Kamaljit specs; whole district | R13: ADCJ-009
A14: 4 | B14: Desilting — Khaira Bet Coordination | C14: Escalation to Central Govt / WRD — status | D14: status | I14: =IF(AND(ISNUMBER(G14),ISNUMBER(H14)),H14-G14,"") | J14: =IF(AND(ISNUMBER(E14),E14>0,ISNUMBER(H14)),H14/E14,"") | K14: Pending/Blocked | L14: =IF(M14="Yes","🔴 BOTTOM",IF(M14="No","✓ Cleared",IF(Q14="MIN",IF(AND(ISNUMBER(F14),ISNUMBER(H14)),IF(H14<F14*'Master Dashboard'!$B$4,"🔴 LOW",""),""),IF(Q14="MAX",IF(AND(ISNUMBER(F14),ISNUMBER(H14)),IF(H14>F14,"🔴 HIGH",""),""),"")))) | M14: Auto | P14: NGT next date pending | R14: ADCJ-010
A15: 5 | B15: SPCA | C15: CAPEX funds plan prepared? (Y/N) | D15: Y/N | I15: =IF(AND(ISNUMBER(G15),ISNUMBER(H15)),H15-G15,"") | J15: =IF(AND(ISNUMBER(E15),E15>0,ISNUMBER(H15)),H15/E15,"") | K15: Pending/Blocked | L15: =IF(M15="Yes","🔴 BOTTOM",IF(M15="No","✓ Cleared",IF(Q15="MIN",IF(AND(ISNUMBER(F15),ISNUMBER(H15)),IF(H15<F15*'Master Dashboard'!$B$4,"🔴 LOW",""),""),IF(Q15="MAX",IF(AND(ISNUMBER(F15),ISNUMBER(H15)),IF(H15>F15,"🔴 HIGH",""),""),"")))) | M15: Auto | P15: ADC Jagraon recommendation pending | R15: ADCJ-011
A16: 6 | B16: Raikot Master Plan | C16: Master Plan — status | D16: status | I16: =IF(AND(ISNUMBER(G16),ISNUMBER(H16)),H16-G16,"") | J16: =IF(AND(ISNUMBER(E16),E16>0,ISNUMBER(H16)),H16/E16,"") | K16: In Progress | L16: =IF(M16="Yes","🔴 BOTTOM",IF(M16="No","✓ Cleared",IF(Q16="MIN",IF(AND(ISNUMBER(F16),ISNUMBER(H16)),IF(H16<F16*'Master Dashboard'!$B$4,"🔴 LOW",""),""),IF(Q16="MAX",IF(AND(ISNUMBER(F16),ISNUMBER(H16)),IF(H16>F16,"🔴 HIGH",""),""),"")))) | M16: Auto | P16: Update pending | R16: ADCJ-012

Sheet ADC (K)
A1: ADC (K) — Priority Agenda Review | DC Ludhiana (MASTER)
A2: Sr | B2: Priority Agenda | C2: KPI / Metric | D2: Concerned Officer / Unit | E2: Target / Total | F2: Flag Bar | G2: Last Value | H2: Current Value | I2: Change | J2: Achieved % | K2: Status | L2: Auto-Flag | M2: Bottom Performer | N2: Updated By | O2: Update Date | P2: Remarks / Context / Pending Action | Q2: Rule | R2: Key
A3: ▣ PRIORITY TASKS — qualitative / assigned tasks
A4: 1 | B4: Court Cases & Legal Matters | C4: Hadon Bet (YnV) — CM Relief Fund status | D4: status | I4: =IF(AND(ISNUMBER(G4),ISNUMBER(H4)),H4-G4,"") | J4: =IF(AND(ISNUMBER(E4),E4>0,ISNUMBER(H4)),H4/E4,"") | K4: Pending/Blocked | L4: =IF(M4="Yes","🔴 BOTTOM",IF(M4="No","✓ Cleared",IF(Q4="MIN",IF(AND(ISNUMBER(F4),ISNUMBER(H4)),IF(H4<F4*'Master Dashboard'!$B$4,"🔴 LOW",""),""),IF(Q4="MAX",IF(AND(ISNUMBER(F4),ISNUMBER(H4)),IF(H4>F4,"🔴 HIGH",""),""),"")))) | M4: Auto | P4: Due 13 May — overdue | R4: ADCK-001
C5: No-representation defaults | D5: no. | E5: 0 | F5: 0 | I5: =IF(AND(ISNUMBER(G5),ISNUMBER(H5)),H5-G5,"") | J5: =IF(AND(ISNUMBER(E5),E5>0,ISNUMBER(H5)),H5/E5,"") | K5: In Progress | L5: =IF(M5="Yes","🔴 BOTTOM",IF(M5="No","✓ Cleared",IF(Q5="MIN",IF(AND(ISNUMBER(F5),ISNUMBER(H5)),IF(H5<F5*'Master Dashboard'!$B$4,"🔴 LOW",""),""),IF(Q5="MAX",IF(AND(ISNUMBER(F5),ISNUMBER(H5)),IF(H5>F5,"🔴 HIGH",""),""),"")))) | M5: Auto | P5: Zero tolerance | Q5: MAX | R5: ADCK-002
A6: 2 | B6: Flood Protection — Sasrali | C6: 📊 Sasrali geotubes installed | H6: 51 | P6: of 448 (35%). Work closed 23.05 by XEN Mining; Show-Cause issued. 12 tippers running.
C7: Sasrali geotubes installed | D7: tubes | E7: 448 | F7: 448 | H7: 51 | I7: =IF(AND(ISNUMBER(G7),ISNUMBER(H7)),H7-G7,"") | J7: =IF(AND(ISNUMBER(E7),E7>0,ISNUMBER(H7)),H7/E7,"") -> 0.11383929 | K7: Pending/Blocked | L7: =IF(M7="Yes","🔴 BOTTOM",IF(M7="No","✓ Cleared",IF(Q7="MIN",IF(AND(ISNUMBER(F7),ISNUMBER(H7)),IF(H7<F7*'Master Dashboard'!$B$4,"🔴 LOW",""),""),IF(Q7="MAX",IF(AND(ISNUMBER(F7),ISNUMBER(H7)),IF(H7>F7,"🔴 HIGH",""),""),"")))) -> 🔴 LOW | M7: Auto | N7: Gov Cell (report) | O7: 05-06-2026 | P7: 35% done; closed 23.05 by XEN Mining; SCN issued | Q7: MIN | R7: ADCK-003
A8: 3 | B8: Flood Protection — Dhulewal | C8: 📊 Dhulewal flood works completed | H8: 2 | P8: of 18 sanctioned; 16 halted (NREGA payment stopped). Rs 97.93L budget decision pending with DC.
C9: Dhulewal works completed | D9: works | E9: 18 | F9: 18 | H9: 2 | I9: =IF(AND(ISNUMBER(G9),ISNUMBER(H9)),H9-G9,"") | J9: =IF(AND(ISNUMBER(E9),E9>0,ISNUMBER(H9)),H9/E9,"") -> 0.11111111 | K9: Pending/Blocked | L9: =IF(M9="Yes","🔴 BOTTOM",IF(M9="No","✓ Cleared",IF(Q9="MIN",IF(AND(ISNUMBER(F9),ISNUMBER(H9)),IF(H9<F9*'Master Dashboard'!$B$4,"🔴 LOW",""),""),IF(Q9="MAX",IF(AND(ISNUMBER(F9),ISNUMBER(H9)),IF(H9>F9,"🔴 HIGH",""),""),"")))) -> 🔴 LOW | M9: Auto | N9: Gov Cell (report) | O9: 05-06-2026 | P9: 16 halted; Rs97.93L budget pending DC; SDRF/DMF decision | Q9: MIN | R9: ADCK-004
A10: 4 | B10: Desilting — Coordination | C10: Working desilting sites | D10: sites | E10: 1 | F10: 1 | H10: 0 | I10: =IF(AND(ISNUMBER(G10),ISNUMBER(H10)),H10-G10,"") | J10: =IF(AND(ISNUMBER(E10),E10>0,ISNUMBER(H10)),H10/E10,"") -> 0 | K10: Pending/Blocked | L10: =IF(M10="Yes","🔴 BOTTOM",IF(M10="No","✓ Cleared",IF(Q10="MIN",IF(AND(ISNUMBER(F10),ISNUMBER(H10)),IF(H10<F10*'Master Dashboard'!$B$4,"🔴 LOW",""),""),IF(Q10="MAX",IF(AND(ISNUMBER(F10),ISNUMBER(H10)),IF(H10>F10,"🔴 HIGH",""),""),"")))) -> 🔴 LOW | M10: Auto | N10: Gov Cell (report) | O10: 05-06-2026 | P10: Mandala (road denied) & Dopana (forest) — no site working | Q10: MIN | R10: ADCK-005
A11: 5 | B11: FCI Silage Works | C11: Ghudani Khurd — status | D11: status | I11: =IF(AND(ISNUMBER(G11),ISNUMBER(H11)),H11-G11,"") | J11: =IF(AND(ISNUMBER(E11),E11>0,ISNUMBER(H11)),H11/E11,"") | K11: In Progress | L11: =IF(M11="Yes","🔴 BOTTOM",IF(M11="No","✓ Cleared",IF(Q11="MIN",IF(AND(ISNUMBER(F11),ISNUMBER(H11)),IF(H11<F11*'Master Dashboard'!$B$4,"🔴 LOW",""),""),IF(Q11="MAX",IF(AND(ISNUMBER(F11),ISNUMBER(H11)),IF(H11>F11,"🔴 HIGH",""),""),"")))) | M11: Auto | P11: Panchayat not ready; ADC mtg 5 Jun | R11: ADCK-006
A12: 6 | B12: NHAI — Pkg 2 (Ldh-Ropar) | C12: Possession pending (km) | D12: km | E12: 0 | F12: 0 | H12: 5 | I12: =IF(AND(ISNUMBER(G12),ISNUMBER(H12)),H12-G12,"") | J12: =IF(AND(ISNUMBER(E12),E12>0,ISNUMBER(H12)),H12/E12,"") | K12: In Progress | L12: =IF(M12="Yes","🔴 BOTTOM",IF(M12="No","✓ Cleared",IF(Q12="MIN",IF(AND(ISNUMBER(F12),ISNUMBER(H12)),IF(H12<F12*'Master Dashboard'!$B$4,"🔴 LOW",""),""),IF(Q12="MAX",IF(AND(ISNUMBER(F12),ISNUMBER(H12)),IF(H12>F12,"🔴 HIGH",""),""),"")))) -> 🔴 HIGH | M12: Auto | N12: Gov Cell (report) | O12: 05-06-2026 | P12: 5.3 of 47.24 km; HC challenge | Q12: MAX | R12: ADCK-007
A13: 7 | B13: Rahon Road | C13: Road pending (mtrs) | D13: mtrs | E13: 0 | F13: 0 | H13: 3500 | I13: =IF(AND(ISNUMBER(G13),ISNUMBER(H13)),H13-G13,"") | J13: =IF(AND(ISNUMBER(E13),E13>0,ISNUMBER(H13)),H13/E13,"") | K13: In Progress | L13: =IF(M13="Yes","🔴 BOTTOM",IF(M13="No","✓ Cleared",IF(Q13="MIN",IF(AND(ISNUMBER(F13),ISNUMBER(H13)),IF(H13<F13*'Master Dashboard'!$B$4,"🔴 LOW",""),""),IF(Q13="MAX",IF(AND(ISNUMBER(F13),ISNUMBER(H13)),IF(H13>F13,"🔴 HIGH",""),""),"")))) -> 🔴 HIGH | M13: Auto | N13: Gov Cell (report) | O13: 05-06-2026 | P13: 3 km done; 4 underpasses done; sewerage work | Q13: MAX | R13: ADCK-008
A14: 8 | B14: SIR (ADC-K) | C14: SIR training — status | D14: status | I14: =IF(AND(ISNUMBER(G14),ISNUMBER(H14)),H14-G14,"") | J14: =IF(AND(ISNUMBER(E14),E14>0,ISNUMBER(H14)),H14/E14,"") | K14: In Progress | L14: =IF(M14="Yes","🔴 BOTTOM",IF(M14="No","✓ Cleared",IF(Q14="MIN",IF(AND(ISNUMBER(F14),ISNUMBER(H14)),IF(H14<F14*'Master Dashboard'!$B$4,"🔴 LOW",""),""),IF(Q14="MAX",IF(AND(ISNUMBER(F14),ISNUMBER(H14)),IF(H14>F14,"🔴 HIGH",""),""),"")))) | M14: Auto | P14: Master trainers geared up | R14: ADCK-009
A15: 9 | B15: Revenue Meeting | C15: Pending revenue actions | D15: status | I15: =IF(AND(ISNUMBER(G15),ISNUMBER(H15)),H15-G15,"") | J15: =IF(AND(ISNUMBER(E15),E15>0,ISNUMBER(H15)),H15/E15,"") | K15: In Progress | L15: =IF(M15="Yes","🔴 BOTTOM",IF(M15="No","✓ Cleared",IF(Q15="MIN",IF(AND(ISNUMBER(F15),ISNUMBER(H15)),IF(H15<F15*'Master Dashboard'!$B$4,"🔴 LOW",""),""),IF(Q15="MAX",IF(AND(ISNUMBER(F15),ISNUMBER(H15)),IF(H15>F15,"🔴 HIGH",""),""),"")))) | M15: Auto | P15: Court cases via Sukhpal Ji (ADC-G office) | R15: ADCK-010

Sheet CMFO
A1: CMFO — Priority Agenda Review | DC Ludhiana (MASTER)
A2: Sr | B2: Priority Agenda | C2: KPI / Metric | D2: Concerned Officer / Unit | E2: Target / Total | F2: Flag Bar | G2: Last Value | H2: Current Value | I2: Change | J2: Achieved % | K2: Status | L2: Auto-Flag | M2: Bottom Performer | N2: Updated By | O2: Update Date | P2: Remarks / Context / Pending Action | Q2: Rule | R2: Key
A3: ▣ SCHEMES — metric-based (fed from officer workbook)
A4: 1 | B4: eSewa Pendency & PGRS | C4: 📊 Ludhiana applications received (year) | H4: 721312 | P4: In process 39,539 | Pendency 5.48% of received. Figures below are 05 Jun (Last = 04 Jun).
C5: District — applications in process | D5: apps | E5: 0 | F5: 20000 | H5: 39539 | I5: =IF(AND(ISNUMBER(G5),ISNUMBER(H5)),H5-G5,"") | J5: =IF(AND(ISNUMBER(E5),E5>0,ISNUMBER(H5)),H5/E5,"") | K5: Pending/Blocked | L5: =IF(M5="Yes","🔴 BOTTOM",IF(M5="No","✓ Cleared",IF(Q5="MIN",IF(AND(ISNUMBER(F5),ISNUMBER(H5)),IF(H5<F5*'Master Dashboard'!$B$4,"🔴 LOW",""),""),IF(Q5="MAX",IF(AND(ISNUMBER(F5),ISNUMBER(H5)),IF(H5>F5,"🔴 HIGH",""),""),"")))) -> 🔴 HIGH | M5: Auto | N5: Gov Cell (report) | O5: 05-06-2026 | P5: Ludhiana total received 721,312; pendency 5.48% | Q5: MAX | R5: CMFO-006
C6: District — pendency % of received | D6: % | E6: 0.05 | F6: 0.05 | H6: 0.0548 | I6: =IF(AND(ISNUMBER(G6),ISNUMBER(H6)),H6-G6,"") | J6: =IF(AND(ISNUMBER(E6),E6>0,ISNUMBER(H6)),H6/E6,"") -> 1.096 | K6: Pending/Blocked | L6: =IF(M6="Yes","🔴 BOTTOM",IF(M6="No","✓ Cleared",IF(Q6="MIN",IF(AND(ISNUMBER(F6),ISNUMBER(H6)),IF(H6<F6*'Master Dashboard'!$B$4,"🔴 LOW",""),""),IF(Q6="MAX",IF(AND(ISNUMBER(F6),ISNUMBER(H6)),IF(H6>F6,"🔴 HIGH",""),""),"")))) -> 🔴 HIGH | M6: Auto | N6: Gov Cell (report) | O6: 05-06-2026 | P6: State comparison rank | Q6: MAX | R6: CMFO-007
C7: Pendency — Akash Garg, EOMC MC Ludhiana | D7: apps | F7: 1000 | G7: 7700 | H7: 7932 | I7: =IF(AND(ISNUMBER(G7),ISNUMBER(H7)),H7-G7,"") -> 232 | J7: =IF(AND(ISNUMBER(E7),E7>0,ISNUMBER(H7)),H7/E7,"") | K7: Pending/Blocked | L7: =IF(M7="Yes","🔴 BOTTOM",IF(M7="No","✓ Cleared",IF(Q7="MIN",IF(AND(ISNUMBER(F7),ISNUMBER(H7)),IF(H7<F7*'Master Dashboard'!$B$4,"🔴 LOW",""),""),IF(Q7="MAX",IF(AND(ISNUMBER(F7),ISNUMBER(H7)),IF(H7>F7,"🔴 HIGH",""),""),"")))) -> 🔴 HIGH | M7: Auto | N7: Gov Cell (report) | O7: 05-06-2026 | P7: 04 Jun: 7,700 — Applications pending disposal with this officer on the eSewa portal (Current = 05 Jun, Last = 04 Jun). | Q7: MAX | R7: CMFO-008
C8: Pendency — Beant Kaur, Clerk CMO | D8: apps | F8: 1000 | G8: 5892 | H8: 6634 | I8: =IF(AND(ISNUMBER(G8),ISNUMBER(H8)),H8-G8,"") -> 742 | J8: =IF(AND(ISNUMBER(E8),E8>0,ISNUMBER(H8)),H8/E8,"") | K8: Pending/Blocked | L8: =IF(M8="Yes","🔴 BOTTOM",IF(M8="No","✓ Cleared",IF(Q8="MIN",IF(AND(ISNUMBER(F8),ISNUMBER(H8)),IF(H8<F8*'Master Dashboard'!$B$4,"🔴 LOW",""),""),IF(Q8="MAX",IF(AND(ISNUMBER(F8),ISNUMBER(H8)),IF(H8>F8,"🔴 HIGH",""),""),"")))) -> 🔴 HIGH | M8: Auto | N8: Gov Cell (report) | O8: 05-06-2026 | P8: 04 Jun: 5,892 — Applications pending disposal with this officer on the eSewa portal (Current = 05 Jun, Last = 04 Jun). | Q8: MAX | R8: CMFO-009
C9: Pendency — Sukhvir Kaur, Clerk Ldh West | D9: apps | F9: 1000 | G9: 5747 | H9: 5579 | I9: =IF(AND(ISNUMBER(G9),ISNUMBER(H9)),H9-G9,"") -> -168 | J9: =IF(AND(ISNUMBER(E9),E9>0,ISNUMBER(H9)),H9/E9,"") | K9: Pending/Blocked | L9: =IF(M9="Yes","🔴 BOTTOM",IF(M9="No","✓ Cleared",IF(Q9="MIN",IF(AND(ISNUMBER(F9),ISNUMBER(H9)),IF(H9<F9*'Master Dashboard'!$B$4,"🔴 LOW",""),""),IF(Q9="MAX",IF(AND(ISNUMBER(F9),ISNUMBER(H9)),IF(H9>F9,"🔴 HIGH",""),""),"")))) -> 🔴 HIGH | M9: Auto | N9: Gov Cell (report) | O9: 05-06-2026 | P9: 04 Jun: 5,747 — Applications pending disposal with this officer on the eSewa portal (Current = 05 Jun, Last = 04 Jun). | Q9: MAX | R9: CMFO-010
C10: Pendency — Kuldeep Singh, Clerk Ldh East | D10: apps | F10: 1000 | G10: 5168 | H10: 5220 | I10: =IF(AND(ISNUMBER(G10),ISNUMBER(H10)),H10-G10,"") -> 52 | J10: =IF(AND(ISNUMBER(E10),E10>0,ISNUMBER(H10)),H10/E10,"") | K10: Pending/Blocked | L10: =IF(M10="Yes","🔴 BOTTOM",IF(M10="No","✓ Cleared",IF(Q10="MIN",IF(AND(ISNUMBER(F10),ISNUMBER(H10)),IF(H10<F10*'Master Dashboard'!$B$4,"🔴 LOW",""),""),IF(Q10="MAX",IF(AND(ISNUMBER(F10),ISNUMBER(H10)),IF(H10>F10,"🔴 HIGH",""),""),"")))) -> 🔴 HIGH | M10: Auto | N10: Gov Cell (report) | O10: 05-06-2026 | P10: 04 Jun: 5,168 — Applications pending disposal with this officer on the eSewa portal (Current = 05 Jun, Last = 04 Jun). | Q10: MAX | R10: CMFO-011
C11: Pendency — Harminder Singh, Tehsildar Ldh West | D11: apps | F11: 500 | G11: 2258 | H11: 2505 | I11: =IF(AND(ISNUMBER(G11),ISNUMBER(H11)),H11-G11,"") -> 247 | J11: =IF(AND(ISNUMBER(E11),E11>0,ISNUMBER(H11)),H11/E11,"") | K11: Pending/Blocked | L11: =IF(M11="Yes","🔴 BOTTOM",IF(M11="No","✓ Cleared",IF(Q11="MIN",IF(AND(ISNUMBER(F11),ISNUMBER(H11)),IF(H11<F11*'Master Dashboard'!$B$4,"🔴 LOW",""),""),IF(Q11="MAX",IF(AND(ISNUMBER(F11),ISNUMBER(H11)),IF(H11>F11,"🔴 HIGH",""),""),"")))) -> 🔴 HIGH | M11: Auto | N11: Gov Cell (report) | O11: 05-06-2026 | P11: 04 Jun: 2,258 — Applications pending disposal with this officer on the eSewa portal (Current = 05 Jun, Last = 04 Jun). | Q11: MAX | R11: CMFO-012
C12: Pendency — Ranjeet Singh, Tehsildar Ldh East | D12: apps | F12: 500 | G12: 542 | H12: 416 | I12: =IF(AND(ISNUMBER(G12),ISNUMBER(H12)),H12-G12,"") -> -126 | J12: =IF(AND(ISNUMBER(E12),E12>0,ISNUMBER(H12)),H12/E12,"") | K12: In Progress | L12: =IF(M12="Yes","🔴 BOTTOM",IF(M12="No","✓ Cleared",IF(Q12="MIN",IF(AND(ISNUMBER(F12),ISNUMBER(H12)),IF(H12<F12*'Master Dashboard'!$B$4,"🔴 LOW",""),""),IF(Q12="MAX",IF(AND(ISNUMBER(F12),ISNUMBER(H12)),IF(H12>F12,"🔴 HIGH",""),""),"")))) | M12: Auto | N12: Gov Cell (report) | O12: 05-06-2026 | P12: 04 Jun: 542 — Applications pending disposal with this officer on the eSewa portal (Current = 05 Jun, Last = 04 Jun). | Q12: MAX | R12: CMFO-013
C13: Pendency — Gurucharan Singh, Tehsildar Khanna | D13: apps | F13: 500 | G13: 260 | H13: 337 | I13: =IF(AND(ISNUMBER(G13),ISNUMBER(H13)),H13-G13,"") -> 77 | J13: =IF(AND(ISNUMBER(E13),E13>0,ISNUMBER(H13)),H13/E13,"") | K13: In Progress | L13: =IF(M13="Yes","🔴 BOTTOM",IF(M13="No","✓ Cleared",IF(Q13="MIN",IF(AND(ISNUMBER(F13),ISNUMBER(H13)),IF(H13<F13*'Master Dashboard'!$B$4,"🔴 LOW",""),""),IF(Q13="MAX",IF(AND(ISNUMBER(F13),ISNUMBER(H13)),IF(H13>F13,"🔴 HIGH",""),""),"")))) | M13: Auto | N13: Gov Cell (report) | O13: 05-06-2026 | P13: 04 Jun: 260 — Applications pending disposal with this officer on the eSewa portal (Current = 05 Jun, Last = 04 Jun). | Q13: MAX | R13: CMFO-014
C14: Approving authority — ADR Harpreet Singh (overall eSewa) | D14: apps | F14: 3000 | H14: 6674 | I14: =IF(AND(ISNUMBER(G14),ISNUMBER(H14)),H14-G14,"") | J14: =IF(AND(ISNUMBER(E14),E14>0,ISNUMBER(H14)),H14/E14,"") | K14: Pending/Blocked | L14: =IF(M14="Yes","🔴 BOTTOM",IF(M14="No","✓ Cleared",IF(Q14="MIN",IF(AND(ISNUMBER(F14),ISNUMBER(H14)),IF(H14<F14*'Master Dashboard'!$B$4,"🔴 LOW",""),""),IF(Q14="MAX",IF(AND(ISNUMBER(F14),ISNUMBER(H14)),IF(H14>F14,"🔴 HIGH",""),""),"")))) -> 🔴 HIGH | M14: Auto | N14: Gov Cell (report) | O14: 05-06-2026 | Q14: MAX | R14: CMFO-015
A15: 2 | B15: Human Rights Commission (HRC) | C15: 📊 Active HRC cases | H15: 13 | P15: Sent to Commission 3 | Report received (to put up) 2 | Direct reply 4 | Report pending from depts 3 | Transferred out 1.
C16: Total active cases | D16: cases | H16: 13 | I16: =IF(AND(ISNUMBER(G16),ISNUMBER(H16)),H16-G16,"") | J16: =IF(AND(ISNUMBER(E16),E16>0,ISNUMBER(H16)),H16/E16,"") | K16: In Progress | L16: =IF(M16="Yes","🔴 BOTTOM",IF(M16="No","✓ Cleared",IF(Q16="MIN",IF(AND(ISNUMBER(F16),ISNUMBER(H16)),IF(H16<F16*'Master Dashboard'!$B$4,"🔴 LOW",""),""),IF(Q16="MAX",IF(AND(ISNUMBER(F16),ISNUMBER(H16)),IF(H16>F16,"🔴 HIGH",""),""),"")))) | M16: Auto | N16: Gov Cell (report) | O16: 05-06-2026 | P16: 3 sent to Comm; 2 report recd; 4 direct reply; 3 dept pending; 1 transferred | R16: CMFO-016
C17: Reports pending from departments | D17: cases | E17: 0 | F17: 0 | H17: 3 | I17: =IF(AND(ISNUMBER(G17),ISNUMBER(H17)),H17-G17,"") | J17: =IF(AND(ISNUMBER(E17),E17>0,ISNUMBER(H17)),H17/E17,"") | K17: Pending/Blocked | L17: =IF(M17="Yes","🔴 BOTTOM",IF(M17="No","✓ Cleared",IF(Q17="MIN",IF(AND(ISNUMBER(F17),ISNUMBER(H17)),IF(H17<F17*'Master Dashboard'!$B$4,"🔴 LOW",""),""),IF(Q17="MAX",IF(AND(ISNUMBER(F17),ISNUMBER(H17)),IF(H17>F17,"🔴 HIGH",""),""),"")))) -> 🔴 HIGH | M17: Auto | N17: Gov Cell (report) | O17: 05-06-2026 | P17: See case rows below | Q17: MAX | R17: CMFO-017
C18: Case 204/10/2026 Umesh Narain | D18: case | H18: REPORT PENDING | I18: =IF(AND(ISNUMBER(G18),ISNUMBER(H18)),H18-G18,"") | J18: =IF(AND(ISNUMBER(E18),E18>0,ISNUMBER(H18)),H18/E18,"") | K18: Pending/Blocked | L18: =IF(M18="Yes","🔴 BOTTOM",IF(M18="No","✓ Cleared",IF(Q18="MIN",IF(AND(ISNUMBER(F18),ISNUMBER(H18)),IF(H18<F18*'Master Dashboard'!$B$4,"🔴 LOW",""),""),IF(Q18="MAX",IF(AND(ISNUMBER(F18),ISNUMBER(H18)),IF(H18>F18,"🔴 HIGH",""),""),"")))) | M18: Auto | N18: Gov Cell (report) | O18: 05-06-2026 | P18: Pending with PD NHAI; due 15.06.2026 | R18: CMFO-018
C19: Case 3846/10/2026 Grain Market | D19: case | H19: REPORT PENDING | I19: =IF(AND(ISNUMBER(G19),ISNUMBER(H19)),H19-G19,"") | J19: =IF(AND(ISNUMBER(E19),E19>0,ISNUMBER(H19)),H19/E19,"") | K19: Pending/Blocked | L19: =IF(M19="Yes","🔴 BOTTOM",IF(M19="No","✓ Cleared",IF(Q19="MIN",IF(AND(ISNUMBER(F19),ISNUMBER(H19)),IF(H19<F19*'Master Dashboard'!$B$4,"🔴 LOW",""),""),IF(Q19="MAX",IF(AND(ISNUMBER(F19),ISNUMBER(H19)),IF(H19>F19,"🔴 HIGH",""),""),"")))) | M19: Auto | N19: Gov Cell (report) | O19: 05-06-2026 | P19: Pending with CP Ludhiana + MCL; due 22.06.2026 | R19: CMFO-019
C20: Case 4832/10/2026 Baldev Singh | D20: case | H20: REPORT PENDING | I20: =IF(AND(ISNUMBER(G20),ISNUMBER(H20)),H20-G20,"") | J20: =IF(AND(ISNUMBER(E20),E20>0,ISNUMBER(H20)),H20/E20,"") | K20: Pending/Blocked | L20: =IF(M20="Yes","🔴 BOTTOM",IF(M20="No","✓ Cleared",IF(Q20="MIN",IF(AND(ISNUMBER(F20),ISNUMBER(H20)),IF(H20<F20*'Master Dashboard'!$B$4,"🔴 LOW",""),""),IF(Q20="MAX",IF(AND(ISNUMBER(F20),ISNUMBER(H20)),IF(H20>F20,"🔴 HIGH",""),""),"")))) | M20: Auto | N20: Gov Cell (report) | O20: 05-06-2026 | P20: Pending with SDM Samrala; due 26.06.2026 | R20: CMFO-020
C21: Case 5334/10/2024 Manjit Kaur | D21: case | H21: DIRECT REPLY | I21: =IF(AND(ISNUMBER(G21),ISNUMBER(H21)),H21-G21,"") | J21: =IF(AND(ISNUMBER(E21),E21>0,ISNUMBER(H21)),H21/E21,"") | K21: In Progress | L21: =IF(M21="Yes","🔴 BOTTOM",IF(M21="No","✓ Cleared",IF(Q21="MIN",IF(AND(ISNUMBER(F21),ISNUMBER(H21)),IF(H21<F21*'Master Dashboard'!$B$4,"🔴 LOW",""),""),IF(Q21="MAX",IF(AND(ISNUMBER(F21),ISNUMBER(H21)),IF(H21>F21,"🔴 HIGH",""),""),"")))) | M21: Auto | N21: Gov Cell (report) | O21: 05-06-2026 | P21: Pending with CP Ludhiana; due 26.06.2026 | R21: CMFO-021
C22: Case 2105/10/2026 Arvind | D22: case | H22: DIRECT REPLY | I22: =IF(AND(ISNUMBER(G22),ISNUMBER(H22)),H22-G22,"") | J22: =IF(AND(ISNUMBER(E22),E22>0,ISNUMBER(H22)),H22/E22,"") | K22: In Progress | L22: =IF(M22="Yes","🔴 BOTTOM",IF(M22="No","✓ Cleared",IF(Q22="MIN",IF(AND(ISNUMBER(F22),ISNUMBER(H22)),IF(H22<F22*'Master Dashboard'!$B$4,"🔴 LOW",""),""),IF(Q22="MAX",IF(AND(ISNUMBER(F22),ISNUMBER(H22)),IF(H22>F22,"🔴 HIGH",""),""),"")))) | M22: Auto | N22: Gov Cell (report) | O22: 05-06-2026 | P22: Pending with Civil Surgeon; due 03.06.2026 | R22: CMFO-022
C23: Case 276/1/2026 Umesh Narain | D23: case | H23: SENT TO COMM | I23: =IF(AND(ISNUMBER(G23),ISNUMBER(H23)),H23-G23,"") | J23: =IF(AND(ISNUMBER(E23),E23>0,ISNUMBER(H23)),H23/E23,"") | K23: In Progress | L23: =IF(M23="Yes","🔴 BOTTOM",IF(M23="No","✓ Cleared",IF(Q23="MIN",IF(AND(ISNUMBER(F23),ISNUMBER(H23)),IF(H23<F23*'Master Dashboard'!$B$4,"🔴 LOW",""),""),IF(Q23="MAX",IF(AND(ISNUMBER(F23),ISNUMBER(H23)),IF(H23>F23,"🔴 HIGH",""),""),"")))) | M23: Auto | N23: Gov Cell (report) | O23: 05-06-2026 | P23: Pending with SDM East (sent to Comm); due 12.06.2026 | R23: CMFO-023
A24: 3 | B24: NRI Commission | C24: 📊 Active NRI cases | H24: 7 | P24: ATR overdue: 1 (Case 5457/2025, pending SDM Ludhiana West).
C25: Total active NRI cases | D25: cases | H25: 7 | I25: =IF(AND(ISNUMBER(G25),ISNUMBER(H25)),H25-G25,"") | J25: =IF(AND(ISNUMBER(E25),E25>0,ISNUMBER(H25)),H25/E25,"") | K25: In Progress | L25: =IF(M25="Yes","🔴 BOTTOM",IF(M25="No","✓ Cleared",IF(Q25="MIN",IF(AND(ISNUMBER(F25),ISNUMBER(H25)),IF(H25<F25*'Master Dashboard'!$B$4,"🔴 LOW",""),""),IF(Q25="MAX",IF(AND(ISNUMBER(F25),ISNUMBER(H25)),IF(H25>F25,"🔴 HIGH",""),""),"")))) | M25: Auto | N25: Gov Cell (report) | O25: 05-06-2026 | R25: CMFO-024
C26: Case 5457/2025 Gurcharan Singh | D26: case | H26: ATR OVERDUE | I26: =IF(AND(ISNUMBER(G26),ISNUMBER(H26)),H26-G26,"") | J26: =IF(AND(ISNUMBER(E26),E26>0,ISNUMBER(H26)),H26/E26,"") | K26: Pending/Blocked | L26: =IF(M26="Yes","🔴 BOTTOM",IF(M26="No","✓ Cleared",IF(Q26="MIN",IF(AND(ISNUMBER(F26),ISNUMBER(H26)),IF(H26<F26*'Master Dashboard'!$B$4,"🔴 LOW",""),""),IF(Q26="MAX",IF(AND(ISNUMBER(F26),ISNUMBER(H26)),IF(H26>F26,"🔴 HIGH",""),""),"")))) | M26: Auto | N26: Gov Cell (report) | O26: 05-06-2026 | P26: Pending with SDM Ludhiana West; next 26.05.2026 | R26: CMFO-025
C27: Case 4111/2022 Jaspal Singh | D27: case | H27: Final disposal outstanding | I27: =IF(AND(ISNUMBER(G27),ISNUMBER(H27)),H27-G27,"") | J27: =IF(AND(ISNUMBER(E27),E27>0,ISNUMBER(H27)),H27/E27,"") | K27: Pending/Blocked | L27: =IF(M27="Yes","🔴 BOTTOM",IF(M27="No","✓ Cleared",IF(Q27="MIN",IF(AND(ISNUMBER(F27),ISNUMBER(H27)),IF(H27<F27*'Master Dashboard'!$B$4,"🔴 LOW",""),""),IF(Q27="MAX",IF(AND(ISNUMBER(F27),ISNUMBER(H27)),IF(H27>F27,"🔴 HIGH",""),""),"")))) | M27: Auto | N27: Gov Cell (report) | O27: 05-06-2026 | P27: Pending with SDM Jagraon; next 24.09.2026 | R27: CMFO-026
C28: Case 2803/2017 Manjeet Singh | D28: case | H28: Reminder issued 18.05 | I28: =IF(AND(ISNUMBER(G28),ISNUMBER(H28)),H28-G28,"") | J28: =IF(AND(ISNUMBER(E28),E28>0,ISNUMBER(H28)),H28/E28,"") | K28: In Progress | L28: =IF(M28="Yes","🔴 BOTTOM",IF(M28="No","✓ Cleared",IF(Q28="MIN",IF(AND(ISNUMBER(F28),ISNUMBER(H28)),IF(H28<F28*'Master Dashboard'!$B$4,"🔴 LOW",""),""),IF(Q28="MAX",IF(AND(ISNUMBER(F28),ISNUMBER(H28)),IF(H28>F28,"🔴 HIGH",""),""),"")))) | M28: Auto | N28: Gov Cell (report) | O28: 05-06-2026 | P28: Pending with SK Branch DC Office; next 22.05.2026 | R28: CMFO-027
C29: Case 5311/2024 Rajinder Kaur | D29: case | H29: Letter to SDM Raikot | I29: =IF(AND(ISNUMBER(G29),ISNUMBER(H29)),H29-G29,"") | J29: =IF(AND(ISNUMBER(E29),E29>0,ISNUMBER(H29)),H29/E29,"") | K29: In Progress | L29: =IF(M29="Yes","🔴 BOTTOM",IF(M29="No","✓ Cleared",IF(Q29="MIN",IF(AND(ISNUMBER(F29),ISNUMBER(H29)),IF(H29<F29*'Master Dashboard'!$B$4,"🔴 LOW",""),""),IF(Q29="MAX",IF(AND(ISNUMBER(F29),ISNUMBER(H29)),IF(H29>F29,"🔴 HIGH",""),""),"")))) | M29: Auto | N29: Gov Cell (report) | O29: 05-06-2026 | P29: Pending with PSC NRI Chandigarh; next 10.07.2026 | R29: CMFO-028
C30: Case 3542687 Davinder Grewal | D30: case | H30: Letter to SDM East | I30: =IF(AND(ISNUMBER(G30),ISNUMBER(H30)),H30-G30,"") | J30: =IF(AND(ISNUMBER(E30),E30>0,ISNUMBER(H30)),H30/E30,"") | K30: In Progress | L30: =IF(M30="Yes","🔴 BOTTOM",IF(M30="No","✓ Cleared",IF(Q30="MIN",IF(AND(ISNUMBER(F30),ISNUMBER(H30)),IF(H30<F30*'Master Dashboard'!$B$4,"🔴 LOW",""),""),IF(Q30="MAX",IF(AND(ISNUMBER(F30),ISNUMBER(H30)),IF(H30>F30,"🔴 HIGH",""),""),"")))) | M30: Auto | N30: Gov Cell (report) | O30: 05-06-2026 | P30: Pending with Commissioner of Police; next 13.05.2026 | R30: CMFO-029
C31: Case E540370 Naginder Kaur | D31: case | H31: Letter to SDM East | I31: =IF(AND(ISNUMBER(G31),ISNUMBER(H31)),H31-G31,"") | J31: =IF(AND(ISNUMBER(E31),E31>0,ISNUMBER(H31)),H31/E31,"") | K31: In Progress | L31: =IF(M31="Yes","🔴 BOTTOM",IF(M31="No","✓ Cleared",IF(Q31="MIN",IF(AND(ISNUMBER(F31),ISNUMBER(H31)),IF(H31<F31*'Master Dashboard'!$B$4,"🔴 LOW",""),""),IF(Q31="MAX",IF(AND(ISNUMBER(F31),ISNUMBER(H31)),IF(H31>F31,"🔴 HIGH",""),""),"")))) | M31: Auto | N31: Gov Cell (report) | O31: 05-06-2026 | P31: Pending with PSC NRI Chandigarh; next 07.05.2024 | R31: CMFO-030
A32: 4 | B32: Caste Certificate eSewa Pendency | C32: 📊 Total caste-certificate pendency | H32: 20093 | P32: SC 15,847 | OBC/BC 4,050 | General 196. Pending on eSewa with revenue authorities.
C33: Total caste cert pendency | D33: apps | E33: 0 | F33: 5000 | H33: 20093 | I33: =IF(AND(ISNUMBER(G33),ISNUMBER(H33)),H33-G33,"") | J33: =IF(AND(ISNUMBER(E33),E33>0,ISNUMBER(H33)),H33/E33,"") | K33: Pending/Blocked | L33: =IF(M33="Yes","🔴 BOTTOM",IF(M33="No","✓ Cleared",IF(Q33="MIN",IF(AND(ISNUMBER(F33),ISNUMBER(H33)),IF(H33<F33*'Master Dashboard'!$B$4,"🔴 LOW",""),""),IF(Q33="MAX",IF(AND(ISNUMBER(F33),ISNUMBER(H33)),IF(H33>F33,"🔴 HIGH",""),""),"")))) -> 🔴 HIGH | M33: Auto | N33: Gov Cell (report) | O33: 05-06-2026 | P33: SC 15847 + OBC/BC 4050 + General 196 | Q33: MAX | R33: CMFO-031
C34: SC certificates pending | D34: apps | E34: 0 | F34: 3000 | H34: 15847 | I34: =IF(AND(ISNUMBER(G34),ISNUMBER(H34)),H34-G34,"") | J34: =IF(AND(ISNUMBER(E34),E34>0,ISNUMBER(H34)),H34/E34,"") | K34: Pending/Blocked | L34: =IF(M34="Yes","🔴 BOTTOM",IF(M34="No","✓ Cleared",IF(Q34="MIN",IF(AND(ISNUMBER(F34),ISNUMBER(H34)),IF(H34<F34*'Master Dashboard'!$B$4,"🔴 LOW",""),""),IF(Q34="MAX",IF(AND(ISNUMBER(F34),ISNUMBER(H34)),IF(H34>F34,"🔴 HIGH",""),""),"")))) -> 🔴 HIGH | M34: Auto | N34: Gov Cell (report) | O34: 05-06-2026 | P34: Caste-certificate applications pending on eSewa. | Q34: MAX | R34: CMFO-032
C35: OBC/BC certificates pending | D35: apps | E35: 0 | F35: 1000 | H35: 4050 | I35: =IF(AND(ISNUMBER(G35),ISNUMBER(H35)),H35-G35,"") | J35: =IF(AND(ISNUMBER(E35),E35>0,ISNUMBER(H35)),H35/E35,"") | K35: Pending/Blocked | L35: =IF(M35="Yes","🔴 BOTTOM",IF(M35="No","✓ Cleared",IF(Q35="MIN",IF(AND(ISNUMBER(F35),ISNUMBER(H35)),IF(H35<F35*'Master Dashboard'!$B$4,"🔴 LOW",""),""),IF(Q35="MAX",IF(AND(ISNUMBER(F35),ISNUMBER(H35)),IF(H35>F35,"🔴 HIGH",""),""),"")))) -> 🔴 HIGH | M35: Auto | N35: Gov Cell (report) | O35: 05-06-2026 | P35: Caste-certificate applications pending on eSewa. | Q35: MAX | R35: CMFO-033
C36: Pending — Tehsildar Ldh West (SC) | D36: apps | E36: 0 | F36: 1000 | H36: 6519 | I36: =IF(AND(ISNUMBER(G36),ISNUMBER(H36)),H36-G36,"") | J36: =IF(AND(ISNUMBER(E36),E36>0,ISNUMBER(H36)),H36/E36,"") | K36: Pending/Blocked | L36: =IF(M36="Yes","🔴 BOTTOM",IF(M36="No","✓ Cleared",IF(Q36="MIN",IF(AND(ISNUMBER(F36),ISNUMBER(H36)),IF(H36<F36*'Master Dashboard'!$B$4,"🔴 LOW",""),""),IF(Q36="MAX",IF(AND(ISNUMBER(F36),ISNUMBER(H36)),IF(H36>F36,"🔴 HIGH",""),""),"")))) -> 🔴 HIGH | M36: Auto | N36: Gov Cell (report) | O36: 05-06-2026 | P36: Caste-certificate applications pending with this authority on eSewa. | Q36: MAX | R36: CMFO-034
C37: Pending — Tehsildar Ldh East (SC) | D37: apps | E37: 0 | F37: 1000 | H37: 4684 | I37: =IF(AND(ISNUMBER(G37),ISNUMBER(H37)),H37-G37,"") | J37: =IF(AND(ISNUMBER(E37),E37>0,ISNUMBER(H37)),H37/E37,"") | K37: Pending/Blocked | L37: =IF(M37="Yes","🔴 BOTTOM",IF(M37="No","✓ Cleared",IF(Q37="MIN",IF(AND(ISNUMBER(F37),ISNUMBER(H37)),IF(H37<F37*'Master Dashboard'!$B$4,"🔴 LOW",""),""),IF(Q37="MAX",IF(AND(ISNUMBER(F37),ISNUMBER(H37)),IF(H37>F37,"🔴 HIGH",""),""),"")))) -> 🔴 HIGH | M37: Auto | N37: Gov Cell (report) | O37: 05-06-2026 | P37: Caste-certificate applications pending with this authority on eSewa. | Q37: MAX | R37: CMFO-035
C38: Pending — Tehsildar Khanna (SC) | D38: apps | E38: 0 | F38: 1000 | H38: 1507 | I38: =IF(AND(ISNUMBER(G38),ISNUMBER(H38)),H38-G38,"") | J38: =IF(AND(ISNUMBER(E38),E38>0,ISNUMBER(H38)),H38/E38,"") | K38: Pending/Blocked | L38: =IF(M38="Yes","🔴 BOTTOM",IF(M38="No","✓ Cleared",IF(Q38="MIN",IF(AND(ISNUMBER(F38),ISNUMBER(H38)),IF(H38<F38*'Master Dashboard'!$B$4,"🔴 LOW",""),""),IF(Q38="MAX",IF(AND(ISNUMBER(F38),ISNUMBER(H38)),IF(H38>F38,"🔴 HIGH",""),""),"")))) -> 🔴 HIGH | M38: Auto | N38: Gov Cell (report) | O38: 05-06-2026 | P38: Caste-certificate applications pending with this authority on eSewa. | Q38: MAX | R38: CMFO-036
C39: Pending — Tehsildar Ldh East (OBC/BC) | D39: apps | E39: 0 | F39: 1000 | H39: 1670 | I39: =IF(AND(ISNUMBER(G39),ISNUMBER(H39)),H39-G39,"") | J39: =IF(AND(ISNUMBER(E39),E39>0,ISNUMBER(H39)),H39/E39,"") | K39: Pending/Blocked | L39: =IF(M39="Yes","🔴 BOTTOM",IF(M39="No","✓ Cleared",IF(Q39="MIN",IF(AND(ISNUMBER(F39),ISNUMBER(H39)),IF(H39<F39*'Master Dashboard'!$B$4,"🔴 LOW",""),""),IF(Q39="MAX",IF(AND(ISNUMBER(F39),ISNUMBER(H39)),IF(H39>F39,"🔴 HIGH",""),""),"")))) -> 🔴 HIGH | M39: Auto | N39: Gov Cell (report) | O39: 05-06-2026 | P39: Caste-certificate applications pending with this authority on eSewa. | Q39: MAX | R39: CMFO-037
C40: Pending — NT Ldh West (OBC/BC) | D40: apps | E40: 0 | F40: 1000 | H40: 1335 | I40: =IF(AND(ISNUMBER(G40),ISNUMBER(H40)),H40-G40,"") | J40: =IF(AND(ISNUMBER(E40),E40>0,ISNUMBER(H40)),H40/E40,"") | K40: Pending/Blocked | L40: =IF(M40="Yes","🔴 BOTTOM",IF(M40="No","✓ Cleared",IF(Q40="MIN",IF(AND(ISNUMBER(F40),ISNUMBER(H40)),IF(H40<F40*'Master Dashboard'!$B$4,"🔴 LOW",""),""),IF(Q40="MAX",IF(AND(ISNUMBER(F40),ISNUMBER(H40)),IF(H40>F40,"🔴 HIGH",""),""),"")))) -> 🔴 HIGH | M40: Auto | N40: Gov Cell (report) | O40: 05-06-2026 | P40: Caste-certificate applications pending with this authority on eSewa. | Q40: MAX | R40: CMFO-038
A41: ▣ PRIORITY TASKS — qualitative / assigned tasks
A42: 5 | B42: Southern Bypass — Land Acquisition & Payment | C42: Award revised Rs75Cr->Rs70Cr documented? (Y/N) | D42: Y/N | I42: =IF(AND(ISNUMBER(G42),ISNUMBER(H42)),H42-G42,"") | J42: =IF(AND(ISNUMBER(E42),E42>0,ISNUMBER(H42)),H42/E42,"") | K42: In Progress | L42: =IF(M42="Yes","🔴 BOTTOM",IF(M42="No","✓ Cleared",IF(Q42="MIN",IF(AND(ISNUMBER(F42),ISNUMBER(H42)),IF(H42<F42*'Master Dashboard'!$B$4,"🔴 LOW",""),""),IF(Q42="MAX",IF(AND(ISNUMBER(F42),ISNUMBER(H42)),IF(H42>F42,"🔴 HIGH",""),""),"")))) | M42: Auto | P42: From 11 May | R42: CMFO-001
C43: Villages — possession pending | D43: villages | E43: 0 | F43: 0 | H43: 16 | I43: =IF(AND(ISNUMBER(G43),ISNUMBER(H43)),H43-G43,"") | J43: =IF(AND(ISNUMBER(E43),E43>0,ISNUMBER(H43)),H43/E43,"") | K43: Pending/Blocked | L43: =IF(M43="Yes","🔴 BOTTOM",IF(M43="No","✓ Cleared",IF(Q43="MIN",IF(AND(ISNUMBER(F43),ISNUMBER(H43)),IF(H43<F43*'Master Dashboard'!$B$4,"🔴 LOW",""),""),IF(Q43="MAX",IF(AND(ISNUMBER(F43),ISNUMBER(H43)),IF(H43>F43,"🔴 HIGH",""),""),"")))) -> 🔴 HIGH | M43: Auto | N43: Gov Cell (report) | O43: 05-06-2026 | P43: All 16 villages | Q43: MAX | R43: CMFO-002
C44: 3.6 km disbursement | D44: status | I44: =IF(AND(ISNUMBER(G44),ISNUMBER(H44)),H44-G44,"") | J44: =IF(AND(ISNUMBER(E44),E44>0,ISNUMBER(H44)),H44/E44,"") | K44: Pending/Blocked | L44: =IF(M44="Yes","🔴 BOTTOM",IF(M44="No","✓ Cleared",IF(Q44="MIN",IF(AND(ISNUMBER(F44),ISNUMBER(H44)),IF(H44<F44*'Master Dashboard'!$B$4,"🔴 LOW",""),""),IF(Q44="MAX",IF(AND(ISNUMBER(F44),ISNUMBER(H44)),IF(H44>F44,"🔴 HIGH",""),""),"")))) | M44: Auto | P44: PENDING | R44: CMFO-003
A45: 6 | B45: Ludhiana–Ropar Package I & II | C45: Package I — amount pending (Rs Cr) | D45: Rs Cr | E45: 0 | F45: 0 | H45: 28 | I45: =IF(AND(ISNUMBER(G45),ISNUMBER(H45)),H45-G45,"") | J45: =IF(AND(ISNUMBER(E45),E45>0,ISNUMBER(H45)),H45/E45,"") | K45: Pending/Blocked | L45: =IF(M45="Yes","🔴 BOTTOM",IF(M45="No","✓ Cleared",IF(Q45="MIN",IF(AND(ISNUMBER(F45),ISNUMBER(H45)),IF(H45<F45*'Master Dashboard'!$B$4,"🔴 LOW",""),""),IF(Q45="MAX",IF(AND(ISNUMBER(F45),ISNUMBER(H45)),IF(H45>F45,"🔴 HIGH",""),""),"")))) -> 🔴 HIGH | M45: Auto | N45: Gov Cell (report) | O45: 05-06-2026 | P45: Talwandi Kalan; 3G-1 segment | Q45: MAX | R45: CMFO-004
C46: Package II — possession pending (km) | D46: km | E46: 0 | F46: 0 | H46: 5 | I46: =IF(AND(ISNUMBER(G46),ISNUMBER(H46)),H46-G46,"") | J46: =IF(AND(ISNUMBER(E46),E46>0,ISNUMBER(H46)),H46/E46,"") | K46: Pending/Blocked | L46: =IF(M46="Yes","🔴 BOTTOM",IF(M46="No","✓ Cleared",IF(Q46="MIN",IF(AND(ISNUMBER(F46),ISNUMBER(H46)),IF(H46<F46*'Master Dashboard'!$B$4,"🔴 LOW",""),""),IF(Q46="MAX",IF(AND(ISNUMBER(F46),ISNUMBER(H46)),IF(H46>F46,"🔴 HIGH",""),""),"")))) -> 🔴 HIGH | M46: Auto | N46: Gov Cell (report) | O46: 05-06-2026 | P46: 5.315 km; arbitration; PD reply overdue | Q46: MAX | R46: CMFO-005
A47: 7 | B47: Census 2026 (Asst. Nodal) | C47: Control room infra set up? (Y/N) | D47: Y/N | I47: =IF(AND(ISNUMBER(G47),ISNUMBER(H47)),H47-G47,"") | J47: =IF(AND(ISNUMBER(E47),E47>0,ISNUMBER(H47)),H47/E47,"") | K47: In Progress | L47: =IF(M47="Yes","🔴 BOTTOM",IF(M47="No","✓ Cleared",IF(Q47="MIN",IF(AND(ISNUMBER(F47),ISNUMBER(H47)),IF(H47<F47*'Master Dashboard'!$B$4,"🔴 LOW",""),""),IF(Q47="MAX",IF(AND(ISNUMBER(F47),ISNUMBER(H47)),IF(H47>F47,"🔴 HIGH",""),""),"")))) | M47: Auto | P47: Training 13 May–13 Jun | R47: CMFO-039

Sheet AC (G)
A1: AC (G) — Priority Agenda Review | DC Ludhiana (MASTER)
A2: Sr | B2: Priority Agenda | C2: KPI / Metric | D2: Concerned Officer / Unit | E2: Target / Total | F2: Flag Bar | G2: Last Value | H2: Current Value | I2: Change | J2: Achieved % | K2: Status | L2: Auto-Flag | M2: Bottom Performer | N2: Updated By | O2: Update Date | P2: Remarks / Context / Pending Action | Q2: Rule | R2: Key
A3: ▣ SCHEMES — metric-based (fed from officer workbook)
A4: 1 | B4: Punjab State Trader Commission (PSTC) | C4: 📊 Total grievances | H4: 233 | P4: All grievances received under PSTC across departments.
C5: 📊 Final resolved | H5: 147 | P5: 63% of total. Implementation under process: 60; Not-agree: 5; Not-resolvable: 7.
C6: MCL — resolved | D6: cases | E6: 52 | F6: 41.6 | H6: 45 | I6: =IF(AND(ISNUMBER(G6),ISNUMBER(H6)),H6-G6,"") | J6: =IF(AND(ISNUMBER(E6),E6>0,ISNUMBER(H6)),H6/E6,"") -> 0.86538462 | K6: In Progress | L6: =IF(M6="Yes","🔴 BOTTOM",IF(M6="No","✓ Cleared",IF(Q6="MIN",IF(AND(ISNUMBER(F6),ISNUMBER(H6)),IF(H6<F6*'Master Dashboard'!$B$4,"🔴 LOW",""),""),IF(Q6="MAX",IF(AND(ISNUMBER(F6),ISNUMBER(H6)),IF(H6>F6,"🔴 HIGH",""),""),"")))) | M6: Auto | N6: Gov Cell (report) | O6: 05-06-2026 | P6: 87% done | active 7 | 6 stale — Resolved of total received for this dept; active = open + under-implementation. | Q6: MIN | R6: ACG-001
C7: Electricity (PSPCL) — resolved | D7: cases | E7: 40 | F7: 32 | H7: 25 | I7: =IF(AND(ISNUMBER(G7),ISNUMBER(H7)),H7-G7,"") | J7: =IF(AND(ISNUMBER(E7),E7>0,ISNUMBER(H7)),H7/E7,"") -> 0.625 | K7: In Progress | L7: =IF(M7="Yes","🔴 BOTTOM",IF(M7="No","✓ Cleared",IF(Q7="MIN",IF(AND(ISNUMBER(F7),ISNUMBER(H7)),IF(H7<F7*'Master Dashboard'!$B$4,"🔴 LOW",""),""),IF(Q7="MAX",IF(AND(ISNUMBER(F7),ISNUMBER(H7)),IF(H7>F7,"🔴 HIGH",""),""),"")))) -> 🔴 LOW | M7: Auto | N7: Gov Cell (report) | O7: 05-06-2026 | P7: 63% done | active 15 | 10 stale — Resolved of total received for this dept; active = open + under-implementation. | Q7: MIN | R7: ACG-002
C8: Local Govt — resolved | D8: cases | E8: 27 | F8: 21.6 | H8: 18 | I8: =IF(AND(ISNUMBER(G8),ISNUMBER(H8)),H8-G8,"") | J8: =IF(AND(ISNUMBER(E8),E8>0,ISNUMBER(H8)),H8/E8,"") -> 0.66666667 | K8: In Progress | L8: =IF(M8="Yes","🔴 BOTTOM",IF(M8="No","✓ Cleared",IF(Q8="MIN",IF(AND(ISNUMBER(F8),ISNUMBER(H8)),IF(H8<F8*'Master Dashboard'!$B$4,"🔴 LOW",""),""),IF(Q8="MAX",IF(AND(ISNUMBER(F8),ISNUMBER(H8)),IF(H8>F8,"🔴 HIGH",""),""),"")))) -> 🔴 LOW | M8: Auto | N8: Gov Cell (report) | O8: 05-06-2026 | P8: 67% done | active 9 | 9 stale — Resolved of total received for this dept; active = open + under-implementation. | Q8: MIN | R8: ACG-003
C9: Others — resolved | D9: cases | E9: 21 | F9: 16.8 | H9: 14 | I9: =IF(AND(ISNUMBER(G9),ISNUMBER(H9)),H9-G9,"") | J9: =IF(AND(ISNUMBER(E9),E9>0,ISNUMBER(H9)),H9/E9,"") -> 0.66666667 | K9: In Progress | L9: =IF(M9="Yes","🔴 BOTTOM",IF(M9="No","✓ Cleared",IF(Q9="MIN",IF(AND(ISNUMBER(F9),ISNUMBER(H9)),IF(H9<F9*'Master Dashboard'!$B$4,"🔴 LOW",""),""),IF(Q9="MAX",IF(AND(ISNUMBER(F9),ISNUMBER(H9)),IF(H9>F9,"🔴 HIGH",""),""),"")))) -> 🔴 LOW | M9: Auto | N9: Gov Cell (report) | O9: 05-06-2026 | P9: 67% done | active 7 | 6 stale — Resolved of total received for this dept; active = open + under-implementation. | Q9: MIN | R9: ACG-004
C10: Rural Dev & Panchayat — resolved | D10: cases | E10: 17 | F10: 13.6 | H10: 4 | I10: =IF(AND(ISNUMBER(G10),ISNUMBER(H10)),H10-G10,"") | J10: =IF(AND(ISNUMBER(E10),E10>0,ISNUMBER(H10)),H10/E10,"") -> 0.23529412 | K10: Pending/Blocked | L10: =IF(M10="Yes","🔴 BOTTOM",IF(M10="No","✓ Cleared",IF(Q10="MIN",IF(AND(ISNUMBER(F10),ISNUMBER(H10)),IF(H10<F10*'Master Dashboard'!$B$4,"🔴 LOW",""),""),IF(Q10="MAX",IF(AND(ISNUMBER(F10),ISNUMBER(H10)),IF(H10>F10,"🔴 HIGH",""),""),"")))) -> 🔴 LOW | M10: Auto | N10: Gov Cell (report) | O10: 05-06-2026 | P10: 24% done | active 13 | 11 stale — Resolved of total received for this dept; active = open + under-implementation. | Q10: MIN | R10: ACG-005
C11: Police — resolved | D11: cases | E11: 44 | F11: 35.2 | H11: 43 | I11: =IF(AND(ISNUMBER(G11),ISNUMBER(H11)),H11-G11,"") | J11: =IF(AND(ISNUMBER(E11),E11>0,ISNUMBER(H11)),H11/E11,"") -> 0.97727273 | K11: In Progress | L11: =IF(M11="Yes","🔴 BOTTOM",IF(M11="No","✓ Cleared",IF(Q11="MIN",IF(AND(ISNUMBER(F11),ISNUMBER(H11)),IF(H11<F11*'Master Dashboard'!$B$4,"🔴 LOW",""),""),IF(Q11="MAX",IF(AND(ISNUMBER(F11),ISNUMBER(H11)),IF(H11>F11,"🔴 HIGH",""),""),"")))) | M11: Auto | N11: Gov Cell (report) | O11: 05-06-2026 | P11: 98% done | active 1 | 1 stale — Resolved of total received for this dept; active = open + under-implementation. | Q11: MIN | R11: ACG-006
C12: District Food & Supply — resolved | D12: cases | E12: 2 | F12: 1.6 | H12: 2 | I12: =IF(AND(ISNUMBER(G12),ISNUMBER(H12)),H12-G12,"") | J12: =IF(AND(ISNUMBER(E12),E12>0,ISNUMBER(H12)),H12/E12,"") -> 1 | K12: Completed | L12: =IF(M12="Yes","🔴 BOTTOM",IF(M12="No","✓ Cleared",IF(Q12="MIN",IF(AND(ISNUMBER(F12),ISNUMBER(H12)),IF(H12<F12*'Master Dashboard'!$B$4,"🔴 LOW",""),""),IF(Q12="MAX",IF(AND(ISNUMBER(F12),ISNUMBER(H12)),IF(H12>F12,"🔴 HIGH",""),""),"")))) | M12: Auto | N12: Gov Cell (report) | O12: 05-06-2026 | P12: 100% done | active 0 | 0 stale — Resolved of total received for this dept; active = open + under-implementation. | Q12: MIN | R12: ACG-007
C13: PWD — resolved | D13: cases | E13: 4 | F13: 3.2 | H13: 0 | I13: =IF(AND(ISNUMBER(G13),ISNUMBER(H13)),H13-G13,"") | J13: =IF(AND(ISNUMBER(E13),E13>0,ISNUMBER(H13)),H13/E13,"") -> 0 | K13: Pending/Blocked | L13: =IF(M13="Yes","🔴 BOTTOM",IF(M13="No","✓ Cleared",IF(Q13="MIN",IF(AND(ISNUMBER(F13),ISNUMBER(H13)),IF(H13<F13*'Master Dashboard'!$B$4,"🔴 LOW",""),""),IF(Q13="MAX",IF(AND(ISNUMBER(F13),ISNUMBER(H13)),IF(H13>F13,"🔴 HIGH",""),""),"")))) -> 🔴 LOW | M13: Auto | N13: Gov Cell (report) | O13: 05-06-2026 | P13: 0% done | active 4 | 4 stale — Resolved of total received for this dept; active = open + under-implementation. | Q13: MIN | R13: ACG-008
C14: Tax & Excise — resolved | D14: cases | E14: 5 | F14: 4 | H14: 4 | I14: =IF(AND(ISNUMBER(G14),ISNUMBER(H14)),H14-G14,"") | J14: =IF(AND(ISNUMBER(E14),E14>0,ISNUMBER(H14)),H14/E14,"") -> 0.8 | K14: In Progress | L14: =IF(M14="Yes","🔴 BOTTOM",IF(M14="No","✓ Cleared",IF(Q14="MIN",IF(AND(ISNUMBER(F14),ISNUMBER(H14)),IF(H14<F14*'Master Dashboard'!$B$4,"🔴 LOW",""),""),IF(Q14="MAX",IF(AND(ISNUMBER(F14),ISNUMBER(H14)),IF(H14>F14,"🔴 HIGH",""),""),"")))) | M14: Auto | N14: Gov Cell (report) | O14: 05-06-2026 | P14: 80% done | active 1 | 0 stale — Resolved of total received for this dept; active = open + under-implementation. | Q14: MIN | R14: ACG-009
C15: Revenue — resolved | D15: cases | E15: 0 | H15: 0 | I15: =IF(AND(ISNUMBER(G15),ISNUMBER(H15)),H15-G15,"") | J15: =IF(AND(ISNUMBER(E15),E15>0,ISNUMBER(H15)),H15/E15,"") | K15: Pending/Blocked | L15: =IF(M15="Yes","🔴 BOTTOM",IF(M15="No","✓ Cleared",IF(Q15="MIN",IF(AND(ISNUMBER(F15),ISNUMBER(H15)),IF(H15<F15*'Master Dashboard'!$B$4,"🔴 LOW",""),""),IF(Q15="MAX",IF(AND(ISNUMBER(F15),ISNUMBER(H15)),IF(H15>F15,"🔴 HIGH",""),""),"")))) | M15: Auto | N15: Gov Cell (report) | O15: 05-06-2026 | P15: 0% done | active 0 | 0 stale — Resolved of total received for this dept; active = open + under-implementation. | Q15: MIN | R15: ACG-010
C16: Mandi Board — resolved | D16: cases | E16: 2 | F16: 1.6 | H16: 2 | I16: =IF(AND(ISNUMBER(G16),ISNUMBER(H16)),H16-G16,"") | J16: =IF(AND(ISNUMBER(E16),E16>0,ISNUMBER(H16)),H16/E16,"") -> 1 | K16: Completed | L16: =IF(M16="Yes","🔴 BOTTOM",IF(M16="No","✓ Cleared",IF(Q16="MIN",IF(AND(ISNUMBER(F16),ISNUMBER(H16)),IF(H16<F16*'Master Dashboard'!$B$4,"🔴 LOW",""),""),IF(Q16="MAX",IF(AND(ISNUMBER(F16),ISNUMBER(H16)),IF(H16>F16,"🔴 HIGH",""),""),"")))) | M16: Auto | N16: Gov Cell (report) | O16: 05-06-2026 | P16: 100% done | active 0 | 0 stale — Resolved of total received for this dept; active = open + under-implementation. | Q16: MIN | R16: ACG-011
C17: Pollution Control — resolved | D17: cases | E17: 1 | F17: 0.8 | H17: 1 | I17: =IF(AND(ISNUMBER(G17),ISNUMBER(H17)),H17-G17,"") | J17: =IF(AND(ISNUMBER(E17),E17>0,ISNUMBER(H17)),H17/E17,"") -> 1 | K17: Completed | L17: =IF(M17="Yes","🔴 BOTTOM",IF(M17="No","✓ Cleared",IF(Q17="MIN",IF(AND(ISNUMBER(F17),ISNUMBER(H17)),IF(H17<F17*'Master Dashboard'!$B$4,"🔴 LOW",""),""),IF(Q17="MAX",IF(AND(ISNUMBER(F17),ISNUMBER(H17)),IF(H17>F17,"🔴 HIGH",""),""),"")))) | M17: Auto | N17: Gov Cell (report) | O17: 05-06-2026 | P17: 100% done | active 0 | 0 stale — Resolved of total received for this dept; active = open + under-implementation. | Q17: MIN | R17: ACG-012
C18: Total grievances (district) | D18: cases | H18: 233 | I18: =IF(AND(ISNUMBER(G18),ISNUMBER(H18)),H18-G18,"") | J18: =IF(AND(ISNUMBER(E18),E18>0,ISNUMBER(H18)),H18/E18,"") | K18: In Progress | L18: =IF(M18="Yes","🔴 BOTTOM",IF(M18="No","✓ Cleared",IF(Q18="MIN",IF(AND(ISNUMBER(F18),ISNUMBER(H18)),IF(H18<F18*'Master Dashboard'!$B$4,"🔴 LOW",""),""),IF(Q18="MAX",IF(AND(ISNUMBER(F18),ISNUMBER(H18)),IF(H18>F18,"🔴 HIGH",""),""),"")))) | M18: Auto | N18: Gov Cell (report) | O18: 05-06-2026 | P18: Resolved 147; under impl 60; not-agree 5; not-resolvable 7 | R18: ACG-013
C19: % resolved — BDPO Ludhiana-1 | D19: % | E19: 0.8 | F19: 0.8 | H19: 0 | I19: =IF(AND(ISNUMBER(G19),ISNUMBER(H19)),H19-G19,"") | J19: =IF(AND(ISNUMBER(E19),E19>0,ISNUMBER(H19)),H19/E19,"") -> 0 | K19: Pending/Blocked | L19: =IF(M19="Yes","🔴 BOTTOM",IF(M19="No","✓ Cleared",IF(Q19="MIN",IF(AND(ISNUMBER(F19),ISNUMBER(H19)),IF(H19<F19*'Master Dashboard'!$B$4,"🔴 LOW",""),""),IF(Q19="MAX",IF(AND(ISNUMBER(F19),ISNUMBER(H19)),IF(H19>F19,"🔴 HIGH",""),""),"")))) -> 🔴 LOW | M19: Auto | N19: Gov Cell (report) | O19: 05-06-2026 | P19: 0 of 5 grievances resolved; 5 stale (4+ days no update). Actor to be called for review. | Q19: MIN | R19: ACG-014
C20: % resolved — BDPO Payal | D20: % | E20: 0.8 | F20: 0.8 | H20: 0 | I20: =IF(AND(ISNUMBER(G20),ISNUMBER(H20)),H20-G20,"") | J20: =IF(AND(ISNUMBER(E20),E20>0,ISNUMBER(H20)),H20/E20,"") -> 0 | K20: Pending/Blocked | L20: =IF(M20="Yes","🔴 BOTTOM",IF(M20="No","✓ Cleared",IF(Q20="MIN",IF(AND(ISNUMBER(F20),ISNUMBER(H20)),IF(H20<F20*'Master Dashboard'!$B$4,"🔴 LOW",""),""),IF(Q20="MAX",IF(AND(ISNUMBER(F20),ISNUMBER(H20)),IF(H20>F20,"🔴 HIGH",""),""),"")))) -> 🔴 LOW | M20: Auto | N20: Gov Cell (report) | O20: 05-06-2026 | P20: 0 of 1 grievances resolved; 1 stale (4+ days no update). Actor to be called for review. | Q20: MIN | R20: ACG-015
C21: % resolved — BDPO Khanna | D21: % | E21: 0.8 | F21: 0.8 | H21: 0.25 | I21: =IF(AND(ISNUMBER(G21),ISNUMBER(H21)),H21-G21,"") | J21: =IF(AND(ISNUMBER(E21),E21>0,ISNUMBER(H21)),H21/E21,"") -> 0.3125 | K21: Pending/Blocked | L21: =IF(M21="Yes","🔴 BOTTOM",IF(M21="No","✓ Cleared",IF(Q21="MIN",IF(AND(ISNUMBER(F21),ISNUMBER(H21)),IF(H21<F21*'Master Dashboard'!$B$4,"🔴 LOW",""),""),IF(Q21="MAX",IF(AND(ISNUMBER(F21),ISNUMBER(H21)),IF(H21>F21,"🔴 HIGH",""),""),"")))) -> 🔴 LOW | M21: Auto | N21: Gov Cell (report) | O21: 05-06-2026 | P21: 1 of 4 grievances resolved; 3 stale (4+ days no update). Actor to be called for review. | Q21: MIN | R21: ACG-016
C22: % resolved — BDPO Dehlon | D22: % | E22: 0.8 | F22: 0.8 | H22: 0.33 | I22: =IF(AND(ISNUMBER(G22),ISNUMBER(H22)),H22-G22,"") | J22: =IF(AND(ISNUMBER(E22),E22>0,ISNUMBER(H22)),H22/E22,"") -> 0.4125 | K22: Pending/Blocked | L22: =IF(M22="Yes","🔴 BOTTOM",IF(M22="No","✓ Cleared",IF(Q22="MIN",IF(AND(ISNUMBER(F22),ISNUMBER(H22)),IF(H22<F22*'Master Dashboard'!$B$4,"🔴 LOW",""),""),IF(Q22="MAX",IF(AND(ISNUMBER(F22),ISNUMBER(H22)),IF(H22>F22,"🔴 HIGH",""),""),"")))) -> 🔴 LOW | M22: Auto | N22: Gov Cell (report) | O22: 05-06-2026 | P22: 2 of 6 grievances resolved; 2 stale (4+ days no update). Actor to be called for review. | Q22: MIN | R22: ACG-017
C23: % resolved — EO Jagraon | D23: % | E23: 0.8 | F23: 0.8 | H23: 0.5 | I23: =IF(AND(ISNUMBER(G23),ISNUMBER(H23)),H23-G23,"") | J23: =IF(AND(ISNUMBER(E23),E23>0,ISNUMBER(H23)),H23/E23,"") -> 0.625 | K23: In Progress | L23: =IF(M23="Yes","🔴 BOTTOM",IF(M23="No","✓ Cleared",IF(Q23="MIN",IF(AND(ISNUMBER(F23),ISNUMBER(H23)),IF(H23<F23*'Master Dashboard'!$B$4,"🔴 LOW",""),""),IF(Q23="MAX",IF(AND(ISNUMBER(F23),ISNUMBER(H23)),IF(H23>F23,"🔴 HIGH",""),""),"")))) -> 🔴 LOW | M23: Auto | N23: Gov Cell (report) | O23: 05-06-2026 | P23: 4 of 8 grievances resolved; 3 stale (4+ days no update). Actor to be called for review. | Q23: MIN | R23: ACG-018
C24: % resolved — PSPCL XEN Ludhiana Central | D24: % | E24: 0.8 | F24: 0.8 | H24: 0.5 | I24: =IF(AND(ISNUMBER(G24),ISNUMBER(H24)),H24-G24,"") | J24: =IF(AND(ISNUMBER(E24),E24>0,ISNUMBER(H24)),H24/E24,"") -> 0.625 | K24: In Progress | L24: =IF(M24="Yes","🔴 BOTTOM",IF(M24="No","✓ Cleared",IF(Q24="MIN",IF(AND(ISNUMBER(F24),ISNUMBER(H24)),IF(H24<F24*'Master Dashboard'!$B$4,"🔴 LOW",""),""),IF(Q24="MAX",IF(AND(ISNUMBER(F24),ISNUMBER(H24)),IF(H24>F24,"🔴 HIGH",""),""),"")))) -> 🔴 LOW | M24: Auto | N24: Gov Cell (report) | O24: 05-06-2026 | P24: 5 of 10 grievances resolved; 4 stale (4+ days no update). Actor to be called for review. | Q24: MIN | R24: ACG-019
A25: 2 | B25: Dormant Accounts & Financial Bills | C25: 📊 Total dormant funds to reconcile | H25: 113.5 | P25: Rs 1.13 Cr across LAC 32L, DC Office 36L, ADC-G 28L, DEO 13L, Tehsil West 4.5L. Welfare Society file with DC.
C26: Total dormant funds to reconcile (Rs L) | D26: Rs lakh | H26: 113.5 | I26: =IF(AND(ISNUMBER(G26),ISNUMBER(H26)),H26-G26,"") | J26: =IF(AND(ISNUMBER(E26),E26>0,ISNUMBER(H26)),H26/E26,"") | K26: In Progress | L26: =IF(M26="Yes","🔴 BOTTOM",IF(M26="No","✓ Cleared",IF(Q26="MIN",IF(AND(ISNUMBER(F26),ISNUMBER(H26)),IF(H26<F26*'Master Dashboard'!$B$4,"🔴 LOW",""),""),IF(Q26="MAX",IF(AND(ISNUMBER(F26),ISNUMBER(H26)),IF(H26>F26,"🔴 HIGH",""),""),"")))) | M26: Auto | N26: Gov Cell (report) | O26: 05-06-2026 | P26: Welfare Society file put up to DC | R26: ACG-020
C27: LAC — reconciled? (Rs32L) | D27: Y/N | I27: =IF(AND(ISNUMBER(G27),ISNUMBER(H27)),H27-G27,"") | J27: =IF(AND(ISNUMBER(E27),E27>0,ISNUMBER(H27)),H27/E27,"") | K27: In Progress | L27: =IF(M27="Yes","🔴 BOTTOM",IF(M27="No","✓ Cleared",IF(Q27="MIN",IF(AND(ISNUMBER(F27),ISNUMBER(H27)),IF(H27<F27*'Master Dashboard'!$B$4,"🔴 LOW",""),""),IF(Q27="MAX",IF(AND(ISNUMBER(F27),ISNUMBER(H27)),IF(H27>F27,"🔴 HIGH",""),""),"")))) | M27: Auto | P27: Welfare Society creation in progress | R27: ACG-021
C28: Tehsil West — reconciled? (Rs4.5L) | D28: Y/N | I28: =IF(AND(ISNUMBER(G28),ISNUMBER(H28)),H28-G28,"") | J28: =IF(AND(ISNUMBER(E28),E28>0,ISNUMBER(H28)),H28/E28,"") | K28: In Progress | L28: =IF(M28="Yes","🔴 BOTTOM",IF(M28="No","✓ Cleared",IF(Q28="MIN",IF(AND(ISNUMBER(F28),ISNUMBER(H28)),IF(H28<F28*'Master Dashboard'!$B$4,"🔴 LOW",""),""),IF(Q28="MAX",IF(AND(ISNUMBER(F28),ISNUMBER(H28)),IF(H28>F28,"🔴 HIGH",""),""),"")))) | M28: Auto | P28: Welfare Society creation in progress | R28: ACG-022
C29: DC Office — reconciled? (Rs36L) | D29: Y/N | I29: =IF(AND(ISNUMBER(G29),ISNUMBER(H29)),H29-G29,"") | J29: =IF(AND(ISNUMBER(E29),E29>0,ISNUMBER(H29)),H29/E29,"") | K29: In Progress | L29: =IF(M29="Yes","🔴 BOTTOM",IF(M29="No","✓ Cleared",IF(Q29="MIN",IF(AND(ISNUMBER(F29),ISNUMBER(H29)),IF(H29<F29*'Master Dashboard'!$B$4,"🔴 LOW",""),""),IF(Q29="MAX",IF(AND(ISNUMBER(F29),ISNUMBER(H29)),IF(H29>F29,"🔴 HIGH",""),""),"")))) | M29: Auto | P29: Welfare Society creation in progress | R29: ACG-023
C30: ADC G — reconciled? (Rs28L) | D30: Y/N | I30: =IF(AND(ISNUMBER(G30),ISNUMBER(H30)),H30-G30,"") | J30: =IF(AND(ISNUMBER(E30),E30>0,ISNUMBER(H30)),H30/E30,"") | K30: In Progress | L30: =IF(M30="Yes","🔴 BOTTOM",IF(M30="No","✓ Cleared",IF(Q30="MIN",IF(AND(ISNUMBER(F30),ISNUMBER(H30)),IF(H30<F30*'Master Dashboard'!$B$4,"🔴 LOW",""),""),IF(Q30="MAX",IF(AND(ISNUMBER(F30),ISNUMBER(H30)),IF(H30>F30,"🔴 HIGH",""),""),"")))) | M30: Auto | P30: Welfare Society creation in progress | R30: ACG-024
C31: DEO — reconciled? (Rs13L) | D31: Y/N | I31: =IF(AND(ISNUMBER(G31),ISNUMBER(H31)),H31-G31,"") | J31: =IF(AND(ISNUMBER(E31),E31>0,ISNUMBER(H31)),H31/E31,"") | K31: In Progress | L31: =IF(M31="Yes","🔴 BOTTOM",IF(M31="No","✓ Cleared",IF(Q31="MIN",IF(AND(ISNUMBER(F31),ISNUMBER(H31)),IF(H31<F31*'Master Dashboard'!$B$4,"🔴 LOW",""),""),IF(Q31="MAX",IF(AND(ISNUMBER(F31),ISNUMBER(H31)),IF(H31>F31,"🔴 HIGH",""),""),"")))) | M31: Auto | P31: Welfare Society creation in progress | R31: ACG-025
A32: ▣ PRIORITY TASKS — qualitative / assigned tasks
A33: 3 | B33: Red Cross FD | C33: FDs merged / interest mode | D33: status | I33: =IF(AND(ISNUMBER(G33),ISNUMBER(H33)),H33-G33,"") | J33: =IF(AND(ISNUMBER(E33),E33>0,ISNUMBER(H33)),H33/E33,"") | K33: On Track | L33: =IF(M33="Yes","🔴 BOTTOM",IF(M33="No","✓ Cleared",IF(Q33="MIN",IF(AND(ISNUMBER(F33),ISNUMBER(H33)),IF(H33<F33*'Master Dashboard'!$B$4,"🔴 LOW",""),""),IF(Q33="MAX",IF(AND(ISNUMBER(F33),ISNUMBER(H33)),IF(H33>F33,"🔴 HIGH",""),""),"")))) | M33: Auto | P33: 6 FDs merged to 2; monthly interest from June | R33: ACG-026
A34: 4 | B34: YnV Bills — Phase I & II | C34: SAARC Knit & PP mismatch — meeting held? (Y/N) | D34: Y/N | I34: =IF(AND(ISNUMBER(G34),ISNUMBER(H34)),H34-G34,"") | J34: =IF(AND(ISNUMBER(E34),E34>0,ISNUMBER(H34)),H34/E34,"") | K34: In Progress | L34: =IF(M34="Yes","🔴 BOTTOM",IF(M34="No","✓ Cleared",IF(Q34="MIN",IF(AND(ISNUMBER(F34),ISNUMBER(H34)),IF(H34<F34*'Master Dashboard'!$B$4,"🔴 LOW",""),""),IF(Q34="MAX",IF(AND(ISNUMBER(F34),ISNUMBER(H34)),IF(H34>F34,"🔴 HIGH",""),""),"")))) | M34: Auto | P34: Phase 1 complete; Phase 2 mtg 5/6 Jun | R34: ACG-027
A35: 5 | B35: Court — Raikot Judicial Complex | C35: Letter to D&S Judge — reply received? (Y/N) | D35: Y/N | I35: =IF(AND(ISNUMBER(G35),ISNUMBER(H35)),H35-G35,"") | J35: =IF(AND(ISNUMBER(E35),E35>0,ISNUMBER(H35)),H35/E35,"") | K35: Pending/Blocked | L35: =IF(M35="Yes","🔴 BOTTOM",IF(M35="No","✓ Cleared",IF(Q35="MIN",IF(AND(ISNUMBER(F35),ISNUMBER(H35)),IF(H35<F35*'Master Dashboard'!$B$4,"🔴 LOW",""),""),IF(Q35="MAX",IF(AND(ISNUMBER(F35),ISNUMBER(H35)),IF(H35>F35,"🔴 HIGH",""),""),"")))) | M35: Auto | P35: Rs7 Cr for judicial infra land | R35: ACG-028
A36: 6 | B36: Building Committee | C36: Tree felling (multi-level parking) — application filed? (Y/N) | D36: Y/N | I36: =IF(AND(ISNUMBER(G36),ISNUMBER(H36)),H36-G36,"") | J36: =IF(AND(ISNUMBER(E36),E36>0,ISNUMBER(H36)),H36/E36,"") | K36: In Progress | L36: =IF(M36="Yes","🔴 BOTTOM",IF(M36="No","✓ Cleared",IF(Q36="MIN",IF(AND(ISNUMBER(F36),ISNUMBER(H36)),IF(H36<F36*'Master Dashboard'!$B$4,"🔴 LOW",""),""),IF(Q36="MAX",IF(AND(ISNUMBER(F36),ISNUMBER(H36)),IF(H36>F36,"🔴 HIGH",""),""),"")))) | M36: Auto | P36: 147 trees; application filed 17/05 | R36: ACG-029
A37: 7 | B37: Camera Court Complex — Smart City | C37: Installation % complete | D37: % | E37: 1 | F37: 1 | I37: =IF(AND(ISNUMBER(G37),ISNUMBER(H37)),H37-G37,"") | J37: =IF(AND(ISNUMBER(E37),E37>0,ISNUMBER(H37)),H37/E37,"") | K37: In Progress | L37: =IF(M37="Yes","🔴 BOTTOM",IF(M37="No","✓ Cleared",IF(Q37="MIN",IF(AND(ISNUMBER(F37),ISNUMBER(H37)),IF(H37<F37*'Master Dashboard'!$B$4,"🔴 LOW",""),""),IF(Q37="MAX",IF(AND(ISNUMBER(F37),ISNUMBER(H37)),IF(H37>F37,"🔴 HIGH",""),""),"")))) | M37: Auto | P37: Smart City funds status pending | Q37: MIN | R37: ACG-030

Sheet DRO
A1: DRO — Priority Agenda Review | DC Ludhiana (MASTER)
A2: Sr | B2: Priority Agenda | C2: KPI / Metric | D2: Concerned Officer / Unit | E2: Target / Total | F2: Flag Bar | G2: Last Value | H2: Current Value | I2: Change | J2: Achieved % | K2: Status | L2: Auto-Flag | M2: Bottom Performer | N2: Updated By | O2: Update Date | P2: Remarks / Context / Pending Action | Q2: Rule | R2: Key
A3: ▣ SCHEMES — metric-based (fed from officer workbook)
A4: 1 | B4: Svamitva — Abadi Deh (Urban Property Cards) | C4: Map-1 estates being finalised | D4: estates | H4: 3 | I4: =IF(AND(ISNUMBER(G4),ISNUMBER(H4)),H4-G4,"") | J4: =IF(AND(ISNUMBER(E4),E4>0,ISNUMBER(H4)),H4/E4,"") | K4: In Progress | L4: =IF(M4="Yes","🔴 BOTTOM",IF(M4="No","✓ Cleared",IF(Q4="MIN",IF(AND(ISNUMBER(F4),ISNUMBER(H4)),IF(H4<F4*'Master Dashboard'!$B$4,"🔴 LOW",""),""),IF(Q4="MAX",IF(AND(ISNUMBER(F4),ISNUMBER(H4)),IF(H4>F4,"🔴 HIGH",""),""),"")))) | M4: Auto | N4: Gov Cell (report) | O4: 05-06-2026 | P4: Haibowal Kalan, Jawaddi Khurd, Ayali Khurd | R4: DRO-001
C5: Map-2 awaited from SOI | D5: estates | E5: 0 | F5: 0 | H5: 4 | I5: =IF(AND(ISNUMBER(G5),ISNUMBER(H5)),H5-G5,"") | J5: =IF(AND(ISNUMBER(E5),E5>0,ISNUMBER(H5)),H5/E5,"") | K5: Pending/Blocked | L5: =IF(M5="Yes","🔴 BOTTOM",IF(M5="No","✓ Cleared",IF(Q5="MIN",IF(AND(ISNUMBER(F5),ISNUMBER(H5)),IF(H5<F5*'Master Dashboard'!$B$4,"🔴 LOW",""),""),IF(Q5="MAX",IF(AND(ISNUMBER(F5),ISNUMBER(H5)),IF(H5>F5,"🔴 HIGH",""),""),"")))) -> 🔴 HIGH | M5: Auto | N5: Gov Cell (report) | O5: 05-06-2026 | P5: Dugri, Rajpura, Barewal Awana, Sunet | Q5: MAX | R5: DRO-002
C6: Ground Truthing sent to SOI | D6: estates | H6: 8 | I6: =IF(AND(ISNUMBER(G6),ISNUMBER(H6)),H6-G6,"") | J6: =IF(AND(ISNUMBER(E6),E6>0,ISNUMBER(H6)),H6/E6,"") | K6: In Progress | L6: =IF(M6="Yes","🔴 BOTTOM",IF(M6="No","✓ Cleared",IF(Q6="MIN",IF(AND(ISNUMBER(F6),ISNUMBER(H6)),IF(H6<F6*'Master Dashboard'!$B$4,"🔴 LOW",""),""),IF(Q6="MAX",IF(AND(ISNUMBER(F6),ISNUMBER(H6)),IF(H6>F6,"🔴 HIGH",""),""),"")))) | M6: Auto | N6: Gov Cell (report) | O6: 05-06-2026 | R6: DRO-003
C7: Ground Truthing PENDING | D7: estates | E7: 0 | F7: 0 | H7: 5 | I7: =IF(AND(ISNUMBER(G7),ISNUMBER(H7)),H7-G7,"") | J7: =IF(AND(ISNUMBER(E7),E7>0,ISNUMBER(H7)),H7/E7,"") | K7: Pending/Blocked | L7: =IF(M7="Yes","🔴 BOTTOM",IF(M7="No","✓ Cleared",IF(Q7="MIN",IF(AND(ISNUMBER(F7),ISNUMBER(H7)),IF(H7<F7*'Master Dashboard'!$B$4,"🔴 LOW",""),""),IF(Q7="MAX",IF(AND(ISNUMBER(F7),ISNUMBER(H7)),IF(H7>F7,"🔴 HIGH",""),""),"")))) -> 🔴 HIGH | M7: Auto | N7: Gov Cell (report) | O7: 05-06-2026 | P7: Dhandari Kalan, Noorwala, Kulewal, Jamalpur Awana, Ludhiana City | Q7: MAX | R7: DRO-004
C8: Estates with No Laal Lakir | D8: estates | H8: 3 | I8: =IF(AND(ISNUMBER(G8),ISNUMBER(H8)),H8-G8,"") | J8: =IF(AND(ISNUMBER(E8),E8>0,ISNUMBER(H8)),H8/E8,"") | K8: In Progress | L8: =IF(M8="Yes","🔴 BOTTOM",IF(M8="No","✓ Cleared",IF(Q8="MIN",IF(AND(ISNUMBER(F8),ISNUMBER(H8)),IF(H8<F8*'Master Dashboard'!$B$4,"🔴 LOW",""),""),IF(Q8="MAX",IF(AND(ISNUMBER(F8),ISNUMBER(H8)),IF(H8>F8,"🔴 HIGH",""),""),"")))) | M8: Auto | N8: Gov Cell (report) | O8: 05-06-2026 | P8: Karabara, Mahal Bhagat, Phamra | R8: DRO-005
A9: 2 | B9: Svamitva — Rural Ground Truthing Pendency | C9: 📊 Tehsils with NO change ~1.5 months | H9: 4 | P9: Ludhiana Central, Dehlon, Mullanpur Dakha, Maloud — immediate follow-up needed.
C10: GT pending — T Ludhiana West | D10: cases | E10: 0 | F10: 5 | G10: 23 | H10: 18 | I10: =IF(AND(ISNUMBER(G10),ISNUMBER(H10)),H10-G10,"") -> -5 | J10: =IF(AND(ISNUMBER(E10),E10>0,ISNUMBER(H10)),H10/E10,"") | K10: Pending/Blocked | L10: =IF(M10="Yes","🔴 BOTTOM",IF(M10="No","✓ Cleared",IF(Q10="MIN",IF(AND(ISNUMBER(F10),ISNUMBER(H10)),IF(H10<F10*'Master Dashboard'!$B$4,"🔴 LOW",""),""),IF(Q10="MAX",IF(AND(ISNUMBER(F10),ISNUMBER(H10)),IF(H10>F10,"🔴 HIGH",""),""),"")))) -> 🔴 HIGH | M10: Auto | N10: Gov Cell (report) | O10: 05-06-2026 | Q10: MAX | R10: DRO-006
C11: GT pending — NT Koom Kalan | D11: cases | E11: 0 | F11: 5 | G11: 12 | H11: 12 | I11: =IF(AND(ISNUMBER(G11),ISNUMBER(H11)),H11-G11,"") -> 0 | J11: =IF(AND(ISNUMBER(E11),E11>0,ISNUMBER(H11)),H11/E11,"") | K11: Pending/Blocked | L11: =IF(M11="Yes","🔴 BOTTOM",IF(M11="No","✓ Cleared",IF(Q11="MIN",IF(AND(ISNUMBER(F11),ISNUMBER(H11)),IF(H11<F11*'Master Dashboard'!$B$4,"🔴 LOW",""),""),IF(Q11="MAX",IF(AND(ISNUMBER(F11),ISNUMBER(H11)),IF(H11>F11,"🔴 HIGH",""),""),"")))) -> 🔴 HIGH | M11: Auto | N11: Gov Cell (report) | O11: 05-06-2026 | Q11: MAX | R11: DRO-007
C12: GT pending — T Central | D12: cases | E12: 0 | F12: 5 | G12: 6 | H12: 5 | I12: =IF(AND(ISNUMBER(G12),ISNUMBER(H12)),H12-G12,"") -> -1 | J12: =IF(AND(ISNUMBER(E12),E12>0,ISNUMBER(H12)),H12/E12,"") | K12: In Progress | L12: =IF(M12="Yes","🔴 BOTTOM",IF(M12="No","✓ Cleared",IF(Q12="MIN",IF(AND(ISNUMBER(F12),ISNUMBER(H12)),IF(H12<F12*'Master Dashboard'!$B$4,"🔴 LOW",""),""),IF(Q12="MAX",IF(AND(ISNUMBER(F12),ISNUMBER(H12)),IF(H12>F12,"🔴 HIGH",""),""),"")))) | M12: Auto | N12: Gov Cell (report) | O12: 05-06-2026 | P12: No change ~1.5 months | Q12: MAX | R12: DRO-008
C13: GT pending — NT Dehlon | D13: cases | E13: 0 | F13: 5 | G13: 4 | H13: 4 | I13: =IF(AND(ISNUMBER(G13),ISNUMBER(H13)),H13-G13,"") -> 0 | J13: =IF(AND(ISNUMBER(E13),E13>0,ISNUMBER(H13)),H13/E13,"") | K13: In Progress | L13: =IF(M13="Yes","🔴 BOTTOM",IF(M13="No","✓ Cleared",IF(Q13="MIN",IF(AND(ISNUMBER(F13),ISNUMBER(H13)),IF(H13<F13*'Master Dashboard'!$B$4,"🔴 LOW",""),""),IF(Q13="MAX",IF(AND(ISNUMBER(F13),ISNUMBER(H13)),IF(H13>F13,"🔴 HIGH",""),""),"")))) | M13: Auto | N13: Gov Cell (report) | O13: 05-06-2026 | P13: No change ~1.5 months | Q13: MAX | R13: DRO-009
C14: GT pending — NT Mullanpur Dakha | D14: cases | E14: 0 | F14: 5 | G14: 9 | H14: 4 | I14: =IF(AND(ISNUMBER(G14),ISNUMBER(H14)),H14-G14,"") -> -5 | J14: =IF(AND(ISNUMBER(E14),E14>0,ISNUMBER(H14)),H14/E14,"") | K14: In Progress | L14: =IF(M14="Yes","🔴 BOTTOM",IF(M14="No","✓ Cleared",IF(Q14="MIN",IF(AND(ISNUMBER(F14),ISNUMBER(H14)),IF(H14<F14*'Master Dashboard'!$B$4,"🔴 LOW",""),""),IF(Q14="MAX",IF(AND(ISNUMBER(F14),ISNUMBER(H14)),IF(H14>F14,"🔴 HIGH",""),""),"")))) | M14: Auto | N14: Gov Cell (report) | O14: 05-06-2026 | P14: No change ~1.5 months | Q14: MAX | R14: DRO-010
C15: GT pending — NT Maloud | D15: cases | E15: 0 | F15: 5 | G15: 4 | H15: 4 | I15: =IF(AND(ISNUMBER(G15),ISNUMBER(H15)),H15-G15,"") -> 0 | J15: =IF(AND(ISNUMBER(E15),E15>0,ISNUMBER(H15)),H15/E15,"") | K15: In Progress | L15: =IF(M15="Yes","🔴 BOTTOM",IF(M15="No","✓ Cleared",IF(Q15="MIN",IF(AND(ISNUMBER(F15),ISNUMBER(H15)),IF(H15<F15*'Master Dashboard'!$B$4,"🔴 LOW",""),""),IF(Q15="MAX",IF(AND(ISNUMBER(F15),ISNUMBER(H15)),IF(H15>F15,"🔴 HIGH",""),""),"")))) | M15: Auto | N15: Gov Cell (report) | O15: 05-06-2026 | P15: No change ~1.5 months | Q15: MAX | R15: DRO-011
C16: GT pending — T Jagraon | D16: cases | E16: 0 | F16: 5 | G16: 11 | H16: 3 | I16: =IF(AND(ISNUMBER(G16),ISNUMBER(H16)),H16-G16,"") -> -8 | J16: =IF(AND(ISNUMBER(E16),E16>0,ISNUMBER(H16)),H16/E16,"") | K16: In Progress | L16: =IF(M16="Yes","🔴 BOTTOM",IF(M16="No","✓ Cleared",IF(Q16="MIN",IF(AND(ISNUMBER(F16),ISNUMBER(H16)),IF(H16<F16*'Master Dashboard'!$B$4,"🔴 LOW",""),""),IF(Q16="MAX",IF(AND(ISNUMBER(F16),ISNUMBER(H16)),IF(H16>F16,"🔴 HIGH",""),""),"")))) | M16: Auto | N16: Gov Cell (report) | O16: 05-06-2026 | Q16: MAX | R16: DRO-012
C17: GT pending — NT Sidhwan Bet | D17: cases | E17: 0 | F17: 5 | G17: 12 | H17: 3 | I17: =IF(AND(ISNUMBER(G17),ISNUMBER(H17)),H17-G17,"") -> -9 | J17: =IF(AND(ISNUMBER(E17),E17>0,ISNUMBER(H17)),H17/E17,"") | K17: In Progress | L17: =IF(M17="Yes","🔴 BOTTOM",IF(M17="No","✓ Cleared",IF(Q17="MIN",IF(AND(ISNUMBER(F17),ISNUMBER(H17)),IF(H17<F17*'Master Dashboard'!$B$4,"🔴 LOW",""),""),IF(Q17="MAX",IF(AND(ISNUMBER(F17),ISNUMBER(H17)),IF(H17>F17,"🔴 HIGH",""),""),"")))) | M17: Auto | N17: Gov Cell (report) | O17: 05-06-2026 | Q17: MAX | R17: DRO-013
C18: GT pending — T Khanna | D18: cases | E18: 0 | F18: 5 | G18: 7 | H18: 1 | I18: =IF(AND(ISNUMBER(G18),ISNUMBER(H18)),H18-G18,"") -> -6 | J18: =IF(AND(ISNUMBER(E18),E18>0,ISNUMBER(H18)),H18/E18,"") | K18: In Progress | L18: =IF(M18="Yes","🔴 BOTTOM",IF(M18="No","✓ Cleared",IF(Q18="MIN",IF(AND(ISNUMBER(F18),ISNUMBER(H18)),IF(H18<F18*'Master Dashboard'!$B$4,"🔴 LOW",""),""),IF(Q18="MAX",IF(AND(ISNUMBER(F18),ISNUMBER(H18)),IF(H18>F18,"🔴 HIGH",""),""),"")))) | M18: Auto | N18: Gov Cell (report) | O18: 05-06-2026 | Q18: MAX | R18: DRO-014
A19: ▣ PRIORITY TASKS — qualitative / assigned tasks
A20: 3 | B20: NHAI Package 1 — Ropar–Ludhiana | C20: Amount pending (Rs Cr) | D20: Rs Cr | E20: 0 | F20: 0 | H20: 28 | I20: =IF(AND(ISNUMBER(G20),ISNUMBER(H20)),H20-G20,"") | J20: =IF(AND(ISNUMBER(E20),E20>0,ISNUMBER(H20)),H20/E20,"") | K20: Pending/Blocked | L20: =IF(M20="Yes","🔴 BOTTOM",IF(M20="No","✓ Cleared",IF(Q20="MIN",IF(AND(ISNUMBER(F20),ISNUMBER(H20)),IF(H20<F20*'Master Dashboard'!$B$4,"🔴 LOW",""),""),IF(Q20="MAX",IF(AND(ISNUMBER(F20),ISNUMBER(H20)),IF(H20>F20,"🔴 HIGH",""),""),"")))) -> 🔴 HIGH | M20: Auto | N20: Gov Cell (report) | O20: 05-06-2026 | P20: Talwandi Kalan & 3G-1 | Q20: MAX | R20: DRO-015
A21: 4 | B21: Kabja Karwai (Possession) | C21: Possession actions this week | D21: no. | I21: =IF(AND(ISNUMBER(G21),ISNUMBER(H21)),H21-G21,"") | J21: =IF(AND(ISNUMBER(E21),E21>0,ISNUMBER(H21)),H21/E21,"") | K21: In Progress | L21: =IF(M21="Yes","🔴 BOTTOM",IF(M21="No","✓ Cleared",IF(Q21="MIN",IF(AND(ISNUMBER(F21),ISNUMBER(H21)),IF(H21<F21*'Master Dashboard'!$B$4,"🔴 LOW",""),""),IF(Q21="MAX",IF(AND(ISNUMBER(F21),ISNUMBER(H21)),IF(H21>F21,"🔴 HIGH",""),""),"")))) | M21: Auto | P21: Regular monitoring | R21: DRO-016
A22: 5 | B22: Action vs Kanungo Jaspreet Dhaka | C22: Departmental proceedings status | D22: status | I22: =IF(AND(ISNUMBER(G22),ISNUMBER(H22)),H22-G22,"") | J22: =IF(AND(ISNUMBER(E22),E22>0,ISNUMBER(H22)),H22/E22,"") | K22: In Progress | L22: =IF(M22="Yes","🔴 BOTTOM",IF(M22="No","✓ Cleared",IF(Q22="MIN",IF(AND(ISNUMBER(F22),ISNUMBER(H22)),IF(H22<F22*'Master Dashboard'!$B$4,"🔴 LOW",""),""),IF(Q22="MAX",IF(AND(ISNUMBER(F22),ISNUMBER(H22)),IF(H22>F22,"🔴 HIGH",""),""),"")))) | M22: Auto | P22: Confirm status | R22: DRO-017
A23: 6 | B23: PM Pragati Portal | C23: Pending packages | D23: no. | E23: 0 | F23: 0 | I23: =IF(AND(ISNUMBER(G23),ISNUMBER(H23)),H23-G23,"") | J23: =IF(AND(ISNUMBER(E23),E23>0,ISNUMBER(H23)),H23/E23,"") | K23: In Progress | L23: =IF(M23="Yes","🔴 BOTTOM",IF(M23="No","✓ Cleared",IF(Q23="MIN",IF(AND(ISNUMBER(F23),ISNUMBER(H23)),IF(H23<F23*'Master Dashboard'!$B$4,"🔴 LOW",""),""),IF(Q23="MAX",IF(AND(ISNUMBER(F23),ISNUMBER(H23)),IF(H23>F23,"🔴 HIGH",""),""),"")))) | M23: Auto | P23: Timely submission | Q23: MAX | R23: DRO-018

Sheet SDM Samrala
A1: SDM Samrala — Priority Agenda Review | DC Ludhiana (MASTER)
A2: Sr | B2: Priority Agenda | C2: KPI / Metric | D2: Concerned Officer / Unit | E2: Target / Total | F2: Flag Bar | G2: Last Value | H2: Current Value | I2: Change | J2: Achieved % | K2: Status | L2: Auto-Flag | M2: Bottom Performer | N2: Updated By | O2: Update Date | P2: Remarks / Context / Pending Action | Q2: Rule | R2: Key
A3: ▣ PRIORITY TASKS — qualitative / assigned tasks
A4: 1 | B4: Ludhiana–Ropar Package II | C4: Possession pending (km) | D4: km | E4: 0 | F4: 0 | H4: 5 | I4: =IF(AND(ISNUMBER(G4),ISNUMBER(H4)),H4-G4,"") | J4: =IF(AND(ISNUMBER(E4),E4>0,ISNUMBER(H4)),H4/E4,"") | K4: Pending/Blocked | L4: =IF(M4="Yes","🔴 BOTTOM",IF(M4="No","✓ Cleared",IF(Q4="MIN",IF(AND(ISNUMBER(F4),ISNUMBER(H4)),IF(H4<F4*'Master Dashboard'!$B$4,"🔴 LOW",""),""),IF(Q4="MAX",IF(AND(ISNUMBER(F4),ISNUMBER(H4)),IF(H4>F4,"🔴 HIGH",""),""),"")))) -> 🔴 HIGH | M4: Auto | N4: Gov Cell (report) | O4: 05-06-2026 | P4: 5.315 km; arbitration; LA award challenged by NHAI | Q4: MAX | R4: SAMR-001
C5: PD reply on HGK draft award — received? (Y/N) | D5: Y/N | I5: =IF(AND(ISNUMBER(G5),ISNUMBER(H5)),H5-G5,"") | J5: =IF(AND(ISNUMBER(E5),E5>0,ISNUMBER(H5)),H5/E5,"") | K5: Pending/Blocked | L5: =IF(M5="Yes","🔴 BOTTOM",IF(M5="No","✓ Cleared",IF(Q5="MIN",IF(AND(ISNUMBER(F5),ISNUMBER(H5)),IF(H5<F5*'Master Dashboard'!$B$4,"🔴 LOW",""),""),IF(Q5="MAX",IF(AND(ISNUMBER(F5),ISNUMBER(H5)),IF(H5>F5,"🔴 HIGH",""),""),"")))) | M5: Auto | P5: NHAI conditionally accepted; under consideration | R5: SAMR-002
C6: Machhiwara Chat/Collector additional award — issued? (Y/N) | D6: Y/N | I6: =IF(AND(ISNUMBER(G6),ISNUMBER(H6)),H6-G6,"") | J6: =IF(AND(ISNUMBER(E6),E6>0,ISNUMBER(H6)),H6/E6,"") | K6: In Progress | L6: =IF(M6="Yes","🔴 BOTTOM",IF(M6="No","✓ Cleared",IF(Q6="MIN",IF(AND(ISNUMBER(F6),ISNUMBER(H6)),IF(H6<F6*'Master Dashboard'!$B$4,"🔴 LOW",""),""),IF(Q6="MAX",IF(AND(ISNUMBER(F6),ISNUMBER(H6)),IF(H6>F6,"🔴 HIGH",""),""),"")))) | M6: Auto | P6: Draft pending final signature; expected next week | R6: SAMR-003
A7: 2 | B7: Dhulewal Complex | C7: 📊 Dhulewal flood works completed | H7: 2 | P7: of 18 sanctioned at Dhussi Bandh; 16 stalled. Awaiting DC decision to shift to non-MGNREGA funds.
C8: Flood works completed | D8: works | E8: 18 | F8: 18 | H8: 2 | I8: =IF(AND(ISNUMBER(G8),ISNUMBER(H8)),H8-G8,"") | J8: =IF(AND(ISNUMBER(E8),E8>0,ISNUMBER(H8)),H8/E8,"") -> 0.11111111 | K8: Pending/Blocked | L8: =IF(M8="Yes","🔴 BOTTOM",IF(M8="No","✓ Cleared",IF(Q8="MIN",IF(AND(ISNUMBER(F8),ISNUMBER(H8)),IF(H8<F8*'Master Dashboard'!$B$4,"🔴 LOW",""),""),IF(Q8="MAX",IF(AND(ISNUMBER(F8),ISNUMBER(H8)),IF(H8>F8,"🔴 HIGH",""),""),"")))) -> 🔴 LOW | M8: Auto | N8: Gov Cell (report) | O8: 05-06-2026 | P8: 16 halted; Rs97.93L pending DC; shift to non-MGNREGA? | Q8: MIN | R8: SAMR-004
A9: 3 | B9: Mushqabad / CBG | C9: Mushqabad objections — draft sent? (Y/N) | D9: Y/N | I9: =IF(AND(ISNUMBER(G9),ISNUMBER(H9)),H9-G9,"") | J9: =IF(AND(ISNUMBER(E9),E9>0,ISNUMBER(H9)),H9/E9,"") | K9: Pending/Blocked | L9: =IF(M9="Yes","🔴 BOTTOM",IF(M9="No","✓ Cleared",IF(Q9="MIN",IF(AND(ISNUMBER(F9),ISNUMBER(H9)),IF(H9<F9*'Master Dashboard'!$B$4,"🔴 LOW",""),""),IF(Q9="MAX",IF(AND(ISNUMBER(F9),ISNUMBER(H9)),IF(H9>F9,"🔴 HIGH",""),""),"")))) | M9: Auto | R9: SAMR-005
A10: 4 | B10: Desilting — Mandala DO Letter | C10: Alternate desilting plan submitted? (Y/N) | D10: Y/N | I10: =IF(AND(ISNUMBER(G10),ISNUMBER(H10)),H10-G10,"") | J10: =IF(AND(ISNUMBER(E10),E10>0,ISNUMBER(H10)),H10/E10,"") | K10: Pending/Blocked | L10: =IF(M10="Yes","🔴 BOTTOM",IF(M10="No","✓ Cleared",IF(Q10="MIN",IF(AND(ISNUMBER(F10),ISNUMBER(H10)),IF(H10<F10*'Master Dashboard'!$B$4,"🔴 LOW",""),""),IF(Q10="MAX",IF(AND(ISNUMBER(F10),ISNUMBER(H10)),IF(H10>F10,"🔴 HIGH",""),""),"")))) | M10: Auto | P10: Village denied road access | R10: SAMR-006

Sheet SDM Jagraon
A1: SDM Jagraon — Priority Agenda Review | DC Ludhiana (MASTER)
A2: Sr | B2: Priority Agenda | C2: KPI / Metric | D2: Concerned Officer / Unit | E2: Target / Total | F2: Flag Bar | G2: Last Value | H2: Current Value | I2: Change | J2: Achieved % | K2: Status | L2: Auto-Flag | M2: Bottom Performer | N2: Updated By | O2: Update Date | P2: Remarks / Context / Pending Action | Q2: Rule | R2: Key
A3: ▣ PRIORITY TASKS — qualitative / assigned tasks
A4: 1 | B4: CBG Akhara | C4: Court case — next date | D4: date | H4: 08.07.2026 | I4: =IF(AND(ISNUMBER(G4),ISNUMBER(H4)),H4-G4,"") | J4: =IF(AND(ISNUMBER(E4),E4>0,ISNUMBER(H4)),H4/E4,"") | K4: Pending/Blocked | L4: =IF(M4="Yes","🔴 BOTTOM",IF(M4="No","✓ Cleared",IF(Q4="MIN",IF(AND(ISNUMBER(F4),ISNUMBER(H4)),IF(H4<F4*'Master Dashboard'!$B$4,"🔴 LOW",""),""),IF(Q4="MAX",IF(AND(ISNUMBER(F4),ISNUMBER(H4)),IF(H4>F4,"🔴 HIGH",""),""),"")))) | M4: Auto | N4: Gov Cell (report) | O4: 05-06-2026 | P4: Pending in High Court; status report PENDING | R4: JAGR-001
A5: 2 | B5: Bhundri | C5: Court case — next date | D5: date | H5: 08.07.2026 | I5: =IF(AND(ISNUMBER(G5),ISNUMBER(H5)),H5-G5,"") | J5: =IF(AND(ISNUMBER(E5),E5>0,ISNUMBER(H5)),H5/E5,"") | K5: Pending/Blocked | L5: =IF(M5="Yes","🔴 BOTTOM",IF(M5="No","✓ Cleared",IF(Q5="MIN",IF(AND(ISNUMBER(F5),ISNUMBER(H5)),IF(H5<F5*'Master Dashboard'!$B$4,"🔴 LOW",""),""),IF(Q5="MAX",IF(AND(ISNUMBER(F5),ISNUMBER(H5)),IF(H5>F5,"🔴 HIGH",""),""),"")))) | M5: Auto | N5: Gov Cell (report) | O5: 05-06-2026 | P5: Pending in High Court | R5: JAGR-002
A6: 3 | B6: Ludhiana–Bathinda Package II | C6: Follow-up with NHAI done? (Y/N) | D6: Y/N | I6: =IF(AND(ISNUMBER(G6),ISNUMBER(H6)),H6-G6,"") | J6: =IF(AND(ISNUMBER(E6),E6>0,ISNUMBER(H6)),H6/E6,"") | K6: In Progress | L6: =IF(M6="Yes","🔴 BOTTOM",IF(M6="No","✓ Cleared",IF(Q6="MIN",IF(AND(ISNUMBER(F6),ISNUMBER(H6)),IF(H6<F6*'Master Dashboard'!$B$4,"🔴 LOW",""),""),IF(Q6="MAX",IF(AND(ISNUMBER(F6),ISNUMBER(H6)),IF(H6>F6,"🔴 HIGH",""),""),"")))) | M6: Auto | R6: JAGR-003
A7: 4 | B7: MLA Jagraon Works — 9 Items | C7: Works completed | D7: works | E7: 9 | F7: 9 | H7: 1 | I7: =IF(AND(ISNUMBER(G7),ISNUMBER(H7)),H7-G7,"") | J7: =IF(AND(ISNUMBER(E7),E7>0,ISNUMBER(H7)),H7/E7,"") -> 0.11111111 | K7: In Progress | L7: =IF(M7="Yes","🔴 BOTTOM",IF(M7="No","✓ Cleared",IF(Q7="MIN",IF(AND(ISNUMBER(F7),ISNUMBER(H7)),IF(H7<F7*'Master Dashboard'!$B$4,"🔴 LOW",""),""),IF(Q7="MAX",IF(AND(ISNUMBER(F7),ISNUMBER(H7)),IF(H7>F7,"🔴 HIGH",""),""),"")))) -> 🔴 LOW | M7: Auto | N7: Gov Cell (report) | O7: 05-06-2026 | P7: Bhundri done; Raikot Rd & Kacha Malak done too | Q7: MIN | R7: JAGR-004
C8: Bridge Bardeke–Gagra (Rs664L) — Finance sanction? (Y/N) | D8: Y/N | I8: =IF(AND(ISNUMBER(G8),ISNUMBER(H8)),H8-G8,"") | J8: =IF(AND(ISNUMBER(E8),E8>0,ISNUMBER(H8)),H8/E8,"") | K8: Pending/Blocked | L8: =IF(M8="Yes","🔴 BOTTOM",IF(M8="No","✓ Cleared",IF(Q8="MIN",IF(AND(ISNUMBER(F8),ISNUMBER(H8)),IF(H8<F8*'Master Dashboard'!$B$4,"🔴 LOW",""),""),IF(Q8="MAX",IF(AND(ISNUMBER(F8),ISNUMBER(H8)),IF(H8>F8,"🔴 HIGH",""),""),"")))) | M8: Auto | P8: Special Assistance Scheme | R8: JAGR-005
C9: Waterlogging Kamal Chowk (Rs10.64Cr) — PMIDC funds? (Y/N) | D9: Y/N | I9: =IF(AND(ISNUMBER(G9),ISNUMBER(H9)),H9-G9,"") | J9: =IF(AND(ISNUMBER(E9),E9>0,ISNUMBER(H9)),H9/E9,"") | K9: Pending/Blocked | L9: =IF(M9="Yes","🔴 BOTTOM",IF(M9="No","✓ Cleared",IF(Q9="MIN",IF(AND(ISNUMBER(F9),ISNUMBER(H9)),IF(H9<F9*'Master Dashboard'!$B$4,"🔴 LOW",""),""),IF(Q9="MAX",IF(AND(ISNUMBER(F9),ISNUMBER(H9)),IF(H9>F9,"🔴 HIGH",""),""),"")))) | M9: Auto | P9: Pending at CEO PMIDC | R9: JAGR-006

Sheet SDM Payal
A1: SDM Payal — Priority Agenda Review | DC Ludhiana (MASTER)
A2: Sr | B2: Priority Agenda | C2: KPI / Metric | D2: Concerned Officer / Unit | E2: Target / Total | F2: Flag Bar | G2: Last Value | H2: Current Value | I2: Change | J2: Achieved % | K2: Status | L2: Auto-Flag | M2: Bottom Performer | N2: Updated By | O2: Update Date | P2: Remarks / Context / Pending Action | Q2: Rule | R2: Key
A3: ▣ PRIORITY TASKS — qualitative / assigned tasks
A4: 1 | B4: Court — Rajgarh / Medical College | C4: Medical College land (acres) | D4: acres | H4: 12.74 | I4: =IF(AND(ISNUMBER(G4),ISNUMBER(H4)),H4-G4,"") | J4: =IF(AND(ISNUMBER(E4),E4>0,ISNUMBER(H4)),H4/E4,"") | K4: In Progress | L4: =IF(M4="Yes","🔴 BOTTOM",IF(M4="No","✓ Cleared",IF(Q4="MIN",IF(AND(ISNUMBER(F4),ISNUMBER(H4)),IF(H4<F4*'Master Dashboard'!$B$4,"🔴 LOW",""),""),IF(Q4="MAX",IF(AND(ISNUMBER(F4),ISNUMBER(H4)),IF(H4>F4,"🔴 HIGH",""),""),"")))) | M4: Auto | N4: Gov Cell (report) | O4: 05-06-2026 | P4: Mutation done; proposal to DC; State surplus land route | R4: PAYL-001
C5: Rajgarh — placed before FCR Sahib? (Y/N) | D5: Y/N | I5: =IF(AND(ISNUMBER(G5),ISNUMBER(H5)),H5-G5,"") | J5: =IF(AND(ISNUMBER(E5),E5>0,ISNUMBER(H5)),H5/E5,"") | K5: In Progress | L5: =IF(M5="Yes","🔴 BOTTOM",IF(M5="No","✓ Cleared",IF(Q5="MIN",IF(AND(ISNUMBER(F5),ISNUMBER(H5)),IF(H5<F5*'Master Dashboard'!$B$4,"🔴 LOW",""),""),IF(Q5="MAX",IF(AND(ISNUMBER(F5),ISNUMBER(H5)),IF(H5>F5,"🔴 HIGH",""),""),"")))) | M5: Auto | P5: Nothing pending at SDM end | R5: PAYL-002
A6: 2 | B6: Doraha Cycle Track | C6: Estimate value (Rs Cr) | D6: Rs Cr | H6: 10 | I6: =IF(AND(ISNUMBER(G6),ISNUMBER(H6)),H6-G6,"") | J6: =IF(AND(ISNUMBER(E6),E6>0,ISNUMBER(H6)),H6/E6,"") | K6: In Progress | L6: =IF(M6="Yes","🔴 BOTTOM",IF(M6="No","✓ Cleared",IF(Q6="MIN",IF(AND(ISNUMBER(F6),ISNUMBER(H6)),IF(H6<F6*'Master Dashboard'!$B$4,"🔴 LOW",""),""),IF(Q6="MAX",IF(AND(ISNUMBER(F6),ISNUMBER(H6)),IF(H6>F6,"🔴 HIGH",""),""),"")))) | M6: Auto | N6: Gov Cell (report) | O6: 05-06-2026 | P6: 12 km; XEN Canal Sangrur; final estimate for vetting | R6: PAYL-003
A7: 3 | B7: Maloud — CSR to DMF | C7: CSR estimate (Rs16L) converted to DMF? (Y/N) | D7: Y/N | I7: =IF(AND(ISNUMBER(G7),ISNUMBER(H7)),H7-G7,"") | J7: =IF(AND(ISNUMBER(E7),E7>0,ISNUMBER(H7)),H7/E7,"") | K7: Pending/Blocked | L7: =IF(M7="Yes","🔴 BOTTOM",IF(M7="No","✓ Cleared",IF(Q7="MIN",IF(AND(ISNUMBER(F7),ISNUMBER(H7)),IF(H7<F7*'Master Dashboard'!$B$4,"🔴 LOW",""),""),IF(Q7="MAX",IF(AND(ISNUMBER(F7),ISNUMBER(H7)),IF(H7>F7,"🔴 HIGH",""),""),"")))) | M7: Auto | P7: Letter under consideration from DC | R7: PAYL-004
A8: 4 | B8: Rangla Punjab — Maloud & Doraha | C8: Block Maloud proposals submitted (Rs Cr) | D8: Rs Cr | H8: 1.25 | I8: =IF(AND(ISNUMBER(G8),ISNUMBER(H8)),H8-G8,"") | J8: =IF(AND(ISNUMBER(E8),E8>0,ISNUMBER(H8)),H8/E8,"") | K8: In Progress | L8: =IF(M8="Yes","🔴 BOTTOM",IF(M8="No","✓ Cleared",IF(Q8="MIN",IF(AND(ISNUMBER(F8),ISNUMBER(H8)),IF(H8<F8*'Master Dashboard'!$B$4,"🔴 LOW",""),""),IF(Q8="MAX",IF(AND(ISNUMBER(F8),ISNUMBER(H8)),IF(H8>F8,"🔴 HIGH",""),""),"")))) | M8: Auto | N8: Gov Cell (report) | O8: 05-06-2026 | P8: Submitted to ADC RD | R8: PAYL-005
C9: Block Doraha — works completed | D9: works | E9: 17 | F9: 17 | H9: 10 | I9: =IF(AND(ISNUMBER(G9),ISNUMBER(H9)),H9-G9,"") | J9: =IF(AND(ISNUMBER(E9),E9>0,ISNUMBER(H9)),H9/E9,"") -> 0.58823529 | K9: In Progress | L9: =IF(M9="Yes","🔴 BOTTOM",IF(M9="No","✓ Cleared",IF(Q9="MIN",IF(AND(ISNUMBER(F9),ISNUMBER(H9)),IF(H9<F9*'Master Dashboard'!$B$4,"🔴 LOW",""),""),IF(Q9="MAX",IF(AND(ISNUMBER(F9),ISNUMBER(H9)),IF(H9>F9,"🔴 HIGH",""),""),"")))) -> 🔴 LOW | M9: Auto | N9: Gov Cell (report) | O9: 05-06-2026 | P9: 7 ongoing; completion by Jun 2026 | Q9: MIN | R9: PAYL-006

Sheet SDM East
A1: SDM East — Priority Agenda Review | DC Ludhiana (MASTER)
A2: Sr | B2: Priority Agenda | C2: KPI / Metric | D2: Concerned Officer / Unit | E2: Target / Total | F2: Flag Bar | G2: Last Value | H2: Current Value | I2: Change | J2: Achieved % | K2: Status | L2: Auto-Flag | M2: Bottom Performer | N2: Updated By | O2: Update Date | P2: Remarks / Context / Pending Action | Q2: Rule | R2: Key
A3: ▣ PRIORITY TASKS — qualitative / assigned tasks
A4: 1 | B4: Flood — Certificates from XENs | C4: Desilting completion certificate (XEN Drainage)? (Y/N) | D4: Y/N | I4: =IF(AND(ISNUMBER(G4),ISNUMBER(H4)),H4-G4,"") | J4: =IF(AND(ISNUMBER(E4),E4>0,ISNUMBER(H4)),H4/E4,"") | K4: Pending/Blocked | L4: =IF(M4="Yes","🔴 BOTTOM",IF(M4="No","✓ Cleared",IF(Q4="MIN",IF(AND(ISNUMBER(F4),ISNUMBER(H4)),IF(H4<F4*'Master Dashboard'!$B$4,"🔴 LOW",""),""),IF(Q4="MAX",IF(AND(ISNUMBER(F4),ISNUMBER(H4)),IF(H4>F4,"🔴 HIGH",""),""),"")))) | M4: Auto | P4: Certificates pending; DSI from XEN Mining too | R4: EAST-001
A5: 2 | B5: Sherpur Chowk | C5: ROW + MC pipeline (Dholewal) resolved? (Y/N) | D5: Y/N | I5: =IF(AND(ISNUMBER(G5),ISNUMBER(H5)),H5-G5,"") | J5: =IF(AND(ISNUMBER(E5),E5>0,ISNUMBER(H5)),H5/E5,"") | K5: Pending/Blocked | L5: =IF(M5="Yes","🔴 BOTTOM",IF(M5="No","✓ Cleared",IF(Q5="MIN",IF(AND(ISNUMBER(F5),ISNUMBER(H5)),IF(H5<F5*'Master Dashboard'!$B$4,"🔴 LOW",""),""),IF(Q5="MAX",IF(AND(ISNUMBER(F5),ISNUMBER(H5)),IF(H5>F5,"🔴 HIGH",""),""),"")))) | M5: Auto | P5: Consultant being hired by MCL | R5: EAST-002
A6: 3 | B6: Giaspura to Sherpur — New Drain | C6: DPR submitted / work started? (Y/N) | D6: Y/N | I6: =IF(AND(ISNUMBER(G6),ISNUMBER(H6)),H6-G6,"") | J6: =IF(AND(ISNUMBER(E6),E6>0,ISNUMBER(H6)),H6/E6,"") | K6: Pending/Blocked | L6: =IF(M6="Yes","🔴 BOTTOM",IF(M6="No","✓ Cleared",IF(Q6="MIN",IF(AND(ISNUMBER(F6),ISNUMBER(H6)),IF(H6<F6*'Master Dashboard'!$B$4,"🔴 LOW",""),""),IF(Q6="MAX",IF(AND(ISNUMBER(F6),ISNUMBER(H6)),IF(H6>F6,"🔴 HIGH",""),""),"")))) | M6: Auto | R6: EAST-003
A7: 4 | B7: Ladhowal DPR — Railway UnderBridge | C7: Designer certificate submitted? (Y/N) | D7: Y/N | I7: =IF(AND(ISNUMBER(G7),ISNUMBER(H7)),H7-G7,"") | J7: =IF(AND(ISNUMBER(E7),E7>0,ISNUMBER(H7)),H7/E7,"") | K7: Pending/Blocked | L7: =IF(M7="Yes","🔴 BOTTOM",IF(M7="No","✓ Cleared",IF(Q7="MIN",IF(AND(ISNUMBER(F7),ISNUMBER(H7)),IF(H7<F7*'Master Dashboard'!$B$4,"🔴 LOW",""),""),IF(Q7="MAX",IF(AND(ISNUMBER(F7),ISNUMBER(H7)),IF(H7>F7,"🔴 HIGH",""),""),"")))) | M7: Auto | R7: EAST-004
A8: 5 | B8: MCL Sewer Line | C8: Permission from competent authority? (Y/N) | D8: Y/N | I8: =IF(AND(ISNUMBER(G8),ISNUMBER(H8)),H8-G8,"") | J8: =IF(AND(ISNUMBER(E8),E8>0,ISNUMBER(H8)),H8/E8,"") | K8: Pending/Blocked | L8: =IF(M8="Yes","🔴 BOTTOM",IF(M8="No","✓ Cleared",IF(Q8="MIN",IF(AND(ISNUMBER(F8),ISNUMBER(H8)),IF(H8<F8*'Master Dashboard'!$B$4,"🔴 LOW",""),""),IF(Q8="MAX",IF(AND(ISNUMBER(F8),ISNUMBER(H8)),IF(H8>F8,"🔴 HIGH",""),""),"")))) | M8: Auto | P8: Proposal pending with RO NHAI | R8: EAST-005
A9: 6 | B9: Service Road Encroachment | C9: Action on encroachment taken? (Y/N) | D9: Y/N | I9: =IF(AND(ISNUMBER(G9),ISNUMBER(H9)),H9-G9,"") | J9: =IF(AND(ISNUMBER(E9),E9>0,ISNUMBER(H9)),H9/E9,"") | K9: In Progress | L9: =IF(M9="Yes","🔴 BOTTOM",IF(M9="No","✓ Cleared",IF(Q9="MIN",IF(AND(ISNUMBER(F9),ISNUMBER(H9)),IF(H9<F9*'Master Dashboard'!$B$4,"🔴 LOW",""),""),IF(Q9="MAX",IF(AND(ISNUMBER(F9),ISNUMBER(H9)),IF(H9>F9,"🔴 HIGH",""),""),"")))) | M9: Auto | P9: Notice issued; copy from Akshat NH | R9: EAST-006
A10: 7 | B10: Gehlewal School Transfer | C10: Police help for demarcation provided? (Y/N) | D10: Y/N | I10: =IF(AND(ISNUMBER(G10),ISNUMBER(H10)),H10-G10,"") | J10: =IF(AND(ISNUMBER(E10),E10>0,ISNUMBER(H10)),H10/E10,"") | K10: Pending/Blocked | L10: =IF(M10="Yes","🔴 BOTTOM",IF(M10="No","✓ Cleared",IF(Q10="MIN",IF(AND(ISNUMBER(F10),ISNUMBER(H10)),IF(H10<F10*'Master Dashboard'!$B$4,"🔴 LOW",""),""),IF(Q10="MAX",IF(AND(ISNUMBER(F10),ISNUMBER(H10)),IF(H10>F10,"🔴 HIGH",""),""),"")))) | M10: Auto | P10: Opposition from villagers; DEO letter to SDM East | R10: EAST-007
A11: 8 | B11: BL Kapoor Hospital | C11: Court case — next hearing date | D11: date | H11: 15.05.2026 | I11: =IF(AND(ISNUMBER(G11),ISNUMBER(H11)),H11-G11,"") | J11: =IF(AND(ISNUMBER(E11),E11>0,ISNUMBER(H11)),H11/E11,"") | K11: In Progress | L11: =IF(M11="Yes","🔴 BOTTOM",IF(M11="No","✓ Cleared",IF(Q11="MIN",IF(AND(ISNUMBER(F11),ISNUMBER(H11)),IF(H11<F11*'Master Dashboard'!$B$4,"🔴 LOW",""),""),IF(Q11="MAX",IF(AND(ISNUMBER(F11),ISNUMBER(H11)),IF(H11>F11,"🔴 HIGH",""),""),"")))) | M11: Auto | N11: Gov Cell (report) | O11: 05-06-2026 | P11: Rebuttal | R11: EAST-008
A12: 9 | B12: Jail Visit & Land Possession | C12: Jail visit done / possession completed? (Y/N) | D12: Y/N | I12: =IF(AND(ISNUMBER(G12),ISNUMBER(H12)),H12-G12,"") | J12: =IF(AND(ISNUMBER(E12),E12>0,ISNUMBER(H12)),H12/E12,"") | K12: In Progress | L12: =IF(M12="Yes","🔴 BOTTOM",IF(M12="No","✓ Cleared",IF(Q12="MIN",IF(AND(ISNUMBER(F12),ISNUMBER(H12)),IF(H12<F12*'Master Dashboard'!$B$4,"🔴 LOW",""),""),IF(Q12="MAX",IF(AND(ISNUMBER(F12),ISNUMBER(H12)),IF(H12>F12,"🔴 HIGH",""),""),"")))) | M12: Auto | P12: Visit done as per demand | R12: EAST-009

Sheet SDM West
A1: SDM West — Priority Agenda Review | DC Ludhiana (MASTER)
A2: Sr | B2: Priority Agenda | C2: KPI / Metric | D2: Concerned Officer / Unit | E2: Target / Total | F2: Flag Bar | G2: Last Value | H2: Current Value | I2: Change | J2: Achieved % | K2: Status | L2: Auto-Flag | M2: Bottom Performer | N2: Updated By | O2: Update Date | P2: Remarks / Context / Pending Action | Q2: Rule | R2: Key
A3: ▣ PRIORITY TASKS — qualitative / assigned tasks
A4: 1 | B4: Southern Bypass — NHAI Matters | C4: SDM West land issues — villages pending | D4: villages | E4: 0 | F4: 0 | H4: 16 | I4: =IF(AND(ISNUMBER(G4),ISNUMBER(H4)),H4-G4,"") | J4: =IF(AND(ISNUMBER(E4),E4>0,ISNUMBER(H4)),H4/E4,"") | K4: Pending/Blocked | L4: =IF(M4="Yes","🔴 BOTTOM",IF(M4="No","✓ Cleared",IF(Q4="MIN",IF(AND(ISNUMBER(F4),ISNUMBER(H4)),IF(H4<F4*'Master Dashboard'!$B$4,"🔴 LOW",""),""),IF(Q4="MAX",IF(AND(ISNUMBER(F4),ISNUMBER(H4)),IF(H4>F4,"🔴 HIGH",""),""),"")))) -> 🔴 HIGH | M4: Auto | N4: Gov Cell (report) | O4: 05-06-2026 | P4: Coordination with CMFO/DRO | Q4: MAX | R4: WEST-001
A5: 2 | B5: NHAI Delhi–Katra | C5: Gujjarwal — land award pending (ha) | D5: ha | E5: 0 | F5: 0 | H5: 0.2546 | I5: =IF(AND(ISNUMBER(G5),ISNUMBER(H5)),H5-G5,"") | J5: =IF(AND(ISNUMBER(E5),E5>0,ISNUMBER(H5)),H5/E5,"") | K5: Pending/Blocked | L5: =IF(M5="Yes","🔴 BOTTOM",IF(M5="No","✓ Cleared",IF(Q5="MIN",IF(AND(ISNUMBER(F5),ISNUMBER(H5)),IF(H5<F5*'Master Dashboard'!$B$4,"🔴 LOW",""),""),IF(Q5="MAX",IF(AND(ISNUMBER(F5),ISNUMBER(H5)),IF(H5>F5,"🔴 HIGH",""),""),"")))) -> 🔴 HIGH | M5: Auto | N5: Gov Cell (report) | O5: 05-06-2026 | P5: To be done next week | Q5: MAX | R5: WEST-002
C6: Dakha 8.25 acres — award done (ha) | D6: ha | E6: 3.34 | F6: 3.34 | H6: 1.413 | I6: =IF(AND(ISNUMBER(G6),ISNUMBER(H6)),H6-G6,"") | J6: =IF(AND(ISNUMBER(E6),E6>0,ISNUMBER(H6)),H6/E6,"") -> 0.42305389 | K6: In Progress | L6: =IF(M6="Yes","🔴 BOTTOM",IF(M6="No","✓ Cleared",IF(Q6="MIN",IF(AND(ISNUMBER(F6),ISNUMBER(H6)),IF(H6<F6*'Master Dashboard'!$B$4,"🔴 LOW",""),""),IF(Q6="MAX",IF(AND(ISNUMBER(F6),ISNUMBER(H6)),IF(H6>F6,"🔴 HIGH",""),""),"")))) -> 🔴 LOW | M6: Auto | N6: Gov Cell (report) | O6: 05-06-2026 | P6: 3.491 acre done, sent to PD | Q6: MIN | R6: WEST-003
C7: Tubewell + Motor compensation — awarded? (Y/N) | D7: Y/N | I7: =IF(AND(ISNUMBER(G7),ISNUMBER(H7)),H7-G7,"") | J7: =IF(AND(ISNUMBER(E7),E7>0,ISNUMBER(H7)),H7/E7,"") | K7: In Progress | L7: =IF(M7="Yes","🔴 BOTTOM",IF(M7="No","✓ Cleared",IF(Q7="MIN",IF(AND(ISNUMBER(F7),ISNUMBER(H7)),IF(H7<F7*'Master Dashboard'!$B$4,"🔴 LOW",""),""),IF(Q7="MAX",IF(AND(ISNUMBER(F7),ISNUMBER(H7)),IF(H7>F7,"🔴 HIGH",""),""),"")))) | M7: Auto | P7: Asset award done this week | R7: WEST-004
C8: Missing Khasra (Dakha) resolved? (Y/N) | D8: Y/N | I8: =IF(AND(ISNUMBER(G8),ISNUMBER(H8)),H8-G8,"") | J8: =IF(AND(ISNUMBER(E8),E8>0,ISNUMBER(H8)),H8/E8,"") | K8: Pending/Blocked | L8: =IF(M8="Yes","🔴 BOTTOM",IF(M8="No","✓ Cleared",IF(Q8="MIN",IF(AND(ISNUMBER(F8),ISNUMBER(H8)),IF(H8<F8*'Master Dashboard'!$B$4,"🔴 LOW",""),""),IF(Q8="MAX",IF(AND(ISNUMBER(F8),ISNUMBER(H8)),IF(H8>F8,"🔴 HIGH",""),""),"")))) | M8: Auto | P8: From 11 May | R8: WEST-005
